Workbook
Name AU_faculty_dep: AU_deps[#Headers]
Name BenchFeeFoundation: AU!$H$10
Name BenchFeePartner1: AU!$I$120
Name CoFinVIPCat: Lists!$N$34:$N$45
Name DateFormat: AU!$D$10
Name Dep_list: INDEX(AU_deps[],,MATCH(Faculty_AU,AU_faculty_dep,0))
Name DepPartner1: AU!$D$7
Name endDate: AU!$D$9
Name ExtrapolationFactorPartner1: IF(AND(DateFormat="Project years",AU!$F$12<>""),AU!$F$12,AU!$H$1)
Name Faculty_AU: AU!$D$6
Name FacultyPartner1: AU!$D$6
Name Foundation: AU!$D$12
Name Foundationdropdown: Lists!$W$2:$W$15
Name IfDay: IF(DATEDIF(startDate,endDate,"md")=1," day"," days")
Name IfMonth: IF(DATEDIF(startDate,endDate,"ym")=1," month"," months")
Name IfYear: IF(DATEDIF(startDate,endDate,"y")=1," year"," years")
Name Institutiondropdown: Lists!$A$2:$A$10
Name InstitutionPartner1: AU!$D$5
Name Nat_AU_deps: Lists!$C$36:$C$43
Name NNFDisseminationCosts: Lists!$Q$23:$Q$26
Name NNFOperationCosts: Lists!$Q$17:$Q$20
Name OHFoundation: Lists!$X$2:$X$15
Name OHPctCoFinancePartner1: AU!$F$163
Name OHPctPartner1: AU!$D$13
Name OHTerm: Lists!$Y$2:$Y$15
Name PhD_navn: Lists!$N$10
Name PLPartner1: AU!$D$11
Name Project_supplement_foundations: Lists!$W$18:$W$26
Name Project_supplement_institutions: Lists!$A$2:$A$9
Name ProjectCosts: Lists!$Q$2:$Q$13
Name ProjectSupplementPartner1: AU!$H$6
Name SalaryYearPartner1: AU!$H$2
Name SciAreaPartner1: AU!$D$6
Name startDate: AU!$D$8
Name TAPCat: Lists!$N$21:$N$31
Name TuitionFeePartner1: AU!$H$8
Name VIPCat: Lists!$N$2:$N$17

Sheet Guide
B1: Getting started with the "NNF Budget template"
B2: • | C2: Fill in the yellow fields - see an example in the picture to the right. (Only the yellow fields can be edited, the rest are protected).
B3: • | C3: Whenever you see an info-icon, like the one to the right, you can hover the mouse over the icon and read a guiding text.
B5: • | C5: If you need to budget more than 6 project years, press the "plus sign" in the very top of the budget template - see picture to the right. (The template by default starts with only 6 budget years visible).
B12: • | C12: If you have filled in all of the visible budget rows in the template, more rows can be accessed by pressing the "plus sign" in the left side.
B16: Guide
B17: • | C17: Remember to fill in all master data regarding the project. All projects must have a start and end date (awards can in a few cases be exempted from this). | H17: For NORMA - this tab you can use for a more to copy/paste-friendly layout of your final and approved budget when you have to enter it into the official NNF application system, Norma. Always ensure the final budget numbers you enter into NORMA are correct and correspond to the ones from the approved budget.
B18: • | C18: Wage estimates for personnel: For each employment category selected, the template will by default show the average AU salary for that position, if one is available (see tab "AU salary costs 2025"). You can overwrite this. You should strive to use the actual salary costs where possible for named, already employed persons.
B19: • | C19: Project supplement: After intensive work between private Danish foundations (Lundbeck, Novo, Leo, Velux, Villum and Carlsberg) and the collected Universities in Denmark, there has been an agreement regarding bigger contributions to the Universities' costs of having an external contribution. These project supplements are given based on specific personnel categories and are in the template calculated automatically for the foundations that have agreed to this support. The support for STEM fields is 250.000 DKK per 12 months, full time employed (FTE) postdoc, PhD or Scientific Assistant. It does involve a few additional personnel categories - the so called VIP group C - which can be selected as well. The calculation in the template adds the amount to the collected requested budget and will adjust for partial FTE. For instance, half a PhD for year one will be automatically calculated to 125.000 DKK if it is for one of the metioned foundations, making it easier to add these fixed costs to your budget. See the official guidelines for further explanation of project supplement.
C20: Link to agreement (Danish): Aftale med fonde om finansiering af forskningsprojekter - Danske Universiteter
C21: Link to agreement (English): eng_aftaletekst_endelig_final.pdf
C22: Link to Danish guide to project supplement (Ver 3): https://dkuni.dk/wp-content/uploads/2025/12/vejledning-projekttillaeg-version-3.pdf
C23: Link to English guide to project supplement (Ver 3): https://dkuni.dk/wp-content/uploads/2025/12/guidelines-for-project-supplement_final_version-3.pdf
B24: • | C24: Project overhead (OH) or Indirect costs/Administrative support is automatically calculated in the budget template, as the product of the entered overhead percentage (if any) and the sum of all the costs.
B25: • | C25: Project costs: Can be entered applied in the section section entitled 'Project costs'. There is attributed a general categorization of the consumables, but otherwise we advise that the notes are used to futher subcategorize the consumables in the degree that it is necessary.
B26: • | C26: Purchase of departmental services (in danish: "Inddækning") This can include hiring of technicians or use of infrastructure specifically for the project - services that are available at your department the costs of which need to be covered by the project. Ask your department which items counts towards this in your budget.
B27: • | C27: Co-financing is where the University (your department) is funding costs directly related to the project. Ask your department regarding this category. All co-financing has to be cleared by your department before applying.
B29: FAQ
C30: Frequently asked question | D30: Answer
B31: • | C31: Will be filled out continuously
B32: •
B33: •
B34: •
B35: •
B36: •
B37: •
B38: •
B39: •
B40: •
B41: •

Sheet AU
G1: Extrapolation factor (default): | H1: =IFERROR(IF(AND(DateFormat="Project years",MONTH($L$1)>6),((YEAR($L$1)+1)-YEAR(SalaryYearPartner1)),(YEAR($L$2)-YEAR(SalaryYearPartner1))),1) -> 2 | K1: Dates Project years | L1: {=IF(startDate="",e,startDate)} -> 46296 | N1: =IF(L1<endDate,MIN(EDATE(L1,12)-1,endDate),"") -> 46660 | O1: =IF(N1<endDate,N1+1,"") -> 46661 | Q1: =IF(O1<endDate,MIN(EDATE(O1,12)-1,endDate),"") -> 47026 | R1: =IF(Q1<endDate,Q1+1,"") -> 47027 | T1: =IF(R1<endDate,MIN(EDATE(R1,12)-1,endDate),"") -> 47391 | U1: =IF(T1<endDate,T1+1,"") -> 47392 | W1: =IF(U1<endDate,MIN(EDATE(U1,12)-1,endDate),"") -> 47756 | X1: =IF(W1<endDate,W1+1,"") -> 47757 | Z1: =IF(X1<endDate,MIN(EDATE(X1,12)-1,endDate),"") -> 48121 | AA1: =IF(Z1<endDate,Z1+1,"") -> 48122 | AC1: =IF(AA1<endDate,MIN(EDATE(AA1,12)-1,endDate),"") -> 48487 | AD1: =IF(AC1<endDate,AC1+1,"") | AF1: =IF(AD1<endDate,MIN(EDATE(AD1,12)-1,endDate),"") | AG1: =IF(AF1<endDate,AF1+1,"") | AI1: =IF(AG1<endDate,MIN(EDATE(AG1,12)-1,endDate),"") | AJ1: =IF(AI1<endDate,AI1+1,"") | AL1: =IF(AJ1<endDate,MIN(EDATE(AJ1,12)-1,endDate),"") | AM1: =IF(AL1<endDate,AL1+1,"") | AO1: =IF(AM1<endDate,MIN(EDATE(AM1,12)-1,endDate),"")
G2: Salary year: | H2: 45658 | K2: Dates Calendar years | L2: {=IF(startDate="",e,startDate)} -> 46296 | N2: =IF(L2<endDate,MIN(endDate,DATE(YEAR(L2),12,31)),"") -> 46387 | O2: =IF(N2<endDate,N2+1,"") -> 46388 | Q2: =IF(O2<endDate,MIN(endDate,DATE(YEAR(O2),12,31)),"") -> 46752 | R2: =IF(Q2<endDate,Q2+1,"") -> 46753 | T2: =IF(R2<endDate,MIN(endDate,DATE(YEAR(R2),12,31)),"") -> 47118 | U2: =IF(T2<endDate,T2+1,"") -> 47119 | W2: =IF(U2<endDate,MIN(endDate,DATE(YEAR(U2),12,31)),"") -> 47483 | X2: =IF(W2<endDate,W2+1,"") -> 47484 | Z2: =IF(X2<endDate,MIN(endDate,DATE(YEAR(X2),12,31)),"") -> 47848 | AA2: =IF(Z2<endDate,Z2+1,"") -> 47849 | AC2: =IF(AA2<endDate,MIN(endDate,DATE(YEAR(AA2),12,31)),"") -> 48213 | AD2: =IF(AC2<endDate,AC2+1,"") -> 48214 | AF2: =IF(AD2<endDate,MIN(endDate,DATE(YEAR(AD2),12,31)),"") -> 48487 | AG2: =IF(AF2<endDate,AF2+1,"") | AI2: =IF(AG2<endDate,MIN(endDate,DATE(YEAR(AG2),12,31)),"") | AJ2: =IF(AI2<endDate,AI2+1,"") | AL2: =IF(AJ2<endDate,MIN(endDate,DATE(YEAR(AJ2),12,31)),"") | AM2: =IF(AL2<endDate,AL2+1,"") | AO2: =IF(AM2<endDate,MIN(endDate,DATE(YEAR(AM2),12,31)),"")
K3: Year number | N3: =ExtrapolationFactorPartner1 -> 2 | Q3: =ExtrapolationFactorPartner1+1 -> 3 | T3: =ExtrapolationFactorPartner1+2 -> 4 | W3: =ExtrapolationFactorPartner1+3 -> 5 | Z3: =ExtrapolationFactorPartner1+4 -> 6 | AC3: =ExtrapolationFactorPartner1+5 -> 7 | AF3: =ExtrapolationFactorPartner1+6 -> 8 | AI3: =ExtrapolationFactorPartner1+7 -> 9 | AL3: =ExtrapolationFactorPartner1+8 -> 10 | AO3: =ExtrapolationFactorPartner1+9 -> 11
B4: Template version: 08-01-2026 | J4: NNF NERD template
B5: Institution | D5: AU | J5: Link to call: | K5: New Exploratory Research and Discovery (NERD) Programme 2026 - Novo Nordisk Fonden
B6: =IFERROR(IF(InstitutionPartner1="AU","Faculty","Scientific Area"),"Faculty") -> Faculty | D6: Natural Sciences | G6: Project supplement: | H6: =IF(InstitutionPartner1="AU",_xlfn.XLOOKUP(FacultyPartner1,Lists!C:C,Lists!E:E),_xlfn.XLOOKUP(SciAreaPartner1,Lists!C:C,Lists!E:E)) -> 250000
B7: Department | D7: MBG
B8: Project start date | D8: 46296 | F8: Tuition fee/year/PhD: | G8: Tuition fee: | H8: =IF(AND(InstitutionPartner1="AU",$F$9=0,Foundation<>"DFF"),_xlfn.XLOOKUP(FacultyPartner1,Lists!C:C,Lists!F:F),IF(AND(InstitutionPartner1="AU",$F$9=0,Foundation="DFF"),_xlfn.XLOOKUP(FacultyPartner1,Lists!C:C,Lists!G:G),$F$9)) -> 80000 | J8: Earliest start: 1 August 2026
B9: Project end date | D9: 48487 | F9: =IF(AND(InstitutionPartner1="AU",Foundation<>"DFF"),_xlfn.XLOOKUP(FacultyPartner1,Lists!C:C,Lists!F:F),IF(AND(InstitutionPartner1="AU",Foundation="DFF"),_xlfn.XLOOKUP(FacultyPartner1,Lists!C:C,Lists!G:G),"")) -> 80000 | J9: Latest start: 1 February 2027
B10: Date format | D10: Project years | G10: Bench fee | H10: =IFERROR(IF(_xlfn.XLOOKUP(Foundation,Foundationdropdown,Lists!Z2:Z15)=0,$F$183,_xlfn.XLOOKUP(Foundation,Foundationdropdown,Lists!Z2:Z15)),"") -> 8000
B11: Salary yearly extrapolation | D11: 0.03 | F11: Extrapolation 1st year: | J11: Amount: | K11: Up to DKK 16 million
B12: Foundation | D12: Novo Nordisk | F12: =IFERROR(IF(AND(DateFormat="Project years",MONTH($L$1)>6),((YEAR($L$1)+1)-YEAR(SalaryYearPartner1)),(YEAR($L$2)-YEAR(SalaryYearPartner1))),1) -> 2 | J12: Duration: | K12: 6 years (min. 5)
B13: =_xlfn.XLOOKUP(Foundation,Foundationdropdown,OHTerm,"Overhead percentage") -> Administrative expenses | D13: =_xlfn.XLOOKUP(Foundation,Foundationdropdown,OHFoundation,"") -> 0
G14: skjul | H14: skjul
C15: Project title: | K15: =IFERROR("Project length: "& ROUND(ABS(YEARFRAC(startDate,EOMONTH(startDate,12-MONTH(startDate)),1)+YEAR(endDate)-YEAR(startDate)-1+YEARFRAC(endDate,EOMONTH(endDate,-MONTH(endDate)),1)),2) & " years","") -> Project length: 6 years | L15: =IFERROR(IF(DateFormat="Calendar years",L2,"Year 1"),"20XX") -> Year 1 | O15: =IFERROR(IF(DateFormat="Calendar years",O2,"Year 2"),"20XX") -> Year 2 | R15: =IFERROR(IF(DateFormat="Calendar years",R2,"Year 3"),"20XX") -> Year 3 | U15: =IFERROR(IF(DateFormat="Calendar years",U2,"Year 4"),"20XX") -> Year 4 | X15: =IFERROR(IF(DateFormat="Calendar years",X2,"Year 5"),"20XX") -> Year 5 | AA15: =IFERROR(IF(DateFormat="Calendar years",AA2,"Year 6"),"20XX") -> Year 6 | AD15: =IFERROR(IF(DateFormat="Calendar years",AD2,"Year 7"),"20XX") -> Year 7 | AG15: =IFERROR(IF(DateFormat="Calendar years",AG2,"Year 8"),"20XX") -> Year 8 | AJ15: =IFERROR(IF(DateFormat="Calendar years",AJ2,"Year 9"),"20XX") -> Year 9 | AM15: =IFERROR(IF(DateFormat="Calendar years",AM2,"Year 10"),"20XX") -> Year 10 | AP15: TOTAL | AT15: FTE hours
L16: Start | N16: End | O16: Start | Q16: End | R16: Start | T16: End | U16: Start | W16: End | X16: Start | Z16: End | AA16: Start | AC16: End | AD16: Start | AF16: End | AG16: Start | AI16: End | AJ16: Start | AL16: End | AM16: Start | AO16: End | AP16: Start | AR16: End
L17: =IFERROR(IF(DateFormat="Project years",L1,L2),"") -> 46296 | N17: =IFERROR(IF(DateFormat="Project years",N1,N2),"") -> 46660 | O17: =IFERROR(IF(DateFormat="Project years",O1,O2),"") -> 46661 | Q17: =IFERROR(IF(DateFormat="Project years",Q1,Q2),"") -> 47026 | R17: =IFERROR(IF(DateFormat="Project years",R1,R2),"") -> 47027 | T17: =IFERROR(IF(DateFormat="Project years",T1,T2),"") -> 47391 | U17: =IFERROR(IF(DateFormat="Project years",U1,U2),"") -> 47392 | W17: =IFERROR(IF(DateFormat="Project years",W1,W2),"") -> 47756 | X17: =IFERROR(IF(DateFormat="Project years",X1,X2),"") -> 47757 | Z17: =IFERROR(IF(DateFormat="Project years",Z1,Z2),"") -> 48121 | AA17: =IFERROR(IF(DateFormat="Project years",AA1,AA2),"") -> 48122 | AC17: =IFERROR(IF(DateFormat="Project years",AC1,AC2),"") -> 48487 | AD17: =IFERROR(IF(DateFormat="Project years",AD1,AD2),"") | AF17: =IFERROR(IF(DateFormat="Project years",AF1,AF2),"") | AG17: =IFERROR(IF(DateFormat="Project years",AG1,AG2),"") | AI17: =IFERROR(IF(DateFormat="Project years",AI1,AI2),"") | AJ17: =IFERROR(IF(DateFormat="Project years",AJ1,AJ2),"") | AL17: =IFERROR(IF(DateFormat="Project years",AL1,AL2),"") | AM17: =IFERROR(IF(DateFormat="Project years",AM1,AM2),"") | AO17: =IFERROR(IF(DateFormat="Project years",AO1,AO2),"") | AP17: =IF(startDate="","",startDate) -> 46296 | AR17: =IF(endDate="","",endDate) -> 48487
B18: Salary | K18: Project months/year: | L18: =IFERROR(ROUND(IF(MONTH(L17)=MONTH(N17),((YEAR(N17)-YEAR(L17))*12)-12+(12-MONTH(L17))+MONTH(N17)-1+(EOMONTH(L17,0)-L17+1)/DAY(EOMONTH(L17,0))+(1-(EOMONTH(N17,0)-N17)/DAY(EOMONTH(N17,0))),((YEAR(N17)-YEAR(L17))*12)-12+(12-MONTH(L17))+MONTH(N17)-1+(EOMONTH(L17,0)-L17+1)/DAY(EOMONTH(L17,0))+(1-(EOMONTH(N17,0)-N17)/DAY(EOMONTH(N17,0)))),2),0) -> 12 | O18: =IFERROR(ROUND(IF(MONTH(O17)=MONTH(Q17),((YEAR(Q17)-YEAR(O17))*12)-12+(12-MONTH(O17))+MONTH(Q17)-1+(EOMONTH(O17,0)-O17+1)/DAY(EOMONTH(O17,0))+(1-(EOMONTH(Q17,0)-Q17)/DAY(EOMONTH(Q17,0))),((YEAR(Q17)-YEAR(O17))*12)-12+(12-MONTH(O17))+MONTH(Q17)-1+(EOMONTH(O17,0)-O17+1)/DAY(EOMONTH(O17,0))+(1-(EOMONTH(Q17,0)-Q17)/DAY(EOMONTH(Q17,0)))),2),0) -> 12 | R18: =IFERROR(ROUND(IF(MONTH(R17)=MONTH(T17),((YEAR(T17)-YEAR(R17))*12)-12+(12-MONTH(R17))+MONTH(T17)-1+(EOMONTH(R17,0)-R17+1)/DAY(EOMONTH(R17,0))+(1-(EOMONTH(T17,0)-T17)/DAY(EOMONTH(T17,0))),((YEAR(T17)-YEAR(R17))*12)-12+(12-MONTH(R17))+MONTH(T17)-1+(EOMONTH(R17,0)-R17+1)/DAY(EOMONTH(R17,0))+(1-(EOMONTH(T17,0)-T17)/DAY(EOMONTH(T17,0)))),2),0) -> 12 | U18: =IFERROR(ROUND(IF(MONTH(U17)=MONTH(W17),((YEAR(W17)-YEAR(U17))*12)-12+(12-MONTH(U17))+MONTH(W17)-1+(EOMONTH(U17,0)-U17+1)/DAY(EOMONTH(U17,0))+(1-(EOMONTH(W17,0)-W17)/DAY(EOMONTH(W17,0))),((YEAR(W17)-YEAR(U17))*12)-12+(12-MONTH(U17))+MONTH(W17)-1+(EOMONTH(U17,0)-U17+1)/DAY(EOMONTH(U17,0))+(1-(EOMONTH(W17,0)-W17)/DAY(EOMONTH(W17,0)))),2),0) -> 12 | X18: =IFERROR(ROUND(IF(MONTH(X17)=MONTH(Z17),((YEAR(Z17)-YEAR(X17))*12)-12+(12-MONTH(X17))+MONTH(Z17)-1+(EOMONTH(X17,0)-X17+1)/DAY(EOMONTH(X17,0))+(1-(EOMONTH(Z17,0)-Z17)/DAY(EOMONTH(Z17,0))),((YEAR(Z17)-YEAR(X17))*12)-12+(12-MONTH(X17))+MONTH(Z17)-1+(EOMONTH(X17,0)-X17+1)/DAY(EOMONTH(X17,0))+(1-(EOMONTH(Z17,0)-Z17)/DAY(EOMONTH(Z17,0)))),2),0) -> 12 | AA18: =IFERROR(ROUND(IF(MONTH(AA17)=MONTH(AC17),((YEAR(AC17)-YEAR(AA17))*12)-12+(12-MONTH(AA17))+MONTH(AC17)-1+(EOMONTH(AA17,0)-AA17+1)/DAY(EOMONTH(AA17,0))+(1-(EOMONTH(AC17,0)-AC17)/DAY(EOMONTH(AC17,0))),((YEAR(AC17)-YEAR(AA17))*12)-12+(12-MONTH(AA17))+MONTH(AC17)-1+(EOMONTH(AA17,0)-AA17+1)/DAY(EOMONTH(AA17,0))+(1-(EOMONTH(AC17,0)-AC17)/DAY(EOMONTH(AC17,0)))),2),0) -> 12 | AD18: =IFERROR(ROUND(IF(MONTH(AD17)=MONTH(AF17),((YEAR(AF17)-YEAR(AD17))*12)-12+(12-MONTH(AD17))+MONTH(AF17)-1+(EOMONTH(AD17,0)-AD17+1)/DAY(EOMONTH(AD17,0))+(1-(EOMONTH(AF17,0)-AF17)/DAY(EOMONTH(AF17,0))),((YEAR(AF17)-YEAR(AD17))*12)-12+(12-MONTH(AD17))+MONTH(AF17)-1+(EOMONTH(AD17,0)-AD17+1)/DAY(EOMONTH(AD17,0))+(1-(EOMONTH(AF17,0)-AF17)/DAY(EOMONTH(AF17,0)))),2),0) -> 0 | AG18: =IFERROR(ROUND(IF(MONTH(AG17)=MONTH(AI17),((YEAR(AI17)-YEAR(AG17))*12)-12+(12-MONTH(AG17))+MONTH(AI17)-1+(EOMONTH(AG17,0)-AG17+1)/DAY(EOMONTH(AG17,0))+(1-(EOMONTH(AI17,0)-AI17)/DAY(EOMONTH(AI17,0))),((YEAR(AI17)-YEAR(AG17))*12)-12+(12-MONTH(AG17))+MONTH(AI17)-1+(EOMONTH(AG17,0)-AG17+1)/DAY(EOMONTH(AG17,0))+(1-(EOMONTH(AI17,0)-AI17)/DAY(EOMONTH(AI17,0)))),2),0) -> 0 | AJ18: =IFERROR(ROUND(IF(MONTH(AJ17)=MONTH(AL17),((YEAR(AL17)-YEAR(AJ17))*12)-12+(12-MONTH(AJ17))+MONTH(AL17)-1+(EOMONTH(AJ17,0)-AJ17+1)/DAY(EOMONTH(AJ17,0))+(1-(EOMONTH(AL17,0)-AL17)/DAY(EOMONTH(AL17,0))),((YEAR(AL17)-YEAR(AJ17))*12)-12+(12-MONTH(AJ17))+MONTH(AL17)-1+(EOMONTH(AJ17,0)-AJ17+1)/DAY(EOMONTH(AJ17,0))+(1-(EOMONTH(AL17,0)-AL17)/DAY(EOMONTH(AL17,0)))),2),0) -> 0 | AM18: =IFERROR(ROUND(IF(MONTH(AM17)=MONTH(AO17),((YEAR(AO17)-YEAR(AM17))*12)-12+(12-MONTH(AM17))+MONTH(AO17)-1+(EOMONTH(AM17,0)-AM17+1)/DAY(EOMONTH(AM17,0))+(1-(EOMONTH(AO17,0)-AO17)/DAY(EOMONTH(AO17,0))),((YEAR(AO17)-YEAR(AM17))*12)-12+(12-MONTH(AM17))+MONTH(AO17)-1+(EOMONTH(AM17,0)-AM17+1)/DAY(EOMONTH(AM17,0))+(1-(EOMONTH(AO17,0)-AO17)/DAY(EOMONTH(AO17,0)))),2),0) -> 0 | AP18: =IFERROR(ROUND(IF(MONTH(AP17)=MONTH(AR17),((YEAR(AR17)-YEAR(AP17))*12)-12+(12-MONTH(AP17))+MONTH(AR17)-1+(EOMONTH(AP17,0)-AP17+1)/DAY(EOMONTH(AP17,0))+(1-(EOMONTH(AR17,0)-AR17)/DAY(EOMONTH(AR17,0))),((YEAR(AR17)-YEAR(AP17))*12)-12+(12-MONTH(AP17))+MONTH(AR17)-1+(EOMONTH(AP17,0)-AP17+1)/DAY(EOMONTH(AP17,0))+(1-(EOMONTH(AR17,0)-AR17)/DAY(EOMONTH(AR17,0)))),2),"") -> 72 | AT18: 1924
C19: 1. VIP | F19: Notes/Name | G19: Project supplement? | H19: Fraction | I19: Salary/mo 2025 | J19: Hrs/wk | K19: Dept.Serv. | L19: Months | M19: FTE | N19: Costs | O19: Months | P19: FTE | Q19: Costs | R19: Months | S19: FTE | T19: Costs | U19: Months | V19: FTE | W19: Costs | X19: Months | Y19: FTE | Z19: Costs | AA19: Months | AB19: FTE | AC19: Costs | AD19: Months | AE19: FTE | AF19: Costs | AG19: Months | AH19: FTE | AI19: Costs | AJ19: Months | AK19: FTE | AL19: Costs | AM19: Months | AN19: FTE | AO19: Costs | AP19: Months | AQ19: FTE | AR19: Costs | AT19: VIP hours
C20: Postdoc | G20: =_xlfn.XLOOKUP(C20,Lists!$N$3:$N$15,Lists!$O$3:$O$15,"") -> 1 | H20: =J20/37 -> 1 | I20: =_xlfn.XLOOKUP(C20,'AU salary costs 2025'!$B$7:$B$35,'AU salary costs 2025'!$D$7:$D$35, "-") -> 52000 | J20: 37 | L20: 12 | M20: =$H20*(L20/12) -> 1 | N20: =IFERROR($I20*$J20/37*(1+PLPartner1)^N$3*L20,"") -> 662001.6 | O20: 12 | P20: =$H20*(O20/12) -> 1 | Q20: =IFERROR($I20*$J20/37*(1+PLPartner1)^Q$3*O20,"") -> 681861.65 | R20: 12 | S20: =$H20*(R20/12) -> 1 | T20: =IFERROR($I20*$J20/37*(1+PLPartner1)^T$3*R20,"") -> 702317.5 | V20: =$H20*(U20/12) -> 0 | W20: =IFERROR($I20*$J20/37*(1+PLPartner1)^W$3*U20,"") -> 0 | Y20: =$H20*(X20/12) -> 0 | Z20: =IFERROR($I20*$J20/37*(1+PLPartner1)^Z$3*X20,"") -> 0 | AB20: =$H20*(AA20/12) -> 0 | AC20: =IFERROR($I20*$J20/37*(1+PLPartner1)^AC$3*AA20,"") -> 0 | AE20: =$H20*(AD20/12) -> 0 | AF20: =IFERROR($I20*$J20/37*(1+PLPartner1)^AF$3*AD20,"") -> 0 | AH20: =$H20*(AG20/12) -> 0 | AI20: =IFERROR($I20*$J20/37*(1+PLPartner1)^AI$3*AG20,"") -> 0 | AK20: =$H20*(AJ20/12) -> 0 | AL20: =IFERROR($I20*$J20/37*(1+PLPartner1)^AL$3*AJ20,"") -> 0 | AN20: =$H20*(AM20/12) -> 0 | AO20: =IFERROR($I20*$J20/37*(1+PLPartner1)^AO$3*AM20,"") -> 0 | AP20: =SUM(L20,O20,R20,U20,X20,AA20,AD20,AG20,AJ20,AM20) -> 36 | AQ20: =SUM(M20,P20,S20,V20,Y20,AB20,AE20,AH20,AK20,AN20) -> 3 | AR20: =SUM(N20,Q20,T20,W20,Z20,AC20,AF20,AI20,AL20,AO20) -> 2046180.7 | AT20: =AQ20*$AT$18 -> 5772
C21: Postdoc | G21: =_xlfn.XLOOKUP(C21,Lists!$N$3:$N$15,Lists!$O$3:$O$15,"") -> 1 | H21: =J21/37 -> 1 | I21: =_xlfn.XLOOKUP(C21,'AU salary costs 2025'!$B$7:$B$35,'AU salary costs 2025'!$D$7:$D$35, "-") -> 52000 | J21: 37 | M21: =$H21*(L21/12) -> 0 | N21: =IFERROR($I21*$J21/37*(1+PLPartner1)^N$3*L21,"") -> 0 | O21: 12 | P21: =$H21*(O21/12) -> 1 | Q21: =IFERROR($I21*$J21/37*(1+PLPartner1)^Q$3*O21,"") -> 681861.65 | R21: 12 | S21: =$H21*(R21/12) -> 1 | T21: =IFERROR($I21*$J21/37*(1+PLPartner1)^T$3*R21,"") -> 702317.5 | U21: 12 | V21: =$H21*(U21/12) -> 1 | W21: =IFERROR($I21*$J21/37*(1+PLPartner1)^W$3*U21,"") -> 723387.02 | Y21: =$H21*(X21/12) -> 0 | Z21: =IFERROR($I21*$J21/37*(1+PLPartner1)^Z$3*X21,"") -> 0 | AB21: =$H21*(AA21/12) -> 0 | AC21: =IFERROR($I21*$J21/37*(1+PLPartner1)^AC$3*AA21,"") -> 0 | AE21: =$H21*(AD21/12) -> 0 | AF21: =IFERROR($I21*$J21/37*(1+PLPartner1)^AF$3*AD21,"") -> 0 | AH21: =$H21*(AG21/12) -> 0 | AI21: =IFERROR($I21*$J21/37*(1+PLPartner1)^AI$3*AG21,"") -> 0 | AK21: =$H21*(AJ21/12) -> 0 | AL21: =IFERROR($I21*$J21/37*(1+PLPartner1)^AL$3*AJ21,"") -> 0 | AN21: =$H21*(AM21/12) -> 0 | AO21: =IFERROR($I21*$J21/37*(1+PLPartner1)^AO$3*AM21,"") -> 0 | AP21: =SUM(L21,O21,R21,U21,X21,AA21,AD21,AG21,AJ21,AM21) -> 36 | AQ21: =SUM(M21,P21,S21,V21,Y21,AB21,AE21,AH21,AK21,AN21) -> 3 | AR21: =SUM(N21,Q21,T21,W21,Z21,AC21,AF21,AI21,AL21,AO21) -> 2107566.2 | AT21: =AQ21*$AT$18 -> 5772
C22: Postdoc | G22: =_xlfn.XLOOKUP(C22,Lists!$N$3:$N$15,Lists!$O$3:$O$15,"") -> 1 | H22: =J22/37 -> 1 | I22: =_xlfn.XLOOKUP(C22,'AU salary costs 2025'!$B$7:$B$35,'AU salary costs 2025'!$D$7:$D$35, "-") -> 52000 | J22: 37 | M22: =$H22*(L22/12) -> 0 | N22: =IFERROR($I22*$J22/37*(1+PLPartner1)^N$3*L22,"") -> 0 | P22: =$H22*(O22/12) -> 0 | Q22: =IFERROR($I22*$J22/37*(1+PLPartner1)^Q$3*O22,"") -> 0 | R22: 6 | S22: =$H22*(R22/12) -> 0.5 | T22: =IFERROR($I22*$J22/37*(1+PLPartner1)^T$3*R22,"") -> 351158.75 | U22: 12 | V22: =$H22*(U22/12) -> 1 | W22: =IFERROR($I22*$J22/37*(1+PLPartner1)^W$3*U22,"") -> 723387.02 | X22: 12 | Y22: =$H22*(X22/12) -> 1 | Z22: =IFERROR($I22*$J22/37*(1+PLPartner1)^Z$3*X22,"") -> 745088.63 | AA22: 6 | AB22: =$H22*(AA22/12) -> 0.5 | AC22: =IFERROR($I22*$J22/37*(1+PLPartner1)^AC$3*AA22,"") -> 383720.65 | AE22: =$H22*(AD22/12) -> 0 | AF22: =IFERROR($I22*$J22/37*(1+PLPartner1)^AF$3*AD22,"") -> 0 | AH22: =$H22*(AG22/12) -> 0 | AI22: =IFERROR($I22*$J22/37*(1+PLPartner1)^AI$3*AG22,"") -> 0 | AK22: =$H22*(AJ22/12) -> 0 | AL22: =IFERROR($I22*$J22/37*(1+PLPartner1)^AL$3*AJ22,"") -> 0 | AN22: =$H22*(AM22/12) -> 0 | AO22: =IFERROR($I22*$J22/37*(1+PLPartner1)^AO$3*AM22,"") -> 0 | AP22: =SUM(L22,O22,R22,U22,X22,AA22,AD22,AG22,AJ22,AM22) -> 36 | AQ22: =SUM(M22,P22,S22,V22,Y22,AB22,AE22,AH22,AK22,AN22) -> 3 | AR22: =SUM(N22,Q22,T22,W22,Z22,AC22,AF22,AI22,AL22,AO22) -> 2203355.1 | AT22: =AQ22*$AT$18 -> 5772
C23: PhD Student | G23: =_xlfn.XLOOKUP(C23,Lists!$N$3:$N$15,Lists!$O$3:$O$15,"") -> 1 | H23: =J23/37 -> 1 | I23: =_xlfn.XLOOKUP(C23,'AU salary costs 2025'!$B$7:$B$35,'AU salary costs 2025'!$D$7:$D$35, "-") -> 42000 | J23: 37 | L23: 6 | M23: =$H23*(L23/12) -> 0.5 | N23: =IFERROR($I23*$J23/37*(1+PLPartner1)^N$3*L23,"") -> 267346.8 | O23: 12 | P23: =$H23*(O23/12) -> 1 | Q23: =IFERROR($I23*$J23/37*(1+PLPartner1)^Q$3*O23,"") -> 550734.41 | R23: 12 | S23: =$H23*(R23/12) -> 1 | T23: =IFERROR($I23*$J23/37*(1+PLPartner1)^T$3*R23,"") -> 567256.44 | U23: 6 | V23: =$H23*(U23/12) -> 0.5 | W23: =IFERROR($I23*$J23/37*(1+PLPartner1)^W$3*U23,"") -> 292137.07 | Y23: =$H23*(X23/12) -> 0 | Z23: =IFERROR($I23*$J23/37*(1+PLPartner1)^Z$3*X23,"") -> 0 | AB23: =$H23*(AA23/12) -> 0 | AC23: =IFERROR($I23*$J23/37*(1+PLPartner1)^AC$3*AA23,"") -> 0 | AE23: =$H23*(AD23/12) -> 0 | AF23: =IFERROR($I23*$J23/37*(1+PLPartner1)^AF$3*AD23,"") -> 0 | AH23: =$H23*(AG23/12) -> 0 | AI23: =IFERROR($I23*$J23/37*(1+PLPartner1)^AI$3*AG23,"") -> 0 | AK23: =$H23*(AJ23/12) -> 0 | AL23: =IFERROR($I23*$J23/37*(1+PLPartner1)^AL$3*AJ23,"") -> 0 | AN23: =$H23*(AM23/12) -> 0 | AO23: =IFERROR($I23*$J23/37*(1+PLPartner1)^AO$3*AM23,"") -> 0 | AP23: =SUM(L23,O23,R23,U23,X23,AA23,AD23,AG23,AJ23,AM23) -> 36 | AQ23: =SUM(M23,P23,S23,V23,Y23,AB23,AE23,AH23,AK23,AN23) -> 3 | AR23: =SUM(N23,Q23,T23,W23,Z23,AC23,AF23,AI23,AL23,AO23) -> 1677474.7 | AT23: =AQ23*$AT$18 -> 5772
C24: PhD Student | G24: =_xlfn.XLOOKUP(C24,Lists!$N$3:$N$15,Lists!$O$3:$O$15,"") -> 1 | H24: =J24/37 -> 1 | I24: =_xlfn.XLOOKUP(C24,'AU salary costs 2025'!$B$7:$B$35,'AU salary costs 2025'!$D$7:$D$35, "-") -> 42000 | J24: 37 | M24: =$H24*(L24/12) -> 0 | N24: =IFERROR($I24*$J24/37*(1+PLPartner1)^N$3*L24,"") -> 0 | P24: =$H24*(O24/12) -> 0 | Q24: =IFERROR($I24*$J24/37*(1+PLPartner1)^Q$3*O24,"") -> 0 | R24: 6 | S24: =$H24*(R24/12) -> 0.5 | T24: =IFERROR($I24*$J24/37*(1+PLPartner1)^T$3*R24,"") -> 283628.22 | U24: 12 | V24: =$H24*(U24/12) -> 1 | W24: =IFERROR($I24*$J24/37*(1+PLPartner1)^W$3*U24,"") -> 584274.13 | X24: 12 | Y24: =$H24*(X24/12) -> 1 | Z24: =IFERROR($I24*$J24/37*(1+PLPartner1)^Z$3*X24,"") -> 601802.36 | AA24: 6 | AB24: =$H24*(AA24/12) -> 0.5 | AC24: =IFERROR($I24*$J24/37*(1+PLPartner1)^AC$3*AA24,"") -> 309928.21 | AE24: =$H24*(AD24/12) -> 0 | AF24: =IFERROR($I24*$J24/37*(1+PLPartner1)^AF$3*AD24,"") -> 0 | AH24: =$H24*(AG24/12) -> 0 | AI24: =IFERROR($I24*$J24/37*(1+PLPartner1)^AI$3*AG24,"") -> 0 | AK24: =$H24*(AJ24/12) -> 0 | AL24: =IFERROR($I24*$J24/37*(1+PLPartner1)^AL$3*AJ24,"") -> 0 | AN24: =$H24*(AM24/12) -> 0 | AO24: =IFERROR($I24*$J24/37*(1+PLPartner1)^AO$3*AM24,"") -> 0 | AP24: =SUM(L24,O24,R24,U24,X24,AA24,AD24,AG24,AJ24,AM24) -> 36 | AQ24: =SUM(M24,P24,S24,V24,Y24,AB24,AE24,AH24,AK24,AN24) -> 3 | AR24: =SUM(N24,Q24,T24,W24,Z24,AC24,AF24,AI24,AL24,AO24) -> 1779632.9 | AT24: =AQ24*$AT$18 -> 5772
C25: - | G25: =_xlfn.XLOOKUP(C25,Lists!$N$3:$N$15,Lists!$O$3:$O$15,"") | H25: =J25/37 -> 1 | I25: =_xlfn.XLOOKUP(C25,'AU salary costs 2025'!$B$7:$B$35,'AU salary costs 2025'!$D$7:$D$35, "-") -> - | J25: 37 | M25: =$H25*(L25/12) -> 0 | N25: =IFERROR($I25*$J25/37*(1+PLPartner1)^N$3*L25,"") | P25: =$H25*(O25/12) -> 0 | Q25: =IFERROR($I25*$J25/37*(1+PLPartner1)^Q$3*O25,"") | S25: =$H25*(R25/12) -> 0 | T25: =IFERROR($I25*$J25/37*(1+PLPartner1)^T$3*R25,"") | V25: =$H25*(U25/12) -> 0 | W25: =IFERROR($I25*$J25/37*(1+PLPartner1)^W$3*U25,"") | Y25: =$H25*(X25/12) -> 0 | Z25: =IFERROR($I25*$J25/37*(1+PLPartner1)^Z$3*X25,"") | AB25: =$H25*(AA25/12) -> 0 | AC25: =IFERROR($I25*$J25/37*(1+PLPartner1)^AC$3*AA25,"") | AE25: =$H25*(AD25/12) -> 0 | AF25: =IFERROR($I25*$J25/37*(1+PLPartner1)^AF$3*AD25,"") | AH25: =$H25*(AG25/12) -> 0 | AI25: =IFERROR($I25*$J25/37*(1+PLPartner1)^AI$3*AG25,"") | AK25: =$H25*(AJ25/12) -> 0 | AL25: =IFERROR($I25*$J25/37*(1+PLPartner1)^AL$3*AJ25,"") | AN25: =$H25*(AM25/12) -> 0 | AO25: =IFERROR($I25*$J25/37*(1+PLPartner1)^AO$3*AM25,"") | AP25: =SUM(L25,O25,R25,U25,X25,AA25,AD25,AG25,AJ25,AM25) -> 0 | AQ25: =SUM(M25,P25,S25,V25,Y25,AB25,AE25,AH25,AK25,AN25) -> 0 | AR25: =SUM(N25,Q25,T25,W25,Z25,AC25,AF25,AI25,AL25,AO25) -> 0 | AT25: =AQ25*$AT$18 -> 0
C26: - | G26: =_xlfn.XLOOKUP(C26,Lists!$N$3:$N$15,Lists!$O$3:$O$15,"") | H26: =J26/37 -> 1 | I26: =_xlfn.XLOOKUP(C26,'AU salary costs 2025'!$B$7:$B$35,'AU salary costs 2025'!$D$7:$D$35, "-") -> - | J26: 37 | M26: =$H26*(L26/12) -> 0 | N26: =IFERROR($I26*$J26/37*(1+PLPartner1)^N$3*L26,"") | P26: =$H26*(O26/12) -> 0 | Q26: =IFERROR($I26*$J26/37*(1+PLPartner1)^Q$3*O26,"") | S26: =$H26*(R26/12) -> 0 | T26: =IFERROR($I26*$J26/37*(1+PLPartner1)^T$3*R26,"") | V26: =$H26*(U26/12) -> 0 | W26: =IFERROR($I26*$J26/37*(1+PLPartner1)^W$3*U26,"") | Y26: =$H26*(X26/12) -> 0 | Z26: =IFERROR($I26*$J26/37*(1+PLPartner1)^Z$3*X26,"") | AB26: =$H26*(AA26/12) -> 0 | AC26: =IFERROR($I26*$J26/37*(1+PLPartner1)^AC$3*AA26,"") | AE26: =$H26*(AD26/12) -> 0 | AF26: =IFERROR($I26*$J26/37*(1+PLPartner1)^AF$3*AD26,"") | AH26: =$H26*(AG26/12) -> 0 | AI26: =IFERROR($I26*$J26/37*(1+PLPartner1)^AI$3*AG26,"") | AK26: =$H26*(AJ26/12) -> 0 | AL26: =IFERROR($I26*$J26/37*(1+PLPartner1)^AL$3*AJ26,"") | AN26: =$H26*(AM26/12) -> 0 | AO26: =IFERROR($I26*$J26/37*(1+PLPartner1)^AO$3*AM26,"") | AP26: =SUM(L26,O26,R26,U26,X26,AA26,AD26,AG26,AJ26,AM26) -> 0 | AQ26: =SUM(M26,P26,S26,V26,Y26,AB26,AE26,AH26,AK26,AN26) -> 0 | AR26: =SUM(N26,Q26,T26,W26,Z26,AC26,AF26,AI26,AL26,AO26) -> 0 | AT26: =AQ26*$AT$18 -> 0
C27: - | G27: =_xlfn.XLOOKUP(C27,Lists!$N$3:$N$15,Lists!$O$3:$O$15,"") | H27: =J27/37 -> 1 | I27: =_xlfn.XLOOKUP(C27,'AU salary costs 2025'!$B$7:$B$35,'AU salary costs 2025'!$D$7:$D$35, "-") -> - | J27: 37 | M27: =$H27*(L27/12) -> 0 | N27: =IFERROR($I27*$J27/37*(1+PLPartner1)^N$3*L27,"") | P27: =$H27*(O27/12) -> 0 | Q27: =IFERROR($I27*$J27/37*(1+PLPartner1)^Q$3*O27,"") | S27: =$H27*(R27/12) -> 0 | T27: =IFERROR($I27*$J27/37*(1+PLPartner1)^T$3*R27,"") | V27: =$H27*(U27/12) -> 0 | W27: =IFERROR($I27*$J27/37*(1+PLPartner1)^W$3*U27,"") | Y27: =$H27*(X27/12) -> 0 | Z27: =IFERROR($I27*$J27/37*(1+PLPartner1)^Z$3*X27,"") | AB27: =$H27*(AA27/12) -> 0 | AC27: =IFERROR($I27*$J27/37*(1+PLPartner1)^AC$3*AA27,"") | AE27: =$H27*(AD27/12) -> 0 | AF27: =IFERROR($I27*$J27/37*(1+PLPartner1)^AF$3*AD27,"") | AH27: =$H27*(AG27/12) -> 0 | AI27: =IFERROR($I27*$J27/37*(1+PLPartner1)^AI$3*AG27,"") | AK27: =$H27*(AJ27/12) -> 0 | AL27: =IFERROR($I27*$J27/37*(1+PLPartner1)^AL$3*AJ27,"") | AN27: =$H27*(AM27/12) -> 0 | AO27: =IFERROR($I27*$J27/37*(1+PLPartner1)^AO$3*AM27,"") | AP27: =SUM(L27,O27,R27,U27,X27,AA27,AD27,AG27,AJ27,AM27) -> 0 | AQ27: =SUM(M27,P27,S27,V27,Y27,AB27,AE27,AH27,AK27,AN27) -> 0 | AR27: =SUM(N27,Q27,T27,W27,Z27,AC27,AF27,AI27,AL27,AO27) -> 0 | AT27: =AQ27*$AT$18 -> 0
C28: - | G28: =_xlfn.XLOOKUP(C28,Lists!$N$3:$N$15,Lists!$O$3:$O$15,"") | H28: =J28/37 -> 1 | I28: =_xlfn.XLOOKUP(C28,'AU salary costs 2025'!$B$7:$B$35,'AU salary costs 2025'!$D$7:$D$35, "-") -> - | J28: 37 | M28: =$H28*(L28/12) -> 0 | N28: =IFERROR($I28*$J28/37*(1+PLPartner1)^N$3*L28,"") | P28: =$H28*(O28/12) -> 0 | Q28: =IFERROR($I28*$J28/37*(1+PLPartner1)^Q$3*O28,"") | S28: =$H28*(R28/12) -> 0 | T28: =IFERROR($I28*$J28/37*(1+PLPartner1)^T$3*R28,"") | V28: =$H28*(U28/12) -> 0 | W28: =IFERROR($I28*$J28/37*(1+PLPartner1)^W$3*U28,"") | Y28: =$H28*(X28/12) -> 0 | Z28: =IFERROR($I28*$J28/37*(1+PLPartner1)^Z$3*X28,"") | AB28: =$H28*(AA28/12) -> 0 | AC28: =IFERROR($I28*$J28/37*(1+PLPartner1)^AC$3*AA28,"") | AE28: =$H28*(AD28/12) -> 0 | AF28: =IFERROR($I28*$J28/37*(1+PLPartner1)^AF$3*AD28,"") | AH28: =$H28*(AG28/12) -> 0 | AI28: =IFERROR($I28*$J28/37*(1+PLPartner1)^AI$3*AG28,"") | AK28: =$H28*(AJ28/12) -> 0 | AL28: =IFERROR($I28*$J28/37*(1+PLPartner1)^AL$3*AJ28,"") | AN28: =$H28*(AM28/12) -> 0 | AO28: =IFERROR($I28*$J28/37*(1+PLPartner1)^AO$3*AM28,"") | AP28: =SUM(L28,O28,R28,U28,X28,AA28,AD28,AG28,AJ28,AM28) -> 0 | AQ28: =SUM(M28,P28,S28,V28,Y28,AB28,AE28,AH28,AK28,AN28) -> 0 | AR28: =SUM(N28,Q28,T28,W28,Z28,AC28,AF28,AI28,AL28,AO28) -> 0 | AT28: =AQ28*$AT$18 -> 0
C29: - | G29: =_xlfn.XLOOKUP(C29,Lists!$N$3:$N$15,Lists!$O$3:$O$15,"") | H29: =J29/37 -> 1 | I29: =_xlfn.XLOOKUP(C29,'AU salary costs 2025'!$B$7:$B$35,'AU salary costs 2025'!$D$7:$D$35, "-") -> - | J29: 37 | M29: =$H29*(L29/12) -> 0 | N29: =IFERROR($I29*$J29/37*(1+PLPartner1)^N$3*L29,"") | P29: =$H29*(O29/12) -> 0 | Q29: =IFERROR($I29*$J29/37*(1+PLPartner1)^Q$3*O29,"") | S29: =$H29*(R29/12) -> 0 | T29: =IFERROR($I29*$J29/37*(1+PLPartner1)^T$3*R29,"") | V29: =$H29*(U29/12) -> 0 | W29: =IFERROR($I29*$J29/37*(1+PLPartner1)^W$3*U29,"") | Y29: =$H29*(X29/12) -> 0 | Z29: =IFERROR($I29*$J29/37*(1+PLPartner1)^Z$3*X29,"") | AB29: =$H29*(AA29/12) -> 0 | AC29: =IFERROR($I29*$J29/37*(1+PLPartner1)^AC$3*AA29,"") | AE29: =$H29*(AD29/12) -> 0 | AF29: =IFERROR($I29*$J29/37*(1+PLPartner1)^AF$3*AD29,"") | AH29: =$H29*(AG29/12) -> 0 | AI29: =IFERROR($I29*$J29/37*(1+PLPartner1)^AI$3*AG29,"") | AK29: =$H29*(AJ29/12) -> 0 | AL29: =IFERROR($I29*$J29/37*(1+PLPartner1)^AL$3*AJ29,"") | AN29: =$H29*(AM29/12) -> 0 | AO29: =IFERROR($I29*$J29/37*(1+PLPartner1)^AO$3*AM29,"") | AP29: =SUM(L29,O29,R29,U29,X29,AA29,AD29,AG29,AJ29,AM29) -> 0 | AQ29: =SUM(M29,P29,S29,V29,Y29,AB29,AE29,AH29,AK29,AN29) -> 0 | AR29: =SUM(N29,Q29,T29,W29,Z29,AC29,AF29,AI29,AL29,AO29) -> 0 | AT29: =AQ29*$AT$18 -> 0
C30: - | G30: =_xlfn.XLOOKUP(C30,Lists!$N$3:$N$15,Lists!$O$3:$O$15,"") | H30: =J30/37 -> 1 | I30: =_xlfn.XLOOKUP(C30,'AU salary costs 2025'!$B$7:$B$35,'AU salary costs 2025'!$D$7:$D$35, "-") -> - | J30: 37 | M30: =$H30*(L30/12) -> 0 | N30: =IFERROR($I30*$J30/37*(1+PLPartner1)^N$3*L30,"") | P30: =$H30*(O30/12) -> 0 | Q30: =IFERROR($I30*$J30/37*(1+PLPartner1)^Q$3*O30,"") | S30: =$H30*(R30/12) -> 0 | T30: =IFERROR($I30*$J30/37*(1+PLPartner1)^T$3*R30,"") | V30: =$H30*(U30/12) -> 0 | W30: =IFERROR($I30*$J30/37*(1+PLPartner1)^W$3*U30,"") | Y30: =$H30*(X30/12) -> 0 | Z30: =IFERROR($I30*$J30/37*(1+PLPartner1)^Z$3*X30,"") | AB30: =$H30*(AA30/12) -> 0 | AC30: =IFERROR($I30*$J30/37*(1+PLPartner1)^AC$3*AA30,"") | AE30: =$H30*(AD30/12) -> 0 | AF30: =IFERROR($I30*$J30/37*(1+PLPartner1)^AF$3*AD30,"") | AH30: =$H30*(AG30/12) -> 0 | AI30: =IFERROR($I30*$J30/37*(1+PLPartner1)^AI$3*AG30,"") | AK30: =$H30*(AJ30/12) -> 0 | AL30: =IFERROR($I30*$J30/37*(1+PLPartner1)^AL$3*AJ30,"") | AN30: =$H30*(AM30/12) -> 0 | AO30: =IFERROR($I30*$J30/37*(1+PLPartner1)^AO$3*AM30,"") | AP30: =SUM(L30,O30,R30,U30,X30,AA30,AD30,AG30,AJ30,AM30) -> 0 | AQ30: =SUM(M30,P30,S30,V30,Y30,AB30,AE30,AH30,AK30,AN30) -> 0 | AR30: =SUM(N30,Q30,T30,W30,Z30,AC30,AF30,AI30,AL30,AO30) -> 0 | AT30: =AQ30*$AT$18 -> 0
C31: - | G31: =_xlfn.XLOOKUP(C31,Lists!$N$3:$N$15,Lists!$O$3:$O$15,"") | H31: =J31/37 -> 1 | I31: =_xlfn.XLOOKUP(C31,'AU salary costs 2025'!$B$7:$B$35,'AU salary costs 2025'!$D$7:$D$35, "-") -> - | J31: 37 | M31: =$H31*(L31/12) -> 0 | N31: =IFERROR($I31*$J31/37*(1+PLPartner1)^N$3*L31,"") | P31: =$H31*(O31/12) -> 0 | Q31: =IFERROR($I31*$J31/37*(1+PLPartner1)^Q$3*O31,"") | S31: =$H31*(R31/12) -> 0 | T31: =IFERROR($I31*$J31/37*(1+PLPartner1)^T$3*R31,"") | V31: =$H31*(U31/12) -> 0 | W31: =IFERROR($I31*$J31/37*(1+PLPartner1)^W$3*U31,"") | Y31: =$H31*(X31/12) -> 0 | Z31: =IFERROR($I31*$J31/37*(1+PLPartner1)^Z$3*X31,"") | AB31: =$H31*(AA31/12) -> 0 | AC31: =IFERROR($I31*$J31/37*(1+PLPartner1)^AC$3*AA31,"") | AE31: =$H31*(AD31/12) -> 0 | AF31: =IFERROR($I31*$J31/37*(1+PLPartner1)^AF$3*AD31,"") | AH31: =$H31*(AG31/12) -> 0 | AI31: =IFERROR($I31*$J31/37*(1+PLPartner1)^AI$3*AG31,"") | AK31: =$H31*(AJ31/12) -> 0 | AL31: =IFERROR($I31*$J31/37*(1+PLPartner1)^AL$3*AJ31,"") | AN31: =$H31*(AM31/12) -> 0 | AO31: =IFERROR($I31*$J31/37*(1+PLPartner1)^AO$3*AM31,"") | AP31: =SUM(L31,O31,R31,U31,X31,AA31,AD31,AG31,AJ31,AM31) -> 0 | AQ31: =SUM(M31,P31,S31,V31,Y31,AB31,AE31,AH31,AK31,AN31) -> 0 | AR31: =SUM(N31,Q31,T31,W31,Z31,AC31,AF31,AI31,AL31,AO31) -> 0 | AT31: =AQ31*$AT$18 -> 0
C32: - | G32: =_xlfn.XLOOKUP(C32,Lists!$N$3:$N$15,Lists!$O$3:$O$15,"") | H32: =J32/37 -> 1 | I32: =_xlfn.XLOOKUP(C32,'AU salary costs 2025'!$B$7:$B$35,'AU salary costs 2025'!$D$7:$D$35, "-") -> - | J32: 37 | M32: =$H32*(L32/12) -> 0 | N32: =IFERROR($I32*$J32/37*(1+PLPartner1)^N$3*L32,"") | P32: =$H32*(O32/12) -> 0 | Q32: =IFERROR($I32*$J32/37*(1+PLPartner1)^Q$3*O32,"") | S32: =$H32*(R32/12) -> 0 | T32: =IFERROR($I32*$J32/37*(1+PLPartner1)^T$3*R32,"") | V32: =$H32*(U32/12) -> 0 | W32: =IFERROR($I32*$J32/37*(1+PLPartner1)^W$3*U32,"") | Y32: =$H32*(X32/12) -> 0 | Z32: =IFERROR($I32*$J32/37*(1+PLPartner1)^Z$3*X32,"") | AB32: =$H32*(AA32/12) -> 0 | AC32: =IFERROR($I32*$J32/37*(1+PLPartner1)^AC$3*AA32,"") | AE32: =$H32*(AD32/12) -> 0 | AF32: =IFERROR($I32*$J32/37*(1+PLPartner1)^AF$3*AD32,"") | AH32: =$H32*(AG32/12) -> 0 | AI32: =IFERROR($I32*$J32/37*(1+PLPartner1)^AI$3*AG32,"") | AK32: =$H32*(AJ32/12) -> 0 | AL32: =IFERROR($I32*$J32/37*(1+PLPartner1)^AL$3*AJ32,"") | AN32: =$H32*(AM32/12) -> 0 | AO32: =IFERROR($I32*$J32/37*(1+PLPartner1)^AO$3*AM32,"") | AP32: =SUM(L32,O32,R32,U32,X32,AA32,AD32,AG32,AJ32,AM32) -> 0 | AQ32: =SUM(M32,P32,S32,V32,Y32,AB32,AE32,AH32,AK32,AN32) -> 0 | AR32: =SUM(N32,Q32,T32,W32,Z32,AC32,AF32,AI32,AL32,AO32) -> 0 | AT32: =AQ32*$AT$18 -> 0
C33: - | G33: =_xlfn.XLOOKUP(C33,Lists!$N$3:$N$15,Lists!$O$3:$O$15,"") | H33: =J33/37 -> 1 | I33: =_xlfn.XLOOKUP(C33,'AU salary costs 2025'!$B$7:$B$35,'AU salary costs 2025'!$D$7:$D$35, "-") -> - | J33: 37 | M33: =$H33*(L33/12) -> 0 | N33: =IFERROR($I33*$J33/37*(1+PLPartner1)^N$3*L33,"") | P33: =$H33*(O33/12) -> 0 | Q33: =IFERROR($I33*$J33/37*(1+PLPartner1)^Q$3*O33,"") | S33: =$H33*(R33/12) -> 0 | T33: =IFERROR($I33*$J33/37*(1+PLPartner1)^T$3*R33,"") | V33: =$H33*(U33/12) -> 0 | W33: =IFERROR($I33*$J33/37*(1+PLPartner1)^W$3*U33,"") | Y33: =$H33*(X33/12) -> 0 | Z33: =IFERROR($I33*$J33/37*(1+PLPartner1)^Z$3*X33,"") | AB33: =$H33*(AA33/12) -> 0 | AC33: =IFERROR($I33*$J33/37*(1+PLPartner1)^AC$3*AA33,"") | AE33: =$H33*(AD33/12) -> 0 | AF33: =IFERROR($I33*$J33/37*(1+PLPartner1)^AF$3*AD33,"") | AH33: =$H33*(AG33/12) -> 0 | AI33: =IFERROR($I33*$J33/37*(1+PLPartner1)^AI$3*AG33,"") | AK33: =$H33*(AJ33/12) -> 0 | AL33: =IFERROR($I33*$J33/37*(1+PLPartner1)^AL$3*AJ33,"") | AN33: =$H33*(AM33/12) -> 0 | AO33: =IFERROR($I33*$J33/37*(1+PLPartner1)^AO$3*AM33,"") | AP33: =SUM(L33,O33,R33,U33,X33,AA33,AD33,AG33,AJ33,AM33) -> 0 | AQ33: =SUM(M33,P33,S33,V33,Y33,AB33,AE33,AH33,AK33,AN33) -> 0 | AR33: =SUM(N33,Q33,T33,W33,Z33,AC33,AF33,AI33,AL33,AO33) -> 0 | AT33: =AQ33*$AT$18 -> 0
C34: - | G34: =_xlfn.XLOOKUP(C34,Lists!$N$3:$N$15,Lists!$O$3:$O$15,"") | H34: =J34/37 -> 1 | I34: =_xlfn.XLOOKUP(C34,'AU salary costs 2025'!$B$7:$B$35,'AU salary costs 2025'!$D$7:$D$35, "-") -> - | J34: 37 | M34: =$H34*(L34/12) -> 0 | N34: =IFERROR($I34*$J34/37*(1+PLPartner1)^N$3*L34,"") | P34: =$H34*(O34/12) -> 0 | Q34: =IFERROR($I34*$J34/37*(1+PLPartner1)^Q$3*O34,"") | S34: =$H34*(R34/12) -> 0 | T34: =IFERROR($I34*$J34/37*(1+PLPartner1)^T$3*R34,"") | V34: =$H34*(U34/12) -> 0 | W34: =IFERROR($I34*$J34/37*(1+PLPartner1)^W$3*U34,"") | Y34: =$H34*(X34/12) -> 0 | Z34: =IFERROR($I34*$J34/37*(1+PLPartner1)^Z$3*X34,"") | AB34: =$H34*(AA34/12) -> 0 | AC34: =IFERROR($I34*$J34/37*(1+PLPartner1)^AC$3*AA34,"") | AE34: =$H34*(AD34/12) -> 0 | AF34: =IFERROR($I34*$J34/37*(1+PLPartner1)^AF$3*AD34,"") | AH34: =$H34*(AG34/12) -> 0 | AI34: =IFERROR($I34*$J34/37*(1+PLPartner1)^AI$3*AG34,"") | AK34: =$H34*(AJ34/12) -> 0 | AL34: =IFERROR($I34*$J34/37*(1+PLPartner1)^AL$3*AJ34,"") | AN34: =$H34*(AM34/12) -> 0 | AO34: =IFERROR($I34*$J34/37*(1+PLPartner1)^AO$3*AM34,"") | AP34: =SUM(L34,O34,R34,U34,X34,AA34,AD34,AG34,AJ34,AM34) -> 0 | AQ34: =SUM(M34,P34,S34,V34,Y34,AB34,AE34,AH34,AK34,AN34) -> 0 | AR34: =SUM(N34,Q34,T34,W34,Z34,AC34,AF34,AI34,AL34,AO34) -> 0 | AT34: =AQ34*$AT$18 -> 0
C35: - | G35: =_xlfn.XLOOKUP(C35,Lists!$N$3:$N$15,Lists!$O$3:$O$15,"") | H35: =J35/37 -> 1 | I35: =_xlfn.XLOOKUP(C35,'AU salary costs 2025'!$B$7:$B$35,'AU salary costs 2025'!$D$7:$D$35, "-") -> - | J35: 37 | M35: =$H35*(L35/12) -> 0 | N35: =IFERROR($I35*$J35/37*(1+PLPartner1)^N$3*L35,"") | P35: =$H35*(O35/12) -> 0 | Q35: =IFERROR($I35*$J35/37*(1+PLPartner1)^Q$3*O35,"") | S35: =$H35*(R35/12) -> 0 | T35: =IFERROR($I35*$J35/37*(1+PLPartner1)^T$3*R35,"") | V35: =$H35*(U35/12) -> 0 | W35: =IFERROR($I35*$J35/37*(1+PLPartner1)^W$3*U35,"") | Y35: =$H35*(X35/12) -> 0 | Z35: =IFERROR($I35*$J35/37*(1+PLPartner1)^Z$3*X35,"") | AB35: =$H35*(AA35/12) -> 0 | AC35: =IFERROR($I35*$J35/37*(1+PLPartner1)^AC$3*AA35,"") | AE35: =$H35*(AD35/12) -> 0 | AF35: =IFERROR($I35*$J35/37*(1+PLPartner1)^AF$3*AD35,"") | AH35: =$H35*(AG35/12) -> 0 | AI35: =IFERROR($I35*$J35/37*(1+PLPartner1)^AI$3*AG35,"") | AK35: =$H35*(AJ35/12) -> 0 | AL35: =IFERROR($I35*$J35/37*(1+PLPartner1)^AL$3*AJ35,"") | AN35: =$H35*(AM35/12) -> 0 | AO35: =IFERROR($I35*$J35/37*(1+PLPartner1)^AO$3*AM35,"") | AP35: =SUM(L35,O35,R35,U35,X35,AA35,AD35,AG35,AJ35,AM35) -> 0 | AQ35: =SUM(M35,P35,S35,V35,Y35,AB35,AE35,AH35,AK35,AN35) -> 0 | AR35: =SUM(N35,Q35,T35,W35,Z35,AC35,AF35,AI35,AL35,AO35) -> 0 | AT35: =AQ35*$AT$18 -> 0
B36: A | K36: Subtotal | L36: =SUM(L20:L35) -> 18 | M36: =SUM(M20:M35) -> 1.5 | N36: =SUM(N20:N35) -> 929348.4 | O36: =SUM(O20:O35) -> 36 | P36: =SUM(P20:P35) -> 3 | Q36: =SUM(Q20:Q35) -> 1914457.7 | R36: =SUM(R20:R35) -> 48 | S36: =SUM(S20:S35) -> 4 | ... AR36: =SUM(AR20:AR35) -> 9814209.6 | AT36: =AQ36*$AT$18 -> 28860
C37: 1. VIP Co-financing | F37: =F19 -> Notes/Name | I37: =I19 -> Salary/mo 2025 | J37: =J19 -> Hrs/wk | AT37: Co-financed VIP hours
C38: - | H38: =J38/37 -> 1 | I38: =_xlfn.XLOOKUP(C38,'AU salary costs 2025'!$B$7:$B$35,'AU salary costs 2025'!$D$7:$D$35, "-") -> - | J38: 37 | M38: =$H38*(L38/12) -> 0 | N38: =IFERROR($I38*$J38/37*(1+PLPartner1)^N$3*L38,"") | P38: =$H38*(O38/12) -> 0 | Q38: =IFERROR($I38*$J38/37*(1+PLPartner1)^Q$3*O38,"") | S38: =$H38*(R38/12) -> 0 | T38: =IFERROR($I38*$J38/37*(1+PLPartner1)^T$3*R38,"") | V38: =$H38*(U38/12) -> 0 | W38: =IFERROR($I38*$J38/37*(1+PLPartner1)^W$3*U38,"") | Y38: =$H38*(X38/12) -> 0 | Z38: =IFERROR($I38*$J38/37*(1+PLPartner1)^Z$3*X38,"") | AB38: =$H38*(AA38/12) -> 0 | AC38: =IFERROR($I38*$J38/37*(1+PLPartner1)^AC$3*AA38,"") | AE38: =$H38*(AD38/12) -> 0 | AF38: =IFERROR($I38*$J38/37*(1+PLPartner1)^AF$3*AD38,"") | AH38: =$H38*(AG38/12) -> 0 | AI38: =IFERROR($I38*$J38/37*(1+PLPartner1)^AI$3*AG38,"") | AK38: =$H38*(AJ38/12) -> 0 | AL38: =IFERROR($I38*$J38/37*(1+PLPartner1)^AL$3*AJ38,"") | AN38: =$H38*(AM38/12) -> 0 | AO38: =IFERROR($I38*$J38/37*(1+PLPartner1)^AO$3*AM38,"") | AP38: =SUM(L38,O38,R38,U38,X38,AA38,AD38,AG38,AJ38,AM38) -> 0 | AQ38: =SUM(M38,P38,S38,V38,Y38,AB38,AE38,AH38,AK38,AN38) -> 0 | AR38: =SUM(N38,Q38,T38,W38,Z38,AC38,AF38,AI38,AL38,AO38) -> 0 | AT38: =AQ38*$AT$18 -> 0
C39: - | H39: =J39/37 -> 1 | I39: =_xlfn.XLOOKUP(C39,'AU salary costs 2025'!$B$7:$B$35,'AU salary costs 2025'!$D$7:$D$35, "-") -> - | J39: 37 | M39: =$H39*(L39/12) -> 0 | N39: =IFERROR($I39*$J39/37*(1+PLPartner1)^N$3*L39,"") | P39: =$H39*(O39/12) -> 0 | Q39: =IFERROR($I39*$J39/37*(1+PLPartner1)^Q$3*O39,"") | S39: =$H39*(R39/12) -> 0 | T39: =IFERROR($I39*$J39/37*(1+PLPartner1)^T$3*R39,"") | V39: =$H39*(U39/12) -> 0 | W39: =IFERROR($I39*$J39/37*(1+PLPartner1)^W$3*U39,"") | Y39: =$H39*(X39/12) -> 0 | Z39: =IFERROR($I39*$J39/37*(1+PLPartner1)^Z$3*X39,"") | AB39: =$H39*(AA39/12) -> 0 | AC39: =IFERROR($I39*$J39/37*(1+PLPartner1)^AC$3*AA39,"") | AE39: =$H39*(AD39/12) -> 0 | AF39: =IFERROR($I39*$J39/37*(1+PLPartner1)^AF$3*AD39,"") | AH39: =$H39*(AG39/12) -> 0 | AI39: =IFERROR($I39*$J39/37*(1+PLPartner1)^AI$3*AG39,"") | AK39: =$H39*(AJ39/12) -> 0 | AL39: =IFERROR($I39*$J39/37*(1+PLPartner1)^AL$3*AJ39,"") | AN39: =$H39*(AM39/12) -> 0 | AO39: =IFERROR($I39*$J39/37*(1+PLPartner1)^AO$3*AM39,"") | AP39: =SUM(L39,O39,R39,U39,X39,AA39,AD39,AG39,AJ39,AM39) -> 0 | AQ39: =SUM(M39,P39,S39,V39,Y39,AB39,AE39,AH39,AK39,AN39) -> 0 | AR39: =SUM(N39,Q39,T39,W39,Z39,AC39,AF39,AI39,AL39,AO39) -> 0 | AT39: =AQ39*$AT$18 -> 0
C40: - | H40: =J40/37 -> 1 | I40: =_xlfn.XLOOKUP(C40,'AU salary costs 2025'!$B$7:$B$35,'AU salary costs 2025'!$D$7:$D$35, "-") -> - | J40: 37 | M40: =$H40*(L40/12) -> 0 | N40: =IFERROR($I40*$J40/37*(1+PLPartner1)^N$3*L40,"") | P40: =$H40*(O40/12) -> 0 | Q40: =IFERROR($I40*$J40/37*(1+PLPartner1)^Q$3*O40,"") | S40: =$H40*(R40/12) -> 0 | T40: =IFERROR($I40*$J40/37*(1+PLPartner1)^T$3*R40,"") | V40: =$H40*(U40/12) -> 0 | W40: =IFERROR($I40*$J40/37*(1+PLPartner1)^W$3*U40,"") | Y40: =$H40*(X40/12) -> 0 | Z40: =IFERROR($I40*$J40/37*(1+PLPartner1)^Z$3*X40,"") | AB40: =$H40*(AA40/12) -> 0 | AC40: =IFERROR($I40*$J40/37*(1+PLPartner1)^AC$3*AA40,"") | AE40: =$H40*(AD40/12) -> 0 | AF40: =IFERROR($I40*$J40/37*(1+PLPartner1)^AF$3*AD40,"") | AH40: =$H40*(AG40/12) -> 0 | AI40: =IFERROR($I40*$J40/37*(1+PLPartner1)^AI$3*AG40,"") | AK40: =$H40*(AJ40/12) -> 0 | AL40: =IFERROR($I40*$J40/37*(1+PLPartner1)^AL$3*AJ40,"") | AN40: =$H40*(AM40/12) -> 0 | AO40: =IFERROR($I40*$J40/37*(1+PLPartner1)^AO$3*AM40,"") | AP40: =SUM(L40,O40,R40,U40,X40,AA40,AD40,AG40,AJ40,AM40) -> 0 | AQ40: =SUM(M40,P40,S40,V40,Y40,AB40,AE40,AH40,AK40,AN40) -> 0 | AR40: =SUM(N40,Q40,T40,W40,Z40,AC40,AF40,AI40,AL40,AO40) -> 0 | AT40: =AQ40*$AT$18 -> 0
C41: - | H41: =J41/37 -> 1 | I41: =_xlfn.XLOOKUP(C41,'AU salary costs 2025'!$B$7:$B$35,'AU salary costs 2025'!$D$7:$D$35, "-") -> - | J41: 37 | M41: =$H41*(L41/12) -> 0 | N41: =IFERROR($I41*$J41/37*(1+PLPartner1)^N$3*L41,"") | P41: =$H41*(O41/12) -> 0 | Q41: =IFERROR($I41*$J41/37*(1+PLPartner1)^Q$3*O41,"") | S41: =$H41*(R41/12) -> 0 | T41: =IFERROR($I41*$J41/37*(1+PLPartner1)^T$3*R41,"") | V41: =$H41*(U41/12) -> 0 | W41: =IFERROR($I41*$J41/37*(1+PLPartner1)^W$3*U41,"") | Y41: =$H41*(X41/12) -> 0 | Z41: =IFERROR($I41*$J41/37*(1+PLPartner1)^Z$3*X41,"") | AB41: =$H41*(AA41/12) -> 0 | AC41: =IFERROR($I41*$J41/37*(1+PLPartner1)^AC$3*AA41,"") | AE41: =$H41*(AD41/12) -> 0 | AF41: =IFERROR($I41*$J41/37*(1+PLPartner1)^AF$3*AD41,"") | AH41: =$H41*(AG41/12) -> 0 | AI41: =IFERROR($I41*$J41/37*(1+PLPartner1)^AI$3*AG41,"") | AK41: =$H41*(AJ41/12) -> 0 | AL41: =IFERROR($I41*$J41/37*(1+PLPartner1)^AL$3*AJ41,"") | AN41: =$H41*(AM41/12) -> 0 | AO41: =IFERROR($I41*$J41/37*(1+PLPartner1)^AO$3*AM41,"") | AP41: =SUM(L41,O41,R41,U41,X41,AA41,AD41,AG41,AJ41,AM41) -> 0 | AQ41: =SUM(M41,P41,S41,V41,Y41,AB41,AE41,AH41,AK41,AN41) -> 0 | AR41: =SUM(N41,Q41,T41,W41,Z41,AC41,AF41,AI41,AL41,AO41) -> 0 | AT41: =AQ41*$AT$18 -> 0
C42: - | H42: =J42/37 -> 1 | I42: =_xlfn.XLOOKUP(C42,'AU salary costs 2025'!$B$7:$B$35,'AU salary costs 2025'!$D$7:$D$35, "-") -> - | J42: 37 | M42: =$H42*(L42/12) -> 0 | N42: =IFERROR($I42*$J42/37*(1+PLPartner1)^N$3*L42,"") | P42: =$H42*(O42/12) -> 0 | Q42: =IFERROR($I42*$J42/37*(1+PLPartner1)^Q$3*O42,"") | S42: =$H42*(R42/12) -> 0 | T42: =IFERROR($I42*$J42/37*(1+PLPartner1)^T$3*R42,"") | V42: =$H42*(U42/12) -> 0 | W42: =IFERROR($I42*$J42/37*(1+PLPartner1)^W$3*U42,"") | Y42: =$H42*(X42/12) -> 0 | Z42: =IFERROR($I42*$J42/37*(1+PLPartner1)^Z$3*X42,"") | AB42: =$H42*(AA42/12) -> 0 | AC42: =IFERROR($I42*$J42/37*(1+PLPartner1)^AC$3*AA42,"") | AE42: =$H42*(AD42/12) -> 0 | AF42: =IFERROR($I42*$J42/37*(1+PLPartner1)^AF$3*AD42,"") | AH42: =$H42*(AG42/12) -> 0 | AI42: =IFERROR($I42*$J42/37*(1+PLPartner1)^AI$3*AG42,"") | AK42: =$H42*(AJ42/12) -> 0 | AL42: =IFERROR($I42*$J42/37*(1+PLPartner1)^AL$3*AJ42,"") | AN42: =$H42*(AM42/12) -> 0 | AO42: =IFERROR($I42*$J42/37*(1+PLPartner1)^AO$3*AM42,"") | AP42: =SUM(L42,O42,R42,U42,X42,AA42,AD42,AG42,AJ42,AM42) -> 0 | AQ42: =SUM(M42,P42,S42,V42,Y42,AB42,AE42,AH42,AK42,AN42) -> 0 | AR42: =SUM(N42,Q42,T42,W42,Z42,AC42,AF42,AI42,AL42,AO42) -> 0 | AT42: =AQ42*$AT$18 -> 0
C43: - | H43: =J43/37 -> 1 | I43: =_xlfn.XLOOKUP(C43,'AU salary costs 2025'!$B$7:$B$35,'AU salary costs 2025'!$D$7:$D$35, "-") -> - | J43: 37 | M43: =$H43*(L43/12) -> 0 | N43: =IFERROR($I43*$J43/37*(1+PLPartner1)^N$3*L43,"") | P43: =$H43*(O43/12) -> 0 | Q43: =IFERROR($I43*$J43/37*(1+PLPartner1)^Q$3*O43,"") | S43: =$H43*(R43/12) -> 0 | T43: =IFERROR($I43*$J43/37*(1+PLPartner1)^T$3*R43,"") | V43: =$H43*(U43/12) -> 0 | W43: =IFERROR($I43*$J43/37*(1+PLPartner1)^W$3*U43,"") | Y43: =$H43*(X43/12) -> 0 | Z43: =IFERROR($I43*$J43/37*(1+PLPartner1)^Z$3*X43,"") | AB43: =$H43*(AA43/12) -> 0 | AC43: =IFERROR($I43*$J43/37*(1+PLPartner1)^AC$3*AA43,"") | AE43: =$H43*(AD43/12) -> 0 | AF43: =IFERROR($I43*$J43/37*(1+PLPartner1)^AF$3*AD43,"") | AH43: =$H43*(AG43/12) -> 0 | AI43: =IFERROR($I43*$J43/37*(1+PLPartner1)^AI$3*AG43,"") | AK43: =$H43*(AJ43/12) -> 0 | AL43: =IFERROR($I43*$J43/37*(1+PLPartner1)^AL$3*AJ43,"") | AN43: =$H43*(AM43/12) -> 0 | AO43: =IFERROR($I43*$J43/37*(1+PLPartner1)^AO$3*AM43,"") | AP43: =SUM(L43,O43,R43,U43,X43,AA43,AD43,AG43,AJ43,AM43) -> 0 | AQ43: =SUM(M43,P43,S43,V43,Y43,AB43,AE43,AH43,AK43,AN43) -> 0 | AR43: =SUM(N43,Q43,T43,W43,Z43,AC43,AF43,AI43,AL43,AO43) -> 0 | AT43: =AQ43*$AT$18 -> 0
C44: - | H44: =J44/37 -> 1 | I44: =_xlfn.XLOOKUP(C44,'AU salary costs 2025'!$B$7:$B$35,'AU salary costs 2025'!$D$7:$D$35, "-") -> - | J44: 37 | M44: =$H44*(L44/12) -> 0 | N44: =IFERROR($I44*$J44/37*(1+PLPartner1)^N$3*L44,"") | P44: =$H44*(O44/12) -> 0 | Q44: =IFERROR($I44*$J44/37*(1+PLPartner1)^Q$3*O44,"") | S44: =$H44*(R44/12) -> 0 | T44: =IFERROR($I44*$J44/37*(1+PLPartner1)^T$3*R44,"") | V44: =$H44*(U44/12) -> 0 | W44: =IFERROR($I44*$J44/37*(1+PLPartner1)^W$3*U44,"") | Y44: =$H44*(X44/12) -> 0 | Z44: =IFERROR($I44*$J44/37*(1+PLPartner1)^Z$3*X44,"") | AB44: =$H44*(AA44/12) -> 0 | AC44: =IFERROR($I44*$J44/37*(1+PLPartner1)^AC$3*AA44,"") | AE44: =$H44*(AD44/12) -> 0 | AF44: =IFERROR($I44*$J44/37*(1+PLPartner1)^AF$3*AD44,"") | AH44: =$H44*(AG44/12) -> 0 | AI44: =IFERROR($I44*$J44/37*(1+PLPartner1)^AI$3*AG44,"") | AK44: =$H44*(AJ44/12) -> 0 | AL44: =IFERROR($I44*$J44/37*(1+PLPartner1)^AL$3*AJ44,"") | AN44: =$H44*(AM44/12) -> 0 | AO44: =IFERROR($I44*$J44/37*(1+PLPartner1)^AO$3*AM44,"") | AP44: =SUM(L44,O44,R44,U44,X44,AA44,AD44,AG44,AJ44,AM44) -> 0 | AQ44: =SUM(M44,P44,S44,V44,Y44,AB44,AE44,AH44,AK44,AN44) -> 0 | AR44: =SUM(N44,Q44,T44,W44,Z44,AC44,AF44,AI44,AL44,AO44) -> 0 | AT44: =AQ44*$AT$18 -> 0
C45: - | H45: =J45/37 -> 1 | I45: =_xlfn.XLOOKUP(C45,'AU salary costs 2025'!$B$7:$B$35,'AU salary costs 2025'!$D$7:$D$35, "-") -> - | J45: 37 | M45: =$H45*(L45/12) -> 0 | N45: =IFERROR($I45*$J45/37*(1+PLPartner1)^N$3*L45,"") | P45: =$H45*(O45/12) -> 0 | Q45: =IFERROR($I45*$J45/37*(1+PLPartner1)^Q$3*O45,"") | S45: =$H45*(R45/12) -> 0 | T45: =IFERROR($I45*$J45/37*(1+PLPartner1)^T$3*R45,"") | V45: =$H45*(U45/12) -> 0 | W45: =IFERROR($I45*$J45/37*(1+PLPartner1)^W$3*U45,"") | Y45: =$H45*(X45/12) -> 0 | Z45: =IFERROR($I45*$J45/37*(1+PLPartner1)^Z$3*X45,"") | AB45: =$H45*(AA45/12) -> 0 | AC45: =IFERROR($I45*$J45/37*(1+PLPartner1)^AC$3*AA45,"") | AE45: =$H45*(AD45/12) -> 0 | AF45: =IFERROR($I45*$J45/37*(1+PLPartner1)^AF$3*AD45,"") | AH45: =$H45*(AG45/12) -> 0 | AI45: =IFERROR($I45*$J45/37*(1+PLPartner1)^AI$3*AG45,"") | AK45: =$H45*(AJ45/12) -> 0 | AL45: =IFERROR($I45*$J45/37*(1+PLPartner1)^AL$3*AJ45,"") | AN45: =$H45*(AM45/12) -> 0 | AO45: =IFERROR($I45*$J45/37*(1+PLPartner1)^AO$3*AM45,"") | AP45: =SUM(L45,O45,R45,U45,X45,AA45,AD45,AG45,AJ45,AM45) -> 0 | AQ45: =SUM(M45,P45,S45,V45,Y45,AB45,AE45,AH45,AK45,AN45) -> 0 | AR45: =SUM(N45,Q45,T45,W45,Z45,AC45,AF45,AI45,AL45,AO45) -> 0 | AT45: =AQ45*$AT$18 -> 0
C46: - | H46: =J46/37 -> 1 | I46: =_xlfn.XLOOKUP(C46,'AU salary costs 2025'!$B$7:$B$35,'AU salary costs 2025'!$D$7:$D$35, "-") -> - | J46: 37 | M46: =$H46*(L46/12) -> 0 | N46: =IFERROR($I46*$J46/37*(1+PLPartner1)^N$3*L46,"") | P46: =$H46*(O46/12) -> 0 | Q46: =IFERROR($I46*$J46/37*(1+PLPartner1)^Q$3*O46,"") | S46: =$H46*(R46/12) -> 0 | T46: =IFERROR($I46*$J46/37*(1+PLPartner1)^T$3*R46,"") | V46: =$H46*(U46/12) -> 0 | W46: =IFERROR($I46*$J46/37*(1+PLPartner1)^W$3*U46,"") | Y46: =$H46*(X46/12) -> 0 | Z46: =IFERROR($I46*$J46/37*(1+PLPartner1)^Z$3*X46,"") | AB46: =$H46*(AA46/12) -> 0 | AC46: =IFERROR($I46*$J46/37*(1+PLPartner1)^AC$3*AA46,"") | AE46: =$H46*(AD46/12) -> 0 | AF46: =IFERROR($I46*$J46/37*(1+PLPartner1)^AF$3*AD46,"") | AH46: =$H46*(AG46/12) -> 0 | AI46: =IFERROR($I46*$J46/37*(1+PLPartner1)^AI$3*AG46,"") | AK46: =$H46*(AJ46/12) -> 0 | AL46: =IFERROR($I46*$J46/37*(1+PLPartner1)^AL$3*AJ46,"") | AN46: =$H46*(AM46/12) -> 0 | AO46: =IFERROR($I46*$J46/37*(1+PLPartner1)^AO$3*AM46,"") | AP46: =SUM(L46,O46,R46,U46,X46,AA46,AD46,AG46,AJ46,AM46) -> 0 | AQ46: =SUM(M46,P46,S46,V46,Y46,AB46,AE46,AH46,AK46,AN46) -> 0 | AR46: =SUM(N46,Q46,T46,W46,Z46,AC46,AF46,AI46,AL46,AO46) -> 0 | AT46: =AQ46*$AT$18 -> 0
C47: - | H47: =J47/37 -> 1 | I47: =_xlfn.XLOOKUP(C47,'AU salary costs 2025'!$B$7:$B$35,'AU salary costs 2025'!$D$7:$D$35, "-") -> - | J47: 37 | M47: =$H47*(L47/12) -> 0 | N47: =IFERROR($I47*$J47/37*(1+PLPartner1)^N$3*L47,"") | P47: =$H47*(O47/12) -> 0 | Q47: =IFERROR($I47*$J47/37*(1+PLPartner1)^Q$3*O47,"") | S47: =$H47*(R47/12) -> 0 | T47: =IFERROR($I47*$J47/37*(1+PLPartner1)^T$3*R47,"") | V47: =$H47*(U47/12) -> 0 | W47: =IFERROR($I47*$J47/37*(1+PLPartner1)^W$3*U47,"") | Y47: =$H47*(X47/12) -> 0 | Z47: =IFERROR($I47*$J47/37*(1+PLPartner1)^Z$3*X47,"") | AB47: =$H47*(AA47/12) -> 0 | AC47: =IFERROR($I47*$J47/37*(1+PLPartner1)^AC$3*AA47,"") | AE47: =$H47*(AD47/12) -> 0 | AF47: =IFERROR($I47*$J47/37*(1+PLPartner1)^AF$3*AD47,"") | AH47: =$H47*(AG47/12) -> 0 | AI47: =IFERROR($I47*$J47/37*(1+PLPartner1)^AI$3*AG47,"") | AK47: =$H47*(AJ47/12) -> 0 | AL47: =IFERROR($I47*$J47/37*(1+PLPartner1)^AL$3*AJ47,"") | AN47: =$H47*(AM47/12) -> 0 | AO47: =IFERROR($I47*$J47/37*(1+PLPartner1)^AO$3*AM47,"") | AP47: =SUM(L47,O47,R47,U47,X47,AA47,AD47,AG47,AJ47,AM47) -> 0 | AQ47: =SUM(M47,P47,S47,V47,Y47,AB47,AE47,AH47,AK47,AN47) -> 0 | AR47: =SUM(N47,Q47,T47,W47,Z47,AC47,AF47,AI47,AL47,AO47) -> 0 | AT47: =AQ47*$AT$18 -> 0
C48: - | H48: =J48/37 -> 1 | I48: =_xlfn.XLOOKUP(C48,'AU salary costs 2025'!$B$7:$B$35,'AU salary costs 2025'!$D$7:$D$35, "-") -> - | J48: 37 | M48: =$H48*(L48/12) -> 0 | N48: =IFERROR($I48*$J48/37*(1+PLPartner1)^N$3*L48,"") | P48: =$H48*(O48/12) -> 0 | Q48: =IFERROR($I48*$J48/37*(1+PLPartner1)^Q$3*O48,"") | S48: =$H48*(R48/12) -> 0 | T48: =IFERROR($I48*$J48/37*(1+PLPartner1)^T$3*R48,"") | V48: =$H48*(U48/12) -> 0 | W48: =IFERROR($I48*$J48/37*(1+PLPartner1)^W$3*U48,"") | Y48: =$H48*(X48/12) -> 0 | Z48: =IFERROR($I48*$J48/37*(1+PLPartner1)^Z$3*X48,"") | AB48: =$H48*(AA48/12) -> 0 | AC48: =IFERROR($I48*$J48/37*(1+PLPartner1)^AC$3*AA48,"") | AE48: =$H48*(AD48/12) -> 0 | AF48: =IFERROR($I48*$J48/37*(1+PLPartner1)^AF$3*AD48,"") | AH48: =$H48*(AG48/12) -> 0 | AI48: =IFERROR($I48*$J48/37*(1+PLPartner1)^AI$3*AG48,"") | AK48: =$H48*(AJ48/12) -> 0 | AL48: =IFERROR($I48*$J48/37*(1+PLPartner1)^AL$3*AJ48,"") | AN48: =$H48*(AM48/12) -> 0 | AO48: =IFERROR($I48*$J48/37*(1+PLPartner1)^AO$3*AM48,"") | AP48: =SUM(L48,O48,R48,U48,X48,AA48,AD48,AG48,AJ48,AM48) -> 0 | AQ48: =SUM(M48,P48,S48,V48,Y48,AB48,AE48,AH48,AK48,AN48) -> 0 | AR48: =SUM(N48,Q48,T48,W48,Z48,AC48,AF48,AI48,AL48,AO48) -> 0 | AT48: =AQ48*$AT$18 -> 0
C49: - | H49: =J49/37 -> 1 | I49: =_xlfn.XLOOKUP(C49,'AU salary costs 2025'!$B$7:$B$35,'AU salary costs 2025'!$D$7:$D$35, "-") -> - | J49: 37 | M49: =$H49*(L49/12) -> 0 | N49: =IFERROR($I49*$J49/37*(1+PLPartner1)^N$3*L49,"") | P49: =$H49*(O49/12) -> 0 | Q49: =IFERROR($I49*$J49/37*(1+PLPartner1)^Q$3*O49,"") | S49: =$H49*(R49/12) -> 0 | T49: =IFERROR($I49*$J49/37*(1+PLPartner1)^T$3*R49,"") | V49: =$H49*(U49/12) -> 0 | W49: =IFERROR($I49*$J49/37*(1+PLPartner1)^W$3*U49,"") | Y49: =$H49*(X49/12) -> 0 | Z49: =IFERROR($I49*$J49/37*(1+PLPartner1)^Z$3*X49,"") | AB49: =$H49*(AA49/12) -> 0 | AC49: =IFERROR($I49*$J49/37*(1+PLPartner1)^AC$3*AA49,"") | AE49: =$H49*(AD49/12) -> 0 | AF49: =IFERROR($I49*$J49/37*(1+PLPartner1)^AF$3*AD49,"") | AH49: =$H49*(AG49/12) -> 0 | AI49: =IFERROR($I49*$J49/37*(1+PLPartner1)^AI$3*AG49,"") | AK49: =$H49*(AJ49/12) -> 0 | AL49: =IFERROR($I49*$J49/37*(1+PLPartner1)^AL$3*AJ49,"") | AN49: =$H49*(AM49/12) -> 0 | AO49: =IFERROR($I49*$J49/37*(1+PLPartner1)^AO$3*AM49,"") | AP49: =SUM(L49,O49,R49,U49,X49,AA49,AD49,AG49,AJ49,AM49) -> 0 | AQ49: =SUM(M49,P49,S49,V49,Y49,AB49,AE49,AH49,AK49,AN49) -> 0 | AR49: =SUM(N49,Q49,T49,W49,Z49,AC49,AF49,AI49,AL49,AO49) -> 0 | AT49: =AQ49*$AT$18 -> 0
... C53: - | H53: =J53/37 -> 1 | I53: =_xlfn.XLOOKUP(C53,'AU salary costs 2025'!$B$7:$B$35,'AU salary costs 2025'!$D$7:$D$35, "-") -> - | J53: 37 | M53: =$H53*(L53/12) -> 0 | N53: =IFERROR($I53*$J53/37*(1+PLPartner1)^N$3*L53,"") | P53: =$H53*(O53/12) -> 0 | Q53: =IFERROR($I53*$J53/37*(1+PLPartner1)^Q$3*O53,"") | S53: =$H53*(R53/12) -> 0 | T53: =IFERROR($I53*$J53/37*(1+PLPartner1)^T$3*R53,"") | V53: =$H53*(U53/12) -> 0 | W53: =IFERROR($I53*$J53/37*(1+PLPartner1)^W$3*U53,"") | Y53: =$H53*(X53/12) -> 0 | Z53: =IFERROR($I53*$J53/37*(1+PLPartner1)^Z$3*X53,"") | AB53: =$H53*(AA53/12) -> 0 | AC53: =IFERROR($I53*$J53/37*(1+PLPartner1)^AC$3*AA53,"") | AE53: =$H53*(AD53/12) -> 0 | AF53: =IFERROR($I53*$J53/37*(1+PLPartner1)^AF$3*AD53,"") | AH53: =$H53*(AG53/12) -> 0 | AI53: =IFERROR($I53*$J53/37*(1+PLPartner1)^AI$3*AG53,"") | AK53: =$H53*(AJ53/12) -> 0 | AL53: =IFERROR($I53*$J53/37*(1+PLPartner1)^AL$3*AJ53,"") | AN53: =$H53*(AM53/12) -> 0 | AO53: =IFERROR($I53*$J53/37*(1+PLPartner1)^AO$3*AM53,"") | AP53: =SUM(L53,O53,R53,U53,X53,AA53,AD53,AG53,AJ53,AM53) -> 0 | AQ53: =SUM(M53,P53,S53,V53,Y53,AB53,AE53,AH53,AK53,AN53) -> 0 | AR53: =SUM(N53,Q53,T53,W53,Z53,AC53,AF53,AI53,AL53,AO53) -> 0 | AT53: =AQ53*$AT$18 -> 0
K54: Sum of VIP co-financing | L54: =SUM(L38:L53) -> 0 | M54: =SUM(M38:M53) -> 0 | N54: =SUM(N38:N53) -> 0 | O54: =SUM(O38:O53) -> 0 | P54: =SUM(P38:P53) -> 0 | Q54: =SUM(Q38:Q53) -> 0 | R54: =SUM(R38:R53) -> 0 | S54: =SUM(S38:S53) -> 0 | ... AR54: =SUM(AR38:AR53) -> 0 | AT54: =AQ54*$AT$18 -> 0
C55: 1. TAP | F55: =F19 -> Notes/Name | I55: =I19 -> Salary/mo 2025 | J55: =J19 -> Hrs/wk | K55: =$K$19 -> Dept.Serv. | AT55: TAP hours
C56: AC staff et al. | H56: =J56/37 -> 1 | I56: =_xlfn.XLOOKUP(C56,'AU salary costs 2025'!$B$7:$B$35,'AU salary costs 2025'!$D$7:$D$35, "-") -> 52000 | J56: 37 | K56: Yes | M56: =$H56*(L56/12) -> 0 | N56: =IFERROR($I56*$J56/37*(1+PLPartner1)^N$3*L56,"") -> 0 | P56: =$H56*(O56/12) -> 0 | Q56: =IFERROR($I56*$J56/37*(1+PLPartner1)^Q$3*O56,"") -> 0 | S56: =$H56*(R56/12) -> 0 | T56: =IFERROR($I56*$J56/37*(1+PLPartner1)^T$3*R56,"") -> 0 | V56: =$H56*(U56/12) -> 0 | W56: =IFERROR($I56*$J56/37*(1+PLPartner1)^W$3*U56,"") -> 0 | Y56: =$H56*(X56/12) -> 0 | Z56: =IFERROR($I56*$J56/37*(1+PLPartner1)^Z$3*X56,"") -> 0 | AB56: =$H56*(AA56/12) -> 0 | AC56: =IFERROR($I56*$J56/37*(1+PLPartner1)^AC$3*AA56,"") -> 0 | AE56: =$H56*(AD56/12) -> 0 | AF56: =IFERROR($I56*$J56/37*(1+PLPartner1)^AF$3*AD56,"") -> 0 | AH56: =$H56*(AG56/12) -> 0 | AI56: =IFERROR($I56*$J56/37*(1+PLPartner1)^AI$3*AG56,"") -> 0 | AK56: =$H56*(AJ56/12) -> 0 | AL56: =IFERROR($I56*$J56/37*(1+PLPartner1)^AL$3*AJ56,"") -> 0 | AN56: =$H56*(AM56/12) -> 0 | AO56: =IFERROR($I56*$J56/37*(1+PLPartner1)^AO$3*AM56,"") -> 0 | AP56: =SUM(L56,O56,R56,U56,X56,AA56,AD56,AG56,AJ56,AM56) -> 0 | AQ56: =SUM(M56,P56,S56,V56,Y56,AB56,AE56,AH56,AK56,AN56) -> 0 | AR56: =SUM(N56,Q56,T56,W56,Z56,AC56,AF56,AI56,AL56,AO56) -> 0 | AT56: =AQ56*$AT$18 -> 0
C57: - | H57: =J57/37 -> 1 | I57: =_xlfn.XLOOKUP(C57,'AU salary costs 2025'!$B$7:$B$35,'AU salary costs 2025'!$D$7:$D$35, "-") -> - | J57: 37 | M57: =$H57*(L57/12) -> 0 | N57: =IFERROR($I57*$J57/37*(1+PLPartner1)^N$3*L57,"") | P57: =$H57*(O57/12) -> 0 | Q57: =IFERROR($I57*$J57/37*(1+PLPartner1)^Q$3*O57,"") | S57: =$H57*(R57/12) -> 0 | T57: =IFERROR($I57*$J57/37*(1+PLPartner1)^T$3*R57,"") | V57: =$H57*(U57/12) -> 0 | W57: =IFERROR($I57*$J57/37*(1+PLPartner1)^W$3*U57,"") | Y57: =$H57*(X57/12) -> 0 | Z57: =IFERROR($I57*$J57/37*(1+PLPartner1)^Z$3*X57,"") | AB57: =$H57*(AA57/12) -> 0 | AC57: =IFERROR($I57*$J57/37*(1+PLPartner1)^AC$3*AA57,"") | AE57: =$H57*(AD57/12) -> 0 | AF57: =IFERROR($I57*$J57/37*(1+PLPartner1)^AF$3*AD57,"") | AH57: =$H57*(AG57/12) -> 0 | AI57: =IFERROR($I57*$J57/37*(1+PLPartner1)^AI$3*AG57,"") | AK57: =$H57*(AJ57/12) -> 0 | AL57: =IFERROR($I57*$J57/37*(1+PLPartner1)^AL$3*AJ57,"") | AN57: =$H57*(AM57/12) -> 0 | AO57: =IFERROR($I57*$J57/37*(1+PLPartner1)^AO$3*AM57,"") | AP57: =SUM(L57,O57,R57,U57,X57,AA57,AD57,AG57,AJ57,AM57) -> 0 | AQ57: =SUM(M57,P57,S57,V57,Y57,AB57,AE57,AH57,AK57,AN57) -> 0 | AR57: =SUM(N57,Q57,T57,W57,Z57,AC57,AF57,AI57,AL57,AO57) -> 0 | AT57: =AQ57*$AT$18 -> 0
C58: - | H58: =J58/37 -> 1 | I58: =_xlfn.XLOOKUP(C58,'AU salary costs 2025'!$B$7:$B$35,'AU salary costs 2025'!$D$7:$D$35, "-") -> - | J58: 37 | M58: =$H58*(L58/12) -> 0 | N58: =IFERROR($I58*$J58/37*(1+PLPartner1)^N$3*L58,"") | P58: =$H58*(O58/12) -> 0 | Q58: =IFERROR($I58*$J58/37*(1+PLPartner1)^Q$3*O58,"") | S58: =$H58*(R58/12) -> 0 | T58: =IFERROR($I58*$J58/37*(1+PLPartner1)^T$3*R58,"") | V58: =$H58*(U58/12) -> 0 | W58: =IFERROR($I58*$J58/37*(1+PLPartner1)^W$3*U58,"") | Y58: =$H58*(X58/12) -> 0 | Z58: =IFERROR($I58*$J58/37*(1+PLPartner1)^Z$3*X58,"") | AB58: =$H58*(AA58/12) -> 0 | AC58: =IFERROR($I58*$J58/37*(1+PLPartner1)^AC$3*AA58,"") | AE58: =$H58*(AD58/12) -> 0 | AF58: =IFERROR($I58*$J58/37*(1+PLPartner1)^AF$3*AD58,"") | AH58: =$H58*(AG58/12) -> 0 | AI58: =IFERROR($I58*$J58/37*(1+PLPartner1)^AI$3*AG58,"") | AK58: =$H58*(AJ58/12) -> 0 | AL58: =IFERROR($I58*$J58/37*(1+PLPartner1)^AL$3*AJ58,"") | AN58: =$H58*(AM58/12) -> 0 | AO58: =IFERROR($I58*$J58/37*(1+PLPartner1)^AO$3*AM58,"") | AP58: =SUM(L58,O58,R58,U58,X58,AA58,AD58,AG58,AJ58,AM58) -> 0 | AQ58: =SUM(M58,P58,S58,V58,Y58,AB58,AE58,AH58,AK58,AN58) -> 0 | AR58: =SUM(N58,Q58,T58,W58,Z58,AC58,AF58,AI58,AL58,AO58) -> 0 | AT58: =AQ58*$AT$18 -> 0
C59: - | H59: =J59/37 -> 1 | I59: =_xlfn.XLOOKUP(C59,'AU salary costs 2025'!$B$7:$B$35,'AU salary costs 2025'!$D$7:$D$35, "-") -> - | J59: 37 | M59: =$H59*(L59/12) -> 0 | N59: =IFERROR($I59*$J59/37*(1+PLPartner1)^N$3*L59,"") | P59: =$H59*(O59/12) -> 0 | Q59: =IFERROR($I59*$J59/37*(1+PLPartner1)^Q$3*O59,"") | S59: =$H59*(R59/12) -> 0 | T59: =IFERROR($I59*$J59/37*(1+PLPartner1)^T$3*R59,"") | V59: =$H59*(U59/12) -> 0 | W59: =IFERROR($I59*$J59/37*(1+PLPartner1)^W$3*U59,"") | Y59: =$H59*(X59/12) -> 0 | Z59: =IFERROR($I59*$J59/37*(1+PLPartner1)^Z$3*X59,"") | AB59: =$H59*(AA59/12) -> 0 | AC59: =IFERROR($I59*$J59/37*(1+PLPartner1)^AC$3*AA59,"") | AE59: =$H59*(AD59/12) -> 0 | AF59: =IFERROR($I59*$J59/37*(1+PLPartner1)^AF$3*AD59,"") | AH59: =$H59*(AG59/12) -> 0 | AI59: =IFERROR($I59*$J59/37*(1+PLPartner1)^AI$3*AG59,"") | AK59: =$H59*(AJ59/12) -> 0 | AL59: =IFERROR($I59*$J59/37*(1+PLPartner1)^AL$3*AJ59,"") | AN59: =$H59*(AM59/12) -> 0 | AO59: =IFERROR($I59*$J59/37*(1+PLPartner1)^AO$3*AM59,"") | AP59: =SUM(L59,O59,R59,U59,X59,AA59,AD59,AG59,AJ59,AM59) -> 0 | AQ59: =SUM(M59,P59,S59,V59,Y59,AB59,AE59,AH59,AK59,AN59) -> 0 | AR59: =SUM(N59,Q59,T59,W59,Z59,AC59,AF59,AI59,AL59,AO59) -> 0 | AT59: =AQ59*$AT$18 -> 0
C60: - | H60: =J60/37 -> 1 | I60: =_xlfn.XLOOKUP(C60,'AU salary costs 2025'!$B$7:$B$35,'AU salary costs 2025'!$D$7:$D$35, "-") -> - | J60: 37 | M60: =$H60*(L60/12) -> 0 | N60: =IFERROR($I60*$J60/37*(1+PLPartner1)^N$3*L60,"") | P60: =$H60*(O60/12) -> 0 | Q60: =IFERROR($I60*$J60/37*(1+PLPartner1)^Q$3*O60,"") | S60: =$H60*(R60/12) -> 0 | T60: =IFERROR($I60*$J60/37*(1+PLPartner1)^T$3*R60,"") | V60: =$H60*(U60/12) -> 0 | W60: =IFERROR($I60*$J60/37*(1+PLPartner1)^W$3*U60,"") | Y60: =$H60*(X60/12) -> 0 | Z60: =IFERROR($I60*$J60/37*(1+PLPartner1)^Z$3*X60,"") | AB60: =$H60*(AA60/12) -> 0 | AC60: =IFERROR($I60*$J60/37*(1+PLPartner1)^AC$3*AA60,"") | AE60: =$H60*(AD60/12) -> 0 | AF60: =IFERROR($I60*$J60/37*(1+PLPartner1)^AF$3*AD60,"") | AH60: =$H60*(AG60/12) -> 0 | AI60: =IFERROR($I60*$J60/37*(1+PLPartner1)^AI$3*AG60,"") | AK60: =$H60*(AJ60/12) -> 0 | AL60: =IFERROR($I60*$J60/37*(1+PLPartner1)^AL$3*AJ60,"") | AN60: =$H60*(AM60/12) -> 0 | AO60: =IFERROR($I60*$J60/37*(1+PLPartner1)^AO$3*AM60,"") | AP60: =SUM(L60,O60,R60,U60,X60,AA60,AD60,AG60,AJ60,AM60) -> 0 | AQ60: =SUM(M60,P60,S60,V60,Y60,AB60,AE60,AH60,AK60,AN60) -> 0 | AR60: =SUM(N60,Q60,T60,W60,Z60,AC60,AF60,AI60,AL60,AO60) -> 0 | AT60: =AQ60*$AT$18 -> 0
C61: - | H61: =J61/37 -> 1 | I61: =_xlfn.XLOOKUP(C61,'AU salary costs 2025'!$B$7:$B$35,'AU salary costs 2025'!$D$7:$D$35, "-") -> - | J61: 37 | M61: =$H61*(L61/12) -> 0 | N61: =IFERROR($I61*$J61/37*(1+PLPartner1)^N$3*L61,"") | P61: =$H61*(O61/12) -> 0 | Q61: =IFERROR($I61*$J61/37*(1+PLPartner1)^Q$3*O61,"") | S61: =$H61*(R61/12) -> 0 | T61: =IFERROR($I61*$J61/37*(1+PLPartner1)^T$3*R61,"") | V61: =$H61*(U61/12) -> 0 | W61: =IFERROR($I61*$J61/37*(1+PLPartner1)^W$3*U61,"") | Y61: =$H61*(X61/12) -> 0 | Z61: =IFERROR($I61*$J61/37*(1+PLPartner1)^Z$3*X61,"") | AB61: =$H61*(AA61/12) -> 0 | AC61: =IFERROR($I61*$J61/37*(1+PLPartner1)^AC$3*AA61,"") | AE61: =$H61*(AD61/12) -> 0 | AF61: =IFERROR($I61*$J61/37*(1+PLPartner1)^AF$3*AD61,"") | AH61: =$H61*(AG61/12) -> 0 | AI61: =IFERROR($I61*$J61/37*(1+PLPartner1)^AI$3*AG61,"") | AK61: =$H61*(AJ61/12) -> 0 | AL61: =IFERROR($I61*$J61/37*(1+PLPartner1)^AL$3*AJ61,"") | AN61: =$H61*(AM61/12) -> 0 | AO61: =IFERROR($I61*$J61/37*(1+PLPartner1)^AO$3*AM61,"") | AP61: =SUM(L61,O61,R61,U61,X61,AA61,AD61,AG61,AJ61,AM61) -> 0 | AQ61: =SUM(M61,P61,S61,V61,Y61,AB61,AE61,AH61,AK61,AN61) -> 0 | AR61: =SUM(N61,Q61,T61,W61,Z61,AC61,AF61,AI61,AL61,AO61) -> 0 | AT61: =AQ61*$AT$18 -> 0
C62: - | H62: =J62/37 -> 1 | I62: =_xlfn.XLOOKUP(C62,'AU salary costs 2025'!$B$7:$B$35,'AU salary costs 2025'!$D$7:$D$35, "-") -> - | J62: 37 | M62: =$H62*(L62/12) -> 0 | N62: =IFERROR($I62*$J62/37*(1+PLPartner1)^N$3*L62,"") | P62: =$H62*(O62/12) -> 0 | Q62: =IFERROR($I62*$J62/37*(1+PLPartner1)^Q$3*O62,"") | S62: =$H62*(R62/12) -> 0 | T62: =IFERROR($I62*$J62/37*(1+PLPartner1)^T$3*R62,"") | V62: =$H62*(U62/12) -> 0 | W62: =IFERROR($I62*$J62/37*(1+PLPartner1)^W$3*U62,"") | Y62: =$H62*(X62/12) -> 0 | Z62: =IFERROR($I62*$J62/37*(1+PLPartner1)^Z$3*X62,"") | AB62: =$H62*(AA62/12) -> 0 | AC62: =IFERROR($I62*$J62/37*(1+PLPartner1)^AC$3*AA62,"") | AE62: =$H62*(AD62/12) -> 0 | AF62: =IFERROR($I62*$J62/37*(1+PLPartner1)^AF$3*AD62,"") | AH62: =$H62*(AG62/12) -> 0 | AI62: =IFERROR($I62*$J62/37*(1+PLPartner1)^AI$3*AG62,"") | AK62: =$H62*(AJ62/12) -> 0 | AL62: =IFERROR($I62*$J62/37*(1+PLPartner1)^AL$3*AJ62,"") | AN62: =$H62*(AM62/12) -> 0 | AO62: =IFERROR($I62*$J62/37*(1+PLPartner1)^AO$3*AM62,"") | AP62: =SUM(L62,O62,R62,U62,X62,AA62,AD62,AG62,AJ62,AM62) -> 0 | AQ62: =SUM(M62,P62,S62,V62,Y62,AB62,AE62,AH62,AK62,AN62) -> 0 | AR62: =SUM(N62,Q62,T62,W62,Z62,AC62,AF62,AI62,AL62,AO62) -> 0 | AT62: =AQ62*$AT$18 -> 0
C63: - | H63: =J63/37 -> 1 | I63: =_xlfn.XLOOKUP(C63,'AU salary costs 2025'!$B$7:$B$35,'AU salary costs 2025'!$D$7:$D$35, "-") -> - | J63: 37 | M63: =$H63*(L63/12) -> 0 | N63: =IFERROR($I63*$J63/37*(1+PLPartner1)^N$3*L63,"") | P63: =$H63*(O63/12) -> 0 | Q63: =IFERROR($I63*$J63/37*(1+PLPartner1)^Q$3*O63,"") | S63: =$H63*(R63/12) -> 0 | T63: =IFERROR($I63*$J63/37*(1+PLPartner1)^T$3*R63,"") | V63: =$H63*(U63/12) -> 0 | W63: =IFERROR($I63*$J63/37*(1+PLPartner1)^W$3*U63,"") | Y63: =$H63*(X63/12) -> 0 | Z63: =IFERROR($I63*$J63/37*(1+PLPartner1)^Z$3*X63,"") | AB63: =$H63*(AA63/12) -> 0 | AC63: =IFERROR($I63*$J63/37*(1+PLPartner1)^AC$3*AA63,"") | AE63: =$H63*(AD63/12) -> 0 | AF63: =IFERROR($I63*$J63/37*(1+PLPartner1)^AF$3*AD63,"") | AH63: =$H63*(AG63/12) -> 0 | AI63: =IFERROR($I63*$J63/37*(1+PLPartner1)^AI$3*AG63,"") | AK63: =$H63*(AJ63/12) -> 0 | AL63: =IFERROR($I63*$J63/37*(1+PLPartner1)^AL$3*AJ63,"") | AN63: =$H63*(AM63/12) -> 0 | AO63: =IFERROR($I63*$J63/37*(1+PLPartner1)^AO$3*AM63,"") | AP63: =SUM(L63,O63,R63,U63,X63,AA63,AD63,AG63,AJ63,AM63) -> 0 | AQ63: =SUM(M63,P63,S63,V63,Y63,AB63,AE63,AH63,AK63,AN63) -> 0 | AR63: =SUM(N63,Q63,T63,W63,Z63,AC63,AF63,AI63,AL63,AO63) -> 0 | AT63: =AQ63*$AT$18 -> 0
C64: - | H64: =J64/37 -> 1 | I64: =_xlfn.XLOOKUP(C64,'AU salary costs 2025'!$B$7:$B$35,'AU salary costs 2025'!$D$7:$D$35, "-") -> - | J64: 37 | M64: =$H64*(L64/12) -> 0 | N64: =IFERROR($I64*$J64/37*(1+PLPartner1)^N$3*L64,"") | P64: =$H64*(O64/12) -> 0 | Q64: =IFERROR($I64*$J64/37*(1+PLPartner1)^Q$3*O64,"") | S64: =$H64*(R64/12) -> 0 | T64: =IFERROR($I64*$J64/37*(1+PLPartner1)^T$3*R64,"") | V64: =$H64*(U64/12) -> 0 | W64: =IFERROR($I64*$J64/37*(1+PLPartner1)^W$3*U64,"") | Y64: =$H64*(X64/12) -> 0 | Z64: =IFERROR($I64*$J64/37*(1+PLPartner1)^Z$3*X64,"") | AB64: =$H64*(AA64/12) -> 0 | AC64: =IFERROR($I64*$J64/37*(1+PLPartner1)^AC$3*AA64,"") | AE64: =$H64*(AD64/12) -> 0 | AF64: =IFERROR($I64*$J64/37*(1+PLPartner1)^AF$3*AD64,"") | AH64: =$H64*(AG64/12) -> 0 | AI64: =IFERROR($I64*$J64/37*(1+PLPartner1)^AI$3*AG64,"") | AK64: =$H64*(AJ64/12) -> 0 | AL64: =IFERROR($I64*$J64/37*(1+PLPartner1)^AL$3*AJ64,"") | AN64: =$H64*(AM64/12) -> 0 | AO64: =IFERROR($I64*$J64/37*(1+PLPartner1)^AO$3*AM64,"") | AP64: =SUM(L64,O64,R64,U64,X64,AA64,AD64,AG64,AJ64,AM64) -> 0 | AQ64: =SUM(M64,P64,S64,V64,Y64,AB64,AE64,AH64,AK64,AN64) -> 0 | AR64: =SUM(N64,Q64,T64,W64,Z64,AC64,AF64,AI64,AL64,AO64) -> 0 | AT64: =AQ64*$AT$18 -> 0
C65: - | H65: =J65/37 -> 1 | I65: =_xlfn.XLOOKUP(C65,'AU salary costs 2025'!$B$7:$B$35,'AU salary costs 2025'!$D$7:$D$35, "-") -> - | J65: 37 | M65: =$H65*(L65/12) -> 0 | N65: =IFERROR($I65*$J65/37*(1+PLPartner1)^N$3*L65,"") | P65: =$H65*(O65/12) -> 0 | Q65: =IFERROR($I65*$J65/37*(1+PLPartner1)^Q$3*O65,"") | S65: =$H65*(R65/12) -> 0 | T65: =IFERROR($I65*$J65/37*(1+PLPartner1)^T$3*R65,"") | V65: =$H65*(U65/12) -> 0 | W65: =IFERROR($I65*$J65/37*(1+PLPartner1)^W$3*U65,"") | Y65: =$H65*(X65/12) -> 0 | Z65: =IFERROR($I65*$J65/37*(1+PLPartner1)^Z$3*X65,"") | AB65: =$H65*(AA65/12) -> 0 | AC65: =IFERROR($I65*$J65/37*(1+PLPartner1)^AC$3*AA65,"") | AE65: =$H65*(AD65/12) -> 0 | AF65: =IFERROR($I65*$J65/37*(1+PLPartner1)^AF$3*AD65,"") | AH65: =$H65*(AG65/12) -> 0 | AI65: =IFERROR($I65*$J65/37*(1+PLPartner1)^AI$3*AG65,"") | AK65: =$H65*(AJ65/12) -> 0 | AL65: =IFERROR($I65*$J65/37*(1+PLPartner1)^AL$3*AJ65,"") | AN65: =$H65*(AM65/12) -> 0 | AO65: =IFERROR($I65*$J65/37*(1+PLPartner1)^AO$3*AM65,"") | AP65: =SUM(L65,O65,R65,U65,X65,AA65,AD65,AG65,AJ65,AM65) -> 0 | AQ65: =SUM(M65,P65,S65,V65,Y65,AB65,AE65,AH65,AK65,AN65) -> 0 | AR65: =SUM(N65,Q65,T65,W65,Z65,AC65,AF65,AI65,AL65,AO65) -> 0 | AT65: =AQ65*$AT$18 -> 0
C66: - | H66: =J66/37 -> 1 | I66: =_xlfn.XLOOKUP(C66,'AU salary costs 2025'!$B$7:$B$35,'AU salary costs 2025'!$D$7:$D$35, "-") -> - | J66: 37 | M66: =$H66*(L66/12) -> 0 | N66: =IFERROR($I66*$J66/37*(1+PLPartner1)^N$3*L66,"") | P66: =$H66*(O66/12) -> 0 | Q66: =IFERROR($I66*$J66/37*(1+PLPartner1)^Q$3*O66,"") | S66: =$H66*(R66/12) -> 0 | T66: =IFERROR($I66*$J66/37*(1+PLPartner1)^T$3*R66,"") | V66: =$H66*(U66/12) -> 0 | W66: =IFERROR($I66*$J66/37*(1+PLPartner1)^W$3*U66,"") | Y66: =$H66*(X66/12) -> 0 | Z66: =IFERROR($I66*$J66/37*(1+PLPartner1)^Z$3*X66,"") | AB66: =$H66*(AA66/12) -> 0 | AC66: =IFERROR($I66*$J66/37*(1+PLPartner1)^AC$3*AA66,"") | AE66: =$H66*(AD66/12) -> 0 | AF66: =IFERROR($I66*$J66/37*(1+PLPartner1)^AF$3*AD66,"") | AH66: =$H66*(AG66/12) -> 0 | AI66: =IFERROR($I66*$J66/37*(1+PLPartner1)^AI$3*AG66,"") | AK66: =$H66*(AJ66/12) -> 0 | AL66: =IFERROR($I66*$J66/37*(1+PLPartner1)^AL$3*AJ66,"") | AN66: =$H66*(AM66/12) -> 0 | AO66: =IFERROR($I66*$J66/37*(1+PLPartner1)^AO$3*AM66,"") | AP66: =SUM(L66,O66,R66,U66,X66,AA66,AD66,AG66,AJ66,AM66) -> 0 | AQ66: =SUM(M66,P66,S66,V66,Y66,AB66,AE66,AH66,AK66,AN66) -> 0 | AR66: =SUM(N66,Q66,T66,W66,Z66,AC66,AF66,AI66,AL66,AO66) -> 0 | AT66: =AQ66*$AT$18 -> 0
C67: - | H67: =J67/37 -> 1 | I67: =_xlfn.XLOOKUP(C67,'AU salary costs 2025'!$B$7:$B$35,'AU salary costs 2025'!$D$7:$D$35, "-") -> - | J67: 37 | M67: =$H67*(L67/12) -> 0 | N67: =IFERROR($I67*$J67/37*(1+PLPartner1)^N$3*L67,"") | P67: =$H67*(O67/12) -> 0 | Q67: =IFERROR($I67*$J67/37*(1+PLPartner1)^Q$3*O67,"") | S67: =$H67*(R67/12) -> 0 | T67: =IFERROR($I67*$J67/37*(1+PLPartner1)^T$3*R67,"") | V67: =$H67*(U67/12) -> 0 | W67: =IFERROR($I67*$J67/37*(1+PLPartner1)^W$3*U67,"") | Y67: =$H67*(X67/12) -> 0 | Z67: =IFERROR($I67*$J67/37*(1+PLPartner1)^Z$3*X67,"") | AB67: =$H67*(AA67/12) -> 0 | AC67: =IFERROR($I67*$J67/37*(1+PLPartner1)^AC$3*AA67,"") | AE67: =$H67*(AD67/12) -> 0 | AF67: =IFERROR($I67*$J67/37*(1+PLPartner1)^AF$3*AD67,"") | AH67: =$H67*(AG67/12) -> 0 | AI67: =IFERROR($I67*$J67/37*(1+PLPartner1)^AI$3*AG67,"") | AK67: =$H67*(AJ67/12) -> 0 | AL67: =IFERROR($I67*$J67/37*(1+PLPartner1)^AL$3*AJ67,"") | AN67: =$H67*(AM67/12) -> 0 | AO67: =IFERROR($I67*$J67/37*(1+PLPartner1)^AO$3*AM67,"") | AP67: =SUM(L67,O67,R67,U67,X67,AA67,AD67,AG67,AJ67,AM67) -> 0 | AQ67: =SUM(M67,P67,S67,V67,Y67,AB67,AE67,AH67,AK67,AN67) -> 0 | AR67: =SUM(N67,Q67,T67,W67,Z67,AC67,AF67,AI67,AL67,AO67) -> 0 | AT67: =AQ67*$AT$18 -> 0
C68: - | H68: =J68/37 -> 1 | I68: =_xlfn.XLOOKUP(C68,'AU salary costs 2025'!$B$7:$B$35,'AU salary costs 2025'!$D$7:$D$35, "-") -> - | J68: 37 | M68: =$H68*(L68/12) -> 0 | N68: =IFERROR($I68*$J68/37*(1+PLPartner1)^N$3*L68,"") | P68: =$H68*(O68/12) -> 0 | Q68: =IFERROR($I68*$J68/37*(1+PLPartner1)^Q$3*O68,"") | S68: =$H68*(R68/12) -> 0 | T68: =IFERROR($I68*$J68/37*(1+PLPartner1)^T$3*R68,"") | V68: =$H68*(U68/12) -> 0 | W68: =IFERROR($I68*$J68/37*(1+PLPartner1)^W$3*U68,"") | Y68: =$H68*(X68/12) -> 0 | Z68: =IFERROR($I68*$J68/37*(1+PLPartner1)^Z$3*X68,"") | AB68: =$H68*(AA68/12) -> 0 | AC68: =IFERROR($I68*$J68/37*(1+PLPartner1)^AC$3*AA68,"") | AE68: =$H68*(AD68/12) -> 0 | AF68: =IFERROR($I68*$J68/37*(1+PLPartner1)^AF$3*AD68,"") | AH68: =$H68*(AG68/12) -> 0 | AI68: =IFERROR($I68*$J68/37*(1+PLPartner1)^AI$3*AG68,"") | AK68: =$H68*(AJ68/12) -> 0 | AL68: =IFERROR($I68*$J68/37*(1+PLPartner1)^AL$3*AJ68,"") | AN68: =$H68*(AM68/12) -> 0 | AO68: =IFERROR($I68*$J68/37*(1+PLPartner1)^AO$3*AM68,"") | AP68: =SUM(L68,O68,R68,U68,X68,AA68,AD68,AG68,AJ68,AM68) -> 0 | AQ68: =SUM(M68,P68,S68,V68,Y68,AB68,AE68,AH68,AK68,AN68) -> 0 | AR68: =SUM(N68,Q68,T68,W68,Z68,AC68,AF68,AI68,AL68,AO68) -> 0 | AT68: =AQ68*$AT$18 -> 0
... C71: - | H71: =J71/37 -> 1 | I71: =_xlfn.XLOOKUP(C71,'AU salary costs 2025'!$B$7:$B$35,'AU salary costs 2025'!$D$7:$D$35, "-") -> - | J71: 37 | M71: =$H71*(L71/12) -> 0 | N71: =IFERROR($I71*$J71/37*(1+PLPartner1)^N$3*L71,"") | P71: =$H71*(O71/12) -> 0 | Q71: =IFERROR($I71*$J71/37*(1+PLPartner1)^Q$3*O71,"") | S71: =$H71*(R71/12) -> 0 | T71: =IFERROR($I71*$J71/37*(1+PLPartner1)^T$3*R71,"") | V71: =$H71*(U71/12) -> 0 | W71: =IFERROR($I71*$J71/37*(1+PLPartner1)^W$3*U71,"") | Y71: =$H71*(X71/12) -> 0 | Z71: =IFERROR($I71*$J71/37*(1+PLPartner1)^Z$3*X71,"") | AB71: =$H71*(AA71/12) -> 0 | AC71: =IFERROR($I71*$J71/37*(1+PLPartner1)^AC$3*AA71,"") | AE71: =$H71*(AD71/12) -> 0 | AF71: =IFERROR($I71*$J71/37*(1+PLPartner1)^AF$3*AD71,"") | AH71: =$H71*(AG71/12) -> 0 | AI71: =IFERROR($I71*$J71/37*(1+PLPartner1)^AI$3*AG71,"") | AK71: =$H71*(AJ71/12) -> 0 | AL71: =IFERROR($I71*$J71/37*(1+PLPartner1)^AL$3*AJ71,"") | AN71: =$H71*(AM71/12) -> 0 | AO71: =IFERROR($I71*$J71/37*(1+PLPartner1)^AO$3*AM71,"") | AP71: =SUM(L71,O71,R71,U71,X71,AA71,AD71,AG71,AJ71,AM71) -> 0 | AQ71: =SUM(M71,P71,S71,V71,Y71,AB71,AE71,AH71,AK71,AN71) -> 0 | AR71: =SUM(N71,Q71,T71,W71,Z71,AC71,AF71,AI71,AL71,AO71) -> 0 | AT71: =AQ71*$AT$18 -> 0
B72: B | K72: Subtotal | L72: =SUM(L56:L71) -> 0 | M72: =SUM(M56:M71) -> 0 | N72: =SUM(N56:N71) -> 0 | O72: =SUM(O56:O71) -> 0 | P72: =SUM(P56:P71) -> 0 | Q72: =SUM(Q56:Q71) -> 0 | R72: =SUM(R56:R71) -> 0 | S72: =SUM(S56:S71) -> 0 | ... AR72: =SUM(AR56:AR71) -> 0 | AT72: =AQ72*$AT$18 -> 0
C73: 1. TAP Co-financing | F73: =F19 -> Notes/Name | I73: =I19 -> Salary/mo 2025 | J73: =J19 -> Hrs/wk | AT73: Co-financed TAP hours
C74: - | H74: =J74/37 -> 1 | I74: =_xlfn.XLOOKUP(C74,'AU salary costs 2025'!$B$7:$B$35,'AU salary costs 2025'!$D$7:$D$35, "-") -> - | J74: 37 | M74: =$H74*(L74/12) -> 0 | N74: =IFERROR($I74*$J74/37*(1+PLPartner1)^N$3*L74,"") | P74: =$H74*(O74/12) -> 0 | Q74: =IFERROR($I74*$J74/37*(1+PLPartner1)^Q$3*O74,"") | S74: =$H74*(R74/12) -> 0 | T74: =IFERROR($I74*$J74/37*(1+PLPartner1)^T$3*R74,"") | V74: =$H74*(U74/12) -> 0 | W74: =IFERROR($I74*$J74/37*(1+PLPartner1)^W$3*U74,"") | Y74: =$H74*(X74/12) -> 0 | Z74: =IFERROR($I74*$J74/37*(1+PLPartner1)^Z$3*X74,"") | AB74: =$H74*(AA74/12) -> 0 | AC74: =IFERROR($I74*$J74/37*(1+PLPartner1)^AC$3*AA74,"") | AE74: =$H74*(AD74/12) -> 0 | AF74: =IFERROR($I74*$J74/37*(1+PLPartner1)^AF$3*AD74,"") | AH74: =$H74*(AG74/12) -> 0 | AI74: =IFERROR($I74*$J74/37*(1+PLPartner1)^AI$3*AG74,"") | AK74: =$H74*(AJ74/12) -> 0 | AL74: =IFERROR($I74*$J74/37*(1+PLPartner1)^AL$3*AJ74,"") | AN74: =$H74*(AM74/12) -> 0 | AO74: =IFERROR($I74*$J74/37*(1+PLPartner1)^AO$3*AM74,"") | AP74: =SUM(L74,O74,R74,U74,X74,AA74,AD74,AG74,AJ74,AM74) -> 0 | AQ74: =SUM(M74,P74,S74,V74,Y74,AB74,AE74,AH74,AK74,AN74) -> 0 | AR74: =SUM(N74,Q74,T74,W74,Z74,AC74,AF74,AI74,AL74,AO74) -> 0 | AT74: =AQ74*$AT$18 -> 0
C75: - | H75: =J75/37 -> 1 | I75: =_xlfn.XLOOKUP(C75,'AU salary costs 2025'!$B$7:$B$35,'AU salary costs 2025'!$D$7:$D$35, "-") -> - | J75: 37 | M75: =$H75*(L75/12) -> 0 | N75: =IFERROR($I75*$J75/37*(1+PLPartner1)^N$3*L75,"") | P75: =$H75*(O75/12) -> 0 | Q75: =IFERROR($I75*$J75/37*(1+PLPartner1)^Q$3*O75,"") | S75: =$H75*(R75/12) -> 0 | T75: =IFERROR($I75*$J75/37*(1+PLPartner1)^T$3*R75,"") | V75: =$H75*(U75/12) -> 0 | W75: =IFERROR($I75*$J75/37*(1+PLPartner1)^W$3*U75,"") | Y75: =$H75*(X75/12) -> 0 | Z75: =IFERROR($I75*$J75/37*(1+PLPartner1)^Z$3*X75,"") | AB75: =$H75*(AA75/12) -> 0 | AC75: =IFERROR($I75*$J75/37*(1+PLPartner1)^AC$3*AA75,"") | AE75: =$H75*(AD75/12) -> 0 | AF75: =IFERROR($I75*$J75/37*(1+PLPartner1)^AF$3*AD75,"") | AH75: =$H75*(AG75/12) -> 0 | AI75: =IFERROR($I75*$J75/37*(1+PLPartner1)^AI$3*AG75,"") | AK75: =$H75*(AJ75/12) -> 0 | AL75: =IFERROR($I75*$J75/37*(1+PLPartner1)^AL$3*AJ75,"") | AN75: =$H75*(AM75/12) -> 0 | AO75: =IFERROR($I75*$J75/37*(1+PLPartner1)^AO$3*AM75,"") | AP75: =SUM(L75,O75,R75,U75,X75,AA75,AD75,AG75,AJ75,AM75) -> 0 | AQ75: =SUM(M75,P75,S75,V75,Y75,AB75,AE75,AH75,AK75,AN75) -> 0 | AR75: =SUM(N75,Q75,T75,W75,Z75,AC75,AF75,AI75,AL75,AO75) -> 0 | AT75: =AQ75*$AT$18 -> 0
C76: - | H76: =J76/37 -> 1 | I76: =_xlfn.XLOOKUP(C76,'AU salary costs 2025'!$B$7:$B$35,'AU salary costs 2025'!$D$7:$D$35, "-") -> - | J76: 37 | M76: =$H76*(L76/12) -> 0 | N76: =IFERROR($I76*$J76/37*(1+PLPartner1)^N$3*L76,"") | P76: =$H76*(O76/12) -> 0 | Q76: =IFERROR($I76*$J76/37*(1+PLPartner1)^Q$3*O76,"") | S76: =$H76*(R76/12) -> 0 | T76: =IFERROR($I76*$J76/37*(1+PLPartner1)^T$3*R76,"") | V76: =$H76*(U76/12) -> 0 | W76: =IFERROR($I76*$J76/37*(1+PLPartner1)^W$3*U76,"") | Y76: =$H76*(X76/12) -> 0 | Z76: =IFERROR($I76*$J76/37*(1+PLPartner1)^Z$3*X76,"") | AB76: =$H76*(AA76/12) -> 0 | AC76: =IFERROR($I76*$J76/37*(1+PLPartner1)^AC$3*AA76,"") | AE76: =$H76*(AD76/12) -> 0 | AF76: =IFERROR($I76*$J76/37*(1+PLPartner1)^AF$3*AD76,"") | AH76: =$H76*(AG76/12) -> 0 | AI76: =IFERROR($I76*$J76/37*(1+PLPartner1)^AI$3*AG76,"") | AK76: =$H76*(AJ76/12) -> 0 | AL76: =IFERROR($I76*$J76/37*(1+PLPartner1)^AL$3*AJ76,"") | AN76: =$H76*(AM76/12) -> 0 | AO76: =IFERROR($I76*$J76/37*(1+PLPartner1)^AO$3*AM76,"") | AP76: =SUM(L76,O76,R76,U76,X76,AA76,AD76,AG76,AJ76,AM76) -> 0 | AQ76: =SUM(M76,P76,S76,V76,Y76,AB76,AE76,AH76,AK76,AN76) -> 0 | AR76: =SUM(N76,Q76,T76,W76,Z76,AC76,AF76,AI76,AL76,AO76) -> 0 | AT76: =AQ76*$AT$18 -> 0
C77: - | H77: =J77/37 -> 1 | I77: =_xlfn.XLOOKUP(C77,'AU salary costs 2025'!$B$7:$B$35,'AU salary costs 2025'!$D$7:$D$35, "-") -> - | J77: 37 | M77: =$H77*(L77/12) -> 0 | N77: =IFERROR($I77*$J77/37*(1+PLPartner1)^N$3*L77,"") | P77: =$H77*(O77/12) -> 0 | Q77: =IFERROR($I77*$J77/37*(1+PLPartner1)^Q$3*O77,"") | S77: =$H77*(R77/12) -> 0 | T77: =IFERROR($I77*$J77/37*(1+PLPartner1)^T$3*R77,"") | V77: =$H77*(U77/12) -> 0 | W77: =IFERROR($I77*$J77/37*(1+PLPartner1)^W$3*U77,"") | Y77: =$H77*(X77/12) -> 0 | Z77: =IFERROR($I77*$J77/37*(1+PLPartner1)^Z$3*X77,"") | AB77: =$H77*(AA77/12) -> 0 | AC77: =IFERROR($I77*$J77/37*(1+PLPartner1)^AC$3*AA77,"") | AE77: =$H77*(AD77/12) -> 0 | AF77: =IFERROR($I77*$J77/37*(1+PLPartner1)^AF$3*AD77,"") | AH77: =$H77*(AG77/12) -> 0 | AI77: =IFERROR($I77*$J77/37*(1+PLPartner1)^AI$3*AG77,"") | AK77: =$H77*(AJ77/12) -> 0 | AL77: =IFERROR($I77*$J77/37*(1+PLPartner1)^AL$3*AJ77,"") | AN77: =$H77*(AM77/12) -> 0 | AO77: =IFERROR($I77*$J77/37*(1+PLPartner1)^AO$3*AM77,"") | AP77: =SUM(L77,O77,R77,U77,X77,AA77,AD77,AG77,AJ77,AM77) -> 0 | AQ77: =SUM(M77,P77,S77,V77,Y77,AB77,AE77,AH77,AK77,AN77) -> 0 | AR77: =SUM(N77,Q77,T77,W77,Z77,AC77,AF77,AI77,AL77,AO77) -> 0 | AT77: =AQ77*$AT$18 -> 0
C78: - | H78: =J78/37 -> 1 | I78: =_xlfn.XLOOKUP(C78,'AU salary costs 2025'!$B$7:$B$35,'AU salary costs 2025'!$D$7:$D$35, "-") -> - | J78: 37 | M78: =$H78*(L78/12) -> 0 | N78: =IFERROR($I78*$J78/37*(1+PLPartner1)^N$3*L78,"") | P78: =$H78*(O78/12) -> 0 | Q78: =IFERROR($I78*$J78/37*(1+PLPartner1)^Q$3*O78,"") | S78: =$H78*(R78/12) -> 0 | T78: =IFERROR($I78*$J78/37*(1+PLPartner1)^T$3*R78,"") | V78: =$H78*(U78/12) -> 0 | W78: =IFERROR($I78*$J78/37*(1+PLPartner1)^W$3*U78,"") | Y78: =$H78*(X78/12) -> 0 | Z78: =IFERROR($I78*$J78/37*(1+PLPartner1)^Z$3*X78,"") | AB78: =$H78*(AA78/12) -> 0 | AC78: =IFERROR($I78*$J78/37*(1+PLPartner1)^AC$3*AA78,"") | AE78: =$H78*(AD78/12) -> 0 | AF78: =IFERROR($I78*$J78/37*(1+PLPartner1)^AF$3*AD78,"") | AH78: =$H78*(AG78/12) -> 0 | AI78: =IFERROR($I78*$J78/37*(1+PLPartner1)^AI$3*AG78,"") | AK78: =$H78*(AJ78/12) -> 0 | AL78: =IFERROR($I78*$J78/37*(1+PLPartner1)^AL$3*AJ78,"") | AN78: =$H78*(AM78/12) -> 0 | AO78: =IFERROR($I78*$J78/37*(1+PLPartner1)^AO$3*AM78,"") | AP78: =SUM(L78,O78,R78,U78,X78,AA78,AD78,AG78,AJ78,AM78) -> 0 | AQ78: =SUM(M78,P78,S78,V78,Y78,AB78,AE78,AH78,AK78,AN78) -> 0 | AR78: =SUM(N78,Q78,T78,W78,Z78,AC78,AF78,AI78,AL78,AO78) -> 0 | AT78: =AQ78*$AT$18 -> 0
C79: - | H79: =J79/37 -> 1 | I79: =_xlfn.XLOOKUP(C79,'AU salary costs 2025'!$B$7:$B$35,'AU salary costs 2025'!$D$7:$D$35, "-") -> - | J79: 37 | M79: =$H79*(L79/12) -> 0 | N79: =IFERROR($I79*$J79/37*(1+PLPartner1)^N$3*L79,"") | P79: =$H79*(O79/12) -> 0 | Q79: =IFERROR($I79*$J79/37*(1+PLPartner1)^Q$3*O79,"") | S79: =$H79*(R79/12) -> 0 | T79: =IFERROR($I79*$J79/37*(1+PLPartner1)^T$3*R79,"") | V79: =$H79*(U79/12) -> 0 | W79: =IFERROR($I79*$J79/37*(1+PLPartner1)^W$3*U79,"") | Y79: =$H79*(X79/12) -> 0 | Z79: =IFERROR($I79*$J79/37*(1+PLPartner1)^Z$3*X79,"") | AB79: =$H79*(AA79/12) -> 0 | AC79: =IFERROR($I79*$J79/37*(1+PLPartner1)^AC$3*AA79,"") | AE79: =$H79*(AD79/12) -> 0 | AF79: =IFERROR($I79*$J79/37*(1+PLPartner1)^AF$3*AD79,"") | AH79: =$H79*(AG79/12) -> 0 | AI79: =IFERROR($I79*$J79/37*(1+PLPartner1)^AI$3*AG79,"") | AK79: =$H79*(AJ79/12) -> 0 | AL79: =IFERROR($I79*$J79/37*(1+PLPartner1)^AL$3*AJ79,"") | AN79: =$H79*(AM79/12) -> 0 | AO79: =IFERROR($I79*$J79/37*(1+PLPartner1)^AO$3*AM79,"") | AP79: =SUM(L79,O79,R79,U79,X79,AA79,AD79,AG79,AJ79,AM79) -> 0 | AQ79: =SUM(M79,P79,S79,V79,Y79,AB79,AE79,AH79,AK79,AN79) -> 0 | AR79: =SUM(N79,Q79,T79,W79,Z79,AC79,AF79,AI79,AL79,AO79) -> 0 | AT79: =AQ79*$AT$18 -> 0
C80: - | H80: =J80/37 -> 1 | I80: =_xlfn.XLOOKUP(C80,'AU salary costs 2025'!$B$7:$B$35,'AU salary costs 2025'!$D$7:$D$35, "-") -> - | J80: 37 | M80: =$H80*(L80/12) -> 0 | N80: =IFERROR($I80*$J80/37*(1+PLPartner1)^N$3*L80,"") | P80: =$H80*(O80/12) -> 0 | Q80: =IFERROR($I80*$J80/37*(1+PLPartner1)^Q$3*O80,"") | S80: =$H80*(R80/12) -> 0 | T80: =IFERROR($I80*$J80/37*(1+PLPartner1)^T$3*R80,"") | V80: =$H80*(U80/12) -> 0 | W80: =IFERROR($I80*$J80/37*(1+PLPartner1)^W$3*U80,"") | Y80: =$H80*(X80/12) -> 0 | Z80: =IFERROR($I80*$J80/37*(1+PLPartner1)^Z$3*X80,"") | AB80: =$H80*(AA80/12) -> 0 | AC80: =IFERROR($I80*$J80/37*(1+PLPartner1)^AC$3*AA80,"") | AE80: =$H80*(AD80/12) -> 0 | AF80: =IFERROR($I80*$J80/37*(1+PLPartner1)^AF$3*AD80,"") | AH80: =$H80*(AG80/12) -> 0 | AI80: =IFERROR($I80*$J80/37*(1+PLPartner1)^AI$3*AG80,"") | AK80: =$H80*(AJ80/12) -> 0 | AL80: =IFERROR($I80*$J80/37*(1+PLPartner1)^AL$3*AJ80,"") | AN80: =$H80*(AM80/12) -> 0 | AO80: =IFERROR($I80*$J80/37*(1+PLPartner1)^AO$3*AM80,"") | AP80: =SUM(L80,O80,R80,U80,X80,AA80,AD80,AG80,AJ80,AM80) -> 0 | AQ80: =SUM(M80,P80,S80,V80,Y80,AB80,AE80,AH80,AK80,AN80) -> 0 | AR80: =SUM(N80,Q80,T80,W80,Z80,AC80,AF80,AI80,AL80,AO80) -> 0 | AT80: =AQ80*$AT$18 -> 0
C81: - | H81: =J81/37 -> 1 | I81: =_xlfn.XLOOKUP(C81,'AU salary costs 2025'!$B$7:$B$35,'AU salary costs 2025'!$D$7:$D$35, "-") -> - | J81: 37 | M81: =$H81*(L81/12) -> 0 | N81: =IFERROR($I81*$J81/37*(1+PLPartner1)^N$3*L81,"") | P81: =$H81*(O81/12) -> 0 | Q81: =IFERROR($I81*$J81/37*(1+PLPartner1)^Q$3*O81,"") | S81: =$H81*(R81/12) -> 0 | T81: =IFERROR($I81*$J81/37*(1+PLPartner1)^T$3*R81,"") | V81: =$H81*(U81/12) -> 0 | W81: =IFERROR($I81*$J81/37*(1+PLPartner1)^W$3*U81,"") | Y81: =$H81*(X81/12) -> 0 | Z81: =IFERROR($I81*$J81/37*(1+PLPartner1)^Z$3*X81,"") | AB81: =$H81*(AA81/12) -> 0 | AC81: =IFERROR($I81*$J81/37*(1+PLPartner1)^AC$3*AA81,"") | AE81: =$H81*(AD81/12) -> 0 | AF81: =IFERROR($I81*$J81/37*(1+PLPartner1)^AF$3*AD81,"") | AH81: =$H81*(AG81/12) -> 0 | AI81: =IFERROR($I81*$J81/37*(1+PLPartner1)^AI$3*AG81,"") | AK81: =$H81*(AJ81/12) -> 0 | AL81: =IFERROR($I81*$J81/37*(1+PLPartner1)^AL$3*AJ81,"") | AN81: =$H81*(AM81/12) -> 0 | AO81: =IFERROR($I81*$J81/37*(1+PLPartner1)^AO$3*AM81,"") | AP81: =SUM(L81,O81,R81,U81,X81,AA81,AD81,AG81,AJ81,AM81) -> 0 | AQ81: =SUM(M81,P81,S81,V81,Y81,AB81,AE81,AH81,AK81,AN81) -> 0 | AR81: =SUM(N81,Q81,T81,W81,Z81,AC81,AF81,AI81,AL81,AO81) -> 0 | AT81: =AQ81*$AT$18 -> 0
C82: - | H82: =J82/37 -> 1 | I82: =_xlfn.XLOOKUP(C82,'AU salary costs 2025'!$B$7:$B$35,'AU salary costs 2025'!$D$7:$D$35, "-") -> - | J82: 37 | M82: =$H82*(L82/12) -> 0 | N82: =IFERROR($I82*$J82/37*(1+PLPartner1)^N$3*L82,"") | P82: =$H82*(O82/12) -> 0 | Q82: =IFERROR($I82*$J82/37*(1+PLPartner1)^Q$3*O82,"") | S82: =$H82*(R82/12) -> 0 | T82: =IFERROR($I82*$J82/37*(1+PLPartner1)^T$3*R82,"") | V82: =$H82*(U82/12) -> 0 | W82: =IFERROR($I82*$J82/37*(1+PLPartner1)^W$3*U82,"") | Y82: =$H82*(X82/12) -> 0 | Z82: =IFERROR($I82*$J82/37*(1+PLPartner1)^Z$3*X82,"") | AB82: =$H82*(AA82/12) -> 0 | AC82: =IFERROR($I82*$J82/37*(1+PLPartner1)^AC$3*AA82,"") | AE82: =$H82*(AD82/12) -> 0 | AF82: =IFERROR($I82*$J82/37*(1+PLPartner1)^AF$3*AD82,"") | AH82: =$H82*(AG82/12) -> 0 | AI82: =IFERROR($I82*$J82/37*(1+PLPartner1)^AI$3*AG82,"") | AK82: =$H82*(AJ82/12) -> 0 | AL82: =IFERROR($I82*$J82/37*(1+PLPartner1)^AL$3*AJ82,"") | AN82: =$H82*(AM82/12) -> 0 | AO82: =IFERROR($I82*$J82/37*(1+PLPartner1)^AO$3*AM82,"") | AP82: =SUM(L82,O82,R82,U82,X82,AA82,AD82,AG82,AJ82,AM82) -> 0 | AQ82: =SUM(M82,P82,S82,V82,Y82,AB82,AE82,AH82,AK82,AN82) -> 0 | AR82: =SUM(N82,Q82,T82,W82,Z82,AC82,AF82,AI82,AL82,AO82) -> 0 | AT82: =AQ82*$AT$18 -> 0
C83: - | H83: =J83/37 -> 1 | I83: =_xlfn.XLOOKUP(C83,'AU salary costs 2025'!$B$7:$B$35,'AU salary costs 2025'!$D$7:$D$35, "-") -> - | J83: 37 | M83: =$H83*(L83/12) -> 0 | N83: =IFERROR($I83*$J83/37*(1+PLPartner1)^N$3*L83,"") | P83: =$H83*(O83/12) -> 0 | Q83: =IFERROR($I83*$J83/37*(1+PLPartner1)^Q$3*O83,"") | S83: =$H83*(R83/12) -> 0 | T83: =IFERROR($I83*$J83/37*(1+PLPartner1)^T$3*R83,"") | V83: =$H83*(U83/12) -> 0 | W83: =IFERROR($I83*$J83/37*(1+PLPartner1)^W$3*U83,"") | Y83: =$H83*(X83/12) -> 0 | Z83: =IFERROR($I83*$J83/37*(1+PLPartner1)^Z$3*X83,"") | AB83: =$H83*(AA83/12) -> 0 | AC83: =IFERROR($I83*$J83/37*(1+PLPartner1)^AC$3*AA83,"") | AE83: =$H83*(AD83/12) -> 0 | AF83: =IFERROR($I83*$J83/37*(1+PLPartner1)^AF$3*AD83,"") | AH83: =$H83*(AG83/12) -> 0 | AI83: =IFERROR($I83*$J83/37*(1+PLPartner1)^AI$3*AG83,"") | AK83: =$H83*(AJ83/12) -> 0 | AL83: =IFERROR($I83*$J83/37*(1+PLPartner1)^AL$3*AJ83,"") | AN83: =$H83*(AM83/12) -> 0 | AO83: =IFERROR($I83*$J83/37*(1+PLPartner1)^AO$3*AM83,"") | AP83: =SUM(L83,O83,R83,U83,X83,AA83,AD83,AG83,AJ83,AM83) -> 0 | AQ83: =SUM(M83,P83,S83,V83,Y83,AB83,AE83,AH83,AK83,AN83) -> 0 | AR83: =SUM(N83,Q83,T83,W83,Z83,AC83,AF83,AI83,AL83,AO83) -> 0 | AT83: =AQ83*$AT$18 -> 0
C84: - | H84: =J84/37 -> 1 | I84: =_xlfn.XLOOKUP(C84,'AU salary costs 2025'!$B$7:$B$35,'AU salary costs 2025'!$D$7:$D$35, "-") -> - | J84: 37 | M84: =$H84*(L84/12) -> 0 | N84: =IFERROR($I84*$J84/37*(1+PLPartner1)^N$3*L84,"") | P84: =$H84*(O84/12) -> 0 | Q84: =IFERROR($I84*$J84/37*(1+PLPartner1)^Q$3*O84,"") | S84: =$H84*(R84/12) -> 0 | T84: =IFERROR($I84*$J84/37*(1+PLPartner1)^T$3*R84,"") | V84: =$H84*(U84/12) -> 0 | W84: =IFERROR($I84*$J84/37*(1+PLPartner1)^W$3*U84,"") | Y84: =$H84*(X84/12) -> 0 | Z84: =IFERROR($I84*$J84/37*(1+PLPartner1)^Z$3*X84,"") | AB84: =$H84*(AA84/12) -> 0 | AC84: =IFERROR($I84*$J84/37*(1+PLPartner1)^AC$3*AA84,"") | AE84: =$H84*(AD84/12) -> 0 | AF84: =IFERROR($I84*$J84/37*(1+PLPartner1)^AF$3*AD84,"") | AH84: =$H84*(AG84/12) -> 0 | AI84: =IFERROR($I84*$J84/37*(1+PLPartner1)^AI$3*AG84,"") | AK84: =$H84*(AJ84/12) -> 0 | AL84: =IFERROR($I84*$J84/37*(1+PLPartner1)^AL$3*AJ84,"") | AN84: =$H84*(AM84/12) -> 0 | AO84: =IFERROR($I84*$J84/37*(1+PLPartner1)^AO$3*AM84,"") | AP84: =SUM(L84,O84,R84,U84,X84,AA84,AD84,AG84,AJ84,AM84) -> 0 | AQ84: =SUM(M84,P84,S84,V84,Y84,AB84,AE84,AH84,AK84,AN84) -> 0 | AR84: =SUM(N84,Q84,T84,W84,Z84,AC84,AF84,AI84,AL84,AO84) -> 0 | AT84: =AQ84*$AT$18 -> 0
C85: - | H85: =J85/37 -> 1 | I85: =_xlfn.XLOOKUP(C85,'AU salary costs 2025'!$B$7:$B$35,'AU salary costs 2025'!$D$7:$D$35, "-") -> - | J85: 37 | M85: =$H85*(L85/12) -> 0 | N85: =IFERROR($I85*$J85/37*(1+PLPartner1)^N$3*L85,"") | P85: =$H85*(O85/12) -> 0 | Q85: =IFERROR($I85*$J85/37*(1+PLPartner1)^Q$3*O85,"") | S85: =$H85*(R85/12) -> 0 | T85: =IFERROR($I85*$J85/37*(1+PLPartner1)^T$3*R85,"") | V85: =$H85*(U85/12) -> 0 | W85: =IFERROR($I85*$J85/37*(1+PLPartner1)^W$3*U85,"") | Y85: =$H85*(X85/12) -> 0 | Z85: =IFERROR($I85*$J85/37*(1+PLPartner1)^Z$3*X85,"") | AB85: =$H85*(AA85/12) -> 0 | AC85: =IFERROR($I85*$J85/37*(1+PLPartner1)^AC$3*AA85,"") | AE85: =$H85*(AD85/12) -> 0 | AF85: =IFERROR($I85*$J85/37*(1+PLPartner1)^AF$3*AD85,"") | AH85: =$H85*(AG85/12) -> 0 | AI85: =IFERROR($I85*$J85/37*(1+PLPartner1)^AI$3*AG85,"") | AK85: =$H85*(AJ85/12) -> 0 | AL85: =IFERROR($I85*$J85/37*(1+PLPartner1)^AL$3*AJ85,"") | AN85: =$H85*(AM85/12) -> 0 | AO85: =IFERROR($I85*$J85/37*(1+PLPartner1)^AO$3*AM85,"") | AP85: =SUM(L85,O85,R85,U85,X85,AA85,AD85,AG85,AJ85,AM85) -> 0 | AQ85: =SUM(M85,P85,S85,V85,Y85,AB85,AE85,AH85,AK85,AN85) -> 0 | AR85: =SUM(N85,Q85,T85,W85,Z85,AC85,AF85,AI85,AL85,AO85) -> 0 | AT85: =AQ85*$AT$18 -> 0
... C89: - | H89: =J89/37 -> 1 | I89: =_xlfn.XLOOKUP(C89,'AU salary costs 2025'!$B$7:$B$35,'AU salary costs 2025'!$D$7:$D$35, "-") -> - | J89: 37 | M89: =$H89*(L89/12) -> 0 | N89: =IFERROR($I89*$J89/37*(1+PLPartner1)^N$3*L89,"") | P89: =$H89*(O89/12) -> 0 | Q89: =IFERROR($I89*$J89/37*(1+PLPartner1)^Q$3*O89,"") | S89: =$H89*(R89/12) -> 0 | T89: =IFERROR($I89*$J89/37*(1+PLPartner1)^T$3*R89,"") | V89: =$H89*(U89/12) -> 0 | W89: =IFERROR($I89*$J89/37*(1+PLPartner1)^W$3*U89,"") | Y89: =$H89*(X89/12) -> 0 | Z89: =IFERROR($I89*$J89/37*(1+PLPartner1)^Z$3*X89,"") | AB89: =$H89*(AA89/12) -> 0 | AC89: =IFERROR($I89*$J89/37*(1+PLPartner1)^AC$3*AA89,"") | AE89: =$H89*(AD89/12) -> 0 | AF89: =IFERROR($I89*$J89/37*(1+PLPartner1)^AF$3*AD89,"") | AH89: =$H89*(AG89/12) -> 0 | AI89: =IFERROR($I89*$J89/37*(1+PLPartner1)^AI$3*AG89,"") | AK89: =$H89*(AJ89/12) -> 0 | AL89: =IFERROR($I89*$J89/37*(1+PLPartner1)^AL$3*AJ89,"") | AN89: =$H89*(AM89/12) -> 0 | AO89: =IFERROR($I89*$J89/37*(1+PLPartner1)^AO$3*AM89,"") | AP89: =SUM(L89,O89,R89,U89,X89,AA89,AD89,AG89,AJ89,AM89) -> 0 | AQ89: =SUM(M89,P89,S89,V89,Y89,AB89,AE89,AH89,AK89,AN89) -> 0 | AR89: =SUM(N89,Q89,T89,W89,Z89,AC89,AF89,AI89,AL89,AO89) -> 0 | AT89: =AQ89*$AT$18 -> 0
K90: Sum of TAP co-financing | L90: =SUM(L74:L89) -> 0 | M90: =SUM(M74:M89) -> 0 | N90: =SUM(N74:N89) -> 0 | O90: =SUM(O74:O89) -> 0 | P90: =SUM(P74:P89) -> 0 | Q90: =SUM(Q74:Q89) -> 0 | R90: =SUM(R74:R89) -> 0 | S90: =SUM(S74:S89) -> 0 | ... AR90: =SUM(AR74:AR89) -> 0 | AT90: =AQ90*$AT$18 -> 0
K91: Total salary co-financing | L91: =L90+L54 -> 0 | M91: =M90+M54 -> 0 | N91: =N90+N54 -> 0 | O91: =O90+O54 -> 0 | P91: =P90+P54 -> 0 | Q91: =Q90+Q54 -> 0 | R91: =R90+R54 -> 0 | S91: =S90+S54 -> 0 | ... AO91: =AO90+AO54 -> 0 | AP91: =SUM(AP90,AP54) -> 0 | AQ91: =SUM(AQ90,AQ54) -> 0 | AR91: =SUM(AR90,AR54) -> 0 | AT91: =AQ91*$AT$18 -> 0
B92: Total salary (A + B) | L92: =L36+L72 -> 18 | M92: =M36+M72 -> 1.5 | N92: =N36+N72 -> 929348.4 | O92: =O36+O72 -> 36 | P92: =P36+P72 -> 3 | Q92: =Q36+Q72 -> 1914457.7 | R92: =R36+R72 -> 48 | S92: =S36+S72 -> 4 | ... AR92: =AR36+AR72 -> 9814209.6 | AT92: =AQ92*$AT$18 -> 28860
B93: Project costs
C94: 2. Operation | F94: Notes | K94: Dept. Serv. | N94: Costs | Q94: Costs | T94: Costs | W94: Costs | Z94: Costs | AC94: Costs | AF94: Costs | AI94: Costs | AL94: Costs | AO94: Costs | AR94: Costs
C95: Equipment | F95: High-performance computers | N95: 50000 | Q95: 50000 | T95: 50000 | AR95: =SUM(N95:AO95) -> 150000
C96: Data management | F96: Cluster time | N96: 50000 | Q96: 50000 | T96: 50000 | W96: 50000 | Z96: 50000 | AC96: 50000 | AR96: =SUM(N96:AO96) -> 300000
C97: Operating expenses | F97: Data storage | N97: 100000 | Q97: 100000 | T97: 100000 | W97: 10000 | Z97: 100000 | AC97: 90000 | AR97: =SUM(N97:AO97) -> 500000
C98: - | AR98: =SUM(N98:AO98) -> 0
C99: - | AR99: =SUM(N99:AO99) -> 0
C100: - | AR100: =SUM(N100:AO100) -> 0
C101: - | AR101: =SUM(N101:AO101) -> 0
C102: - | AR102: =SUM(N102:AO102) -> 0
C103: - | AR103: =SUM(N103:AO103) -> 0
C104: - | AR104: =SUM(N104:AO104) -> 0
C105: - | AR105: =SUM(N105:AO105) -> 0
C106: - | AR106: =SUM(N106:AO106) -> 0
C107: - | AR107: =SUM(N107:AO107) -> 0
C108: - | AR108: =SUM(N108:AO108) -> 0
...

Sheet ReAp
H17: =YEARFRAC(AU!$L$17,IF(YEAR(AU!$N$17)=YEAR(AU!$L$1),AU!$N$17,DATE(YEAR(AU!$L$1),12,31)))*12 -> 3
H18: =AU!L18-H17 -> 9
H19: =SUM(H17:H18) -> 12

Sheet Overview - AU
B1: Applied for from the foundation | Q1: Co-financing
B3: =AU!C19 & " Man months" -> 1. VIP Man months | D3: =AU!L15 -> Year 1 | E3: =AU!O15 -> Year 2 | F3: =AU!R15 -> Year 3 | G3: =AU!U15 -> Year 4 | H3: =AU!X15 -> Year 5 | I3: =AU!AA15 -> Year 6 | J3: =AU!AD15 -> Year 7 | K3: =AU!AG15 -> Year 8 | L3: =AU!AJ15 -> Year 9 | M3: =AU!AM15 -> Year 10 | N3: Total | Q3: =B3 -> 1. VIP Man months | S3: =AU!L15 -> Year 1 | T3: =AU!O15 -> Year 2 | U3: =AU!R15 -> Year 3 | V3: =AU!U15 -> Year 4 | W3: =AU!X15 -> Year 5 | X3: =AU!AA15 -> Year 6 | Y3: =AU!AD15 -> Year 7 | Z3: =AU!AG15 -> Year 8 | AA3: =AU!AJ15 -> Year 9 | AB3: =AU!AM15 -> Year 10 | AC3: Total
B4: =AU!C20 -> Postdoc | C4: =IF(AU!F20=0,"",AU!F20) | D4: =AU!L20 -> 12 | E4: =AU!O20 -> 12 | F4: =AU!R20 -> 12 | G4: =AU!U20 -> 0 | H4: =AU!X20 -> 0 | I4: =AU!AA20 -> 0 | J4: =AU!AD20 -> 0 | K4: =AU!AG20 -> 0 | L4: =AU!AJ20 -> 0 | M4: =AU!AM20 -> 0 | N4: =SUM(D4:M4) -> 36 | Q4: =AU!C38 -> - | R4: =IF(AU!F38=0,"",AU!F38) | S4: =AU!L38 -> 0 | T4: =AU!O38 -> 0 | U4: =AU!R38 -> 0 | V4: =AU!U38 -> 0 | W4: =AU!X38 -> 0 | X4: =AU!AA38 -> 0 | Y4: =AU!AD38 -> 0 | Z4: =AU!AG38 -> 0 | AA4: =AU!AJ38 -> 0 | AB4: =AU!AM38 -> 0 | AC4: =SUM(S4:AB4) -> 0
B5: =AU!C21 -> Postdoc | C5: =IF(AU!F21=0,"",AU!F21) | D5: =AU!L21 -> 0 | E5: =AU!O21 -> 12 | F5: =AU!R21 -> 12 | G5: =AU!U21 -> 12 | H5: =AU!X21 -> 0 | I5: =AU!AA21 -> 0 | J5: =AU!AD21 -> 0 | K5: =AU!AG21 -> 0 | L5: =AU!AJ21 -> 0 | M5: =AU!AM21 -> 0 | N5: =SUM(D5:M5) -> 36 | Q5: =AU!C39 -> - | R5: =IF(AU!F39=0,"",AU!F39) | S5: =AU!L39 -> 0 | T5: =AU!O39 -> 0 | U5: =AU!R39 -> 0 | V5: =AU!U39 -> 0 | W5: =AU!X39 -> 0 | X5: =AU!AA39 -> 0 | Y5: =AU!AD39 -> 0 | Z5: =AU!AG39 -> 0 | AA5: =AU!AJ39 -> 0 | AB5: =AU!AM39 -> 0 | AC5: =SUM(S5:AB5) -> 0
B6: =AU!C22 -> Postdoc | C6: =IF(AU!F22=0,"",AU!F22) | D6: =AU!L22 -> 0 | E6: =AU!O22 -> 0 | F6: =AU!R22 -> 6 | G6: =AU!U22 -> 12 | H6: =AU!X22 -> 12 | I6: =AU!AA22 -> 6 | J6: =AU!AD22 -> 0 | K6: =AU!AG22 -> 0 | L6: =AU!AJ22 -> 0 | M6: =AU!AM22 -> 0 | N6: =SUM(D6:M6) -> 36 | Q6: =AU!C40 -> - | R6: =IF(AU!F40=0,"",AU!F40) | S6: =AU!L40 -> 0 | T6: =AU!O40 -> 0 | U6: =AU!R40 -> 0 | V6: =AU!U40 -> 0 | W6: =AU!X40 -> 0 | X6: =AU!AA40 -> 0 | Y6: =AU!AD40 -> 0 | Z6: =AU!AG40 -> 0 | AA6: =AU!AJ40 -> 0 | AB6: =AU!AM40 -> 0 | AC6: =SUM(S6:AB6) -> 0
B7: =AU!C23 -> PhD Student | C7: =IF(AU!F23=0,"",AU!F23) | D7: =AU!L23 -> 6 | E7: =AU!O23 -> 12 | F7: =AU!R23 -> 12 | G7: =AU!U23 -> 6 | H7: =AU!X23 -> 0 | I7: =AU!AA23 -> 0 | J7: =AU!AD23 -> 0 | K7: =AU!AG23 -> 0 | L7: =AU!AJ23 -> 0 | M7: =AU!AM23 -> 0 | N7: =SUM(D7:M7) -> 36 | Q7: =AU!C41 -> - | R7: =IF(AU!F41=0,"",AU!F41) | S7: =AU!L41 -> 0 | T7: =AU!O41 -> 0 | U7: =AU!R41 -> 0 | V7: =AU!U41 -> 0 | W7: =AU!X41 -> 0 | X7: =AU!AA41 -> 0 | Y7: =AU!AD41 -> 0 | Z7: =AU!AG41 -> 0 | AA7: =AU!AJ41 -> 0 | AB7: =AU!AM41 -> 0 | AC7: =SUM(S7:AB7) -> 0
B8: =AU!C24 -> PhD Student | C8: =IF(AU!F24=0,"",AU!F24) | D8: =AU!L24 -> 0 | E8: =AU!O24 -> 0 | F8: =AU!R24 -> 6 | G8: =AU!U24 -> 12 | H8: =AU!X24 -> 12 | I8: =AU!AA24 -> 6 | J8: =AU!AD24 -> 0 | K8: =AU!AG24 -> 0 | L8: =AU!AJ24 -> 0 | M8: =AU!AM24 -> 0 | N8: =SUM(D8:M8) -> 36 | Q8: =AU!C42 -> - | R8: =IF(AU!F42=0,"",AU!F42) | S8: =AU!L42 -> 0 | T8: =AU!O42 -> 0 | U8: =AU!R42 -> 0 | V8: =AU!U42 -> 0 | W8: =AU!X42 -> 0 | X8: =AU!AA42 -> 0 | Y8: =AU!AD42 -> 0 | Z8: =AU!AG42 -> 0 | AA8: =AU!AJ42 -> 0 | AB8: =AU!AM42 -> 0 | AC8: =SUM(S8:AB8) -> 0
B9: =AU!C25 -> - | C9: =IF(AU!F25=0,"",AU!F25) | D9: =AU!L25 -> 0 | E9: =AU!O25 -> 0 | F9: =AU!R25 -> 0 | G9: =AU!U25 -> 0 | H9: =AU!X25 -> 0 | I9: =AU!AA25 -> 0 | J9: =AU!AD25 -> 0 | K9: =AU!AG25 -> 0 | L9: =AU!AJ25 -> 0 | M9: =AU!AM25 -> 0 | N9: =SUM(D9:M9) -> 0 | Q9: =AU!C43 -> - | R9: =IF(AU!F43=0,"",AU!F43) | S9: =AU!L43 -> 0 | T9: =AU!O43 -> 0 | U9: =AU!R43 -> 0 | V9: =AU!U43 -> 0 | W9: =AU!X43 -> 0 | X9: =AU!AA43 -> 0 | Y9: =AU!AD43 -> 0 | Z9: =AU!AG43 -> 0 | AA9: =AU!AJ43 -> 0 | AB9: =AU!AM43 -> 0 | AC9: =SUM(S9:AB9) -> 0
B10: =AU!C26 -> - | C10: =IF(AU!F26=0,"",AU!F26) | D10: =AU!L26 -> 0 | E10: =AU!O26 -> 0 | F10: =AU!R26 -> 0 | G10: =AU!U26 -> 0 | H10: =AU!X26 -> 0 | I10: =AU!AA26 -> 0 | J10: =AU!AD26 -> 0 | K10: =AU!AG26 -> 0 | L10: =AU!AJ26 -> 0 | M10: =AU!AM26 -> 0 | N10: =SUM(D10:M10) -> 0 | Q10: =AU!C44 -> - | R10: =IF(AU!F44=0,"",AU!F44) | S10: =AU!L44 -> 0 | T10: =AU!O44 -> 0 | U10: =AU!R44 -> 0 | V10: =AU!U44 -> 0 | W10: =AU!X44 -> 0 | X10: =AU!AA44 -> 0 | Y10: =AU!AD44 -> 0 | Z10: =AU!AG44 -> 0 | AA10: =AU!AJ44 -> 0 | AB10: =AU!AM44 -> 0 | AC10: =SUM(S10:AB10) -> 0
B11: =AU!C27 -> - | C11: =IF(AU!F27=0,"",AU!F27) | D11: =AU!L27 -> 0 | E11: =AU!O27 -> 0 | F11: =AU!R27 -> 0 | G11: =AU!U27 -> 0 | H11: =AU!X27 -> 0 | I11: =AU!AA27 -> 0 | J11: =AU!AD27 -> 0 | K11: =AU!AG27 -> 0 | L11: =AU!AJ27 -> 0 | M11: =AU!AM27 -> 0 | N11: =SUM(D11:M11) -> 0 | Q11: =AU!C45 -> - | R11: =IF(AU!F45=0,"",AU!F45) | S11: =AU!L45 -> 0 | T11: =AU!O45 -> 0 | U11: =AU!R45 -> 0 | V11: =AU!U45 -> 0 | W11: =AU!X45 -> 0 | X11: =AU!AA45 -> 0 | Y11: =AU!AD45 -> 0 | Z11: =AU!AG45 -> 0 | AA11: =AU!AJ45 -> 0 | AB11: =AU!AM45 -> 0 | AC11: =SUM(S11:AB11) -> 0
B12: =AU!C28 -> - | C12: =IF(AU!F28=0,"",AU!F28) | D12: =AU!L28 -> 0 | E12: =AU!O28 -> 0 | F12: =AU!R28 -> 0 | G12: =AU!U28 -> 0 | H12: =AU!X28 -> 0 | I12: =AU!AA28 -> 0 | J12: =AU!AD28 -> 0 | K12: =AU!AG28 -> 0 | L12: =AU!AJ28 -> 0 | M12: =AU!AM28 -> 0 | N12: =SUM(D12:M12) -> 0 | Q12: =AU!C46 -> - | R12: =IF(AU!F46=0,"",AU!F46) | S12: =AU!L46 -> 0 | T12: =AU!O46 -> 0 | U12: =AU!R46 -> 0 | V12: =AU!U46 -> 0 | W12: =AU!X46 -> 0 | X12: =AU!AA46 -> 0 | Y12: =AU!AD46 -> 0 | Z12: =AU!AG46 -> 0 | AA12: =AU!AJ46 -> 0 | AB12: =AU!AM46 -> 0 | AC12: =SUM(S12:AB12) -> 0
B13: =AU!C29 -> - | C13: =IF(AU!F29=0,"",AU!F29) | D13: =AU!L29 -> 0 | E13: =AU!O29 -> 0 | F13: =AU!R29 -> 0 | G13: =AU!U29 -> 0 | H13: =AU!X29 -> 0 | I13: =AU!AA29 -> 0 | J13: =AU!AD29 -> 0 | K13: =AU!AG29 -> 0 | L13: =AU!AJ29 -> 0 | M13: =AU!AM29 -> 0 | N13: =SUM(D13:M13) -> 0 | Q13: =AU!C47 -> - | R13: =IF(AU!F47=0,"",AU!F47) | S13: =AU!L47 -> 0 | T13: =AU!O47 -> 0 | U13: =AU!R47 -> 0 | V13: =AU!U47 -> 0 | W13: =AU!X47 -> 0 | X13: =AU!AA47 -> 0 | Y13: =AU!AD47 -> 0 | Z13: =AU!AG47 -> 0 | AA13: =AU!AJ47 -> 0 | AB13: =AU!AM47 -> 0 | AC13: =SUM(S13:AB13) -> 0
B14: =AU!C30 -> - | C14: =IF(AU!F30=0,"",AU!F30) | D14: =AU!L30 -> 0 | E14: =AU!O30 -> 0 | F14: =AU!R30 -> 0 | G14: =AU!U30 -> 0 | H14: =AU!X30 -> 0 | I14: =AU!AA30 -> 0 | J14: =AU!AD30 -> 0 | K14: =AU!AG30 -> 0 | L14: =AU!AJ30 -> 0 | M14: =AU!AM30 -> 0 | N14: =SUM(D14:M14) -> 0 | Q14: =AU!C48 -> - | R14: =IF(AU!F48=0,"",AU!F48) | S14: =AU!L48 -> 0 | T14: =AU!O48 -> 0 | U14: =AU!R48 -> 0 | V14: =AU!U48 -> 0 | W14: =AU!X48 -> 0 | X14: =AU!AA48 -> 0 | Y14: =AU!AD48 -> 0 | Z14: =AU!AG48 -> 0 | AA14: =AU!AJ48 -> 0 | AB14: =AU!AM48 -> 0 | AC14: =SUM(S14:AB14) -> 0
B15: =AU!C31 -> - | C15: =IF(AU!F31=0,"",AU!F31) | D15: =AU!L31 -> 0 | E15: =AU!O31 -> 0 | F15: =AU!R31 -> 0 | G15: =AU!U31 -> 0 | H15: =AU!X31 -> 0 | I15: =AU!AA31 -> 0 | J15: =AU!AD31 -> 0 | K15: =AU!AG31 -> 0 | L15: =AU!AJ31 -> 0 | M15: =AU!AM31 -> 0 | N15: =SUM(D15:M15) -> 0 | Q15: =AU!C49 -> - | R15: =IF(AU!F49=0,"",AU!F49) | S15: =AU!L49 -> 0 | T15: =AU!O49 -> 0 | U15: =AU!R49 -> 0 | V15: =AU!U49 -> 0 | W15: =AU!X49 -> 0 | X15: =AU!AA49 -> 0 | Y15: =AU!AD49 -> 0 | Z15: =AU!AG49 -> 0 | AA15: =AU!AJ49 -> 0 | AB15: =AU!AM49 -> 0 | AC15: =SUM(S15:AB15) -> 0
... B19: =AU!C35 -> - | C19: =IF(AU!F35=0,"",AU!F35) | D19: =AU!L35 -> 0 | E19: =AU!O35 -> 0 | F19: =AU!R35 -> 0 | G19: =AU!U35 -> 0 | H19: =AU!X35 -> 0 | I19: =AU!AA35 -> 0 | J19: =AU!AD35 -> 0 | K19: =AU!AG35 -> 0 | L19: =AU!AJ35 -> 0 | M19: =AU!AM35 -> 0 | N19: =SUM(D19:M19) -> 0 | Q19: =AU!C53 -> - | R19: =IF(AU!F53=0,"",AU!F53) | S19: =AU!L53 -> 0 | T19: =AU!O53 -> 0 | U19: =AU!R53 -> 0 | V19: =AU!U53 -> 0 | W19: =AU!X53 -> 0 | X19: =AU!AA53 -> 0 | Y19: =AU!AD53 -> 0 | Z19: =AU!AG53 -> 0 | AA19: =AU!AJ53 -> 0 | AB19: =AU!AM53 -> 0 | AC19: =SUM(S19:AB19) -> 0
B20: =AU!C55& " Man months" -> 1. TAP Man months | Q20: =B20 -> 1. TAP Man months
B21: =AU!C56 -> AC staff et al. | C21: =IF(AU!F56=0,"",AU!F56) | D21: =AU!L56 -> 0 | E21: =AU!O56 -> 0 | F21: =AU!R56 -> 0 | G21: =AU!U56 -> 0 | H21: =AU!X56 -> 0 | I21: =AU!AA56 -> 0 | J21: =AU!AD56 -> 0 | K21: =AU!AG56 -> 0 | L21: =AU!AJ56 -> 0 | M21: =AU!AM56 -> 0 | N21: =SUM(D21:M21) -> 0 | Q21: =AU!C74 -> - | R21: =IF(AU!F74=0,"",AU!F74) | S21: =AU!L74 -> 0 | T21: =AU!O74 -> 0 | U21: =AU!R74 -> 0 | V21: =AU!U74 -> 0 | W21: =AU!X74 -> 0 | X21: =AU!AA74 -> 0 | Y21: =AU!AD74 -> 0 | Z21: =AU!AG74 -> 0 | AA21: =AU!AJ74 -> 0 | AB21: =AU!AM74 -> 0 | AC21: =SUM(S21:AB21) -> 0
B22: =AU!C57 -> - | C22: =IF(AU!F57=0,"",AU!F57) | D22: =AU!L57 -> 0 | E22: =AU!O57 -> 0 | F22: =AU!R57 -> 0 | G22: =AU!U57 -> 0 | H22: =AU!X57 -> 0 | I22: =AU!AA57 -> 0 | J22: =AU!AD57 -> 0 | K22: =AU!AG57 -> 0 | L22: =AU!AJ57 -> 0 | M22: =AU!AM57 -> 0 | N22: =SUM(D22:M22) -> 0 | Q22: =AU!C75 -> - | R22: =IF(AU!F75=0,"",AU!F75) | S22: =AU!L75 -> 0 | T22: =AU!O75 -> 0 | U22: =AU!R75 -> 0 | V22: =AU!U75 -> 0 | W22: =AU!X75 -> 0 | X22: =AU!AA75 -> 0 | Y22: =AU!AD75 -> 0 | Z22: =AU!AG75 -> 0 | AA22: =AU!AJ75 -> 0 | AB22: =AU!AM75 -> 0 | AC22: =SUM(S22:AB22) -> 0
B23: =AU!C58 -> - | C23: =IF(AU!F58=0,"",AU!F58) | D23: =AU!L58 -> 0 | E23: =AU!O58 -> 0 | F23: =AU!R58 -> 0 | G23: =AU!U58 -> 0 | H23: =AU!X58 -> 0 | I23: =AU!AA58 -> 0 | J23: =AU!AD58 -> 0 | K23: =AU!AG58 -> 0 | L23: =AU!AJ58 -> 0 | M23: =AU!AM58 -> 0 | N23: =SUM(D23:M23) -> 0 | Q23: =AU!C76 -> - | R23: =IF(AU!F76=0,"",AU!F76) | S23: =AU!L76 -> 0 | T23: =AU!O76 -> 0 | U23: =AU!R76 -> 0 | V23: =AU!U76 -> 0 | W23: =AU!X76 -> 0 | X23: =AU!AA76 -> 0 | Y23: =AU!AD76 -> 0 | Z23: =AU!AG76 -> 0 | AA23: =AU!AJ76 -> 0 | AB23: =AU!AM76 -> 0 | AC23: =SUM(S23:AB23) -> 0
B24: =AU!C59 -> - | C24: =IF(AU!F59=0,"",AU!F59) | D24: =AU!L59 -> 0 | E24: =AU!O59 -> 0 | F24: =AU!R59 -> 0 | G24: =AU!U59 -> 0 | H24: =AU!X59 -> 0 | I24: =AU!AA59 -> 0 | J24: =AU!AD59 -> 0 | K24: =AU!AG59 -> 0 | L24: =AU!AJ59 -> 0 | M24: =AU!AM59 -> 0 | N24: =SUM(D24:M24) -> 0 | Q24: =AU!C77 -> - | R24: =IF(AU!F77=0,"",AU!F77) | S24: =AU!L77 -> 0 | T24: =AU!O77 -> 0 | U24: =AU!R77 -> 0 | V24: =AU!U77 -> 0 | W24: =AU!X77 -> 0 | X24: =AU!AA77 -> 0 | Y24: =AU!AD77 -> 0 | Z24: =AU!AG77 -> 0 | AA24: =AU!AJ77 -> 0 | AB24: =AU!AM77 -> 0 | AC24: =SUM(S24:AB24) -> 0
B25: =AU!C60 -> - | C25: =IF(AU!F60=0,"",AU!F60) | D25: =AU!L60 -> 0 | E25: =AU!O60 -> 0 | F25: =AU!R60 -> 0 | G25: =AU!U60 -> 0 | H25: =AU!X60 -> 0 | I25: =AU!AA60 -> 0 | J25: =AU!AD60 -> 0 | K25: =AU!AG60 -> 0 | L25: =AU!AJ60 -> 0 | M25: =AU!AM60 -> 0 | N25: =SUM(D25:M25) -> 0 | Q25: =AU!C78 -> - | R25: =IF(AU!F78=0,"",AU!F78) | S25: =AU!L78 -> 0 | T25: =AU!O78 -> 0 | U25: =AU!R78 -> 0 | V25: =AU!U78 -> 0 | W25: =AU!X78 -> 0 | X25: =AU!AA78 -> 0 | Y25: =AU!AD78 -> 0 | Z25: =AU!AG78 -> 0 | AA25: =AU!AJ78 -> 0 | AB25: =AU!AM78 -> 0 | AC25: =SUM(S25:AB25) -> 0
B26: =AU!C61 -> - | C26: =IF(AU!F61=0,"",AU!F61) | D26: =AU!L61 -> 0 | E26: =AU!O61 -> 0 | F26: =AU!R61 -> 0 | G26: =AU!U61 -> 0 | H26: =AU!X61 -> 0 | I26: =AU!AA61 -> 0 | J26: =AU!AD61 -> 0 | K26: =AU!AG61 -> 0 | L26: =AU!AJ61 -> 0 | M26: =AU!AM61 -> 0 | N26: =SUM(D26:M26) -> 0 | Q26: =AU!C79 -> - | R26: =IF(AU!F79=0,"",AU!F79) | S26: =AU!L79 -> 0 | T26: =AU!O79 -> 0 | U26: =AU!R79 -> 0 | V26: =AU!U79 -> 0 | W26: =AU!X79 -> 0 | X26: =AU!AA79 -> 0 | Y26: =AU!AD79 -> 0 | Z26: =AU!AG79 -> 0 | AA26: =AU!AJ79 -> 0 | AB26: =AU!AM79 -> 0 | AC26: =SUM(S26:AB26) -> 0
B27: =AU!C62 -> - | C27: =IF(AU!F62=0,"",AU!F62) | D27: =AU!L62 -> 0 | E27: =AU!O62 -> 0 | F27: =AU!R62 -> 0 | G27: =AU!U62 -> 0 | H27: =AU!X62 -> 0 | I27: =AU!AA62 -> 0 | J27: =AU!AD62 -> 0 | K27: =AU!AG62 -> 0 | L27: =AU!AJ62 -> 0 | M27: =AU!AM62 -> 0 | N27: =SUM(D27:M27) -> 0 | Q27: =AU!C80 -> - | R27: =IF(AU!F80=0,"",AU!F80) | S27: =AU!L80 -> 0 | T27: =AU!O80 -> 0 | U27: =AU!R80 -> 0 | V27: =AU!U80 -> 0 | W27: =AU!X80 -> 0 | X27: =AU!AA80 -> 0 | Y27: =AU!AD80 -> 0 | Z27: =AU!AG80 -> 0 | AA27: =AU!AJ80 -> 0 | AB27: =AU!AM80 -> 0 | AC27: =SUM(S27:AB27) -> 0
B28: =AU!C63 -> - | C28: =IF(AU!F63=0,"",AU!F63) | D28: =AU!L63 -> 0 | E28: =AU!O63 -> 0 | F28: =AU!R63 -> 0 | G28: =AU!U63 -> 0 | H28: =AU!X63 -> 0 | I28: =AU!AA63 -> 0 | J28: =AU!AD63 -> 0 | K28: =AU!AG63 -> 0 | L28: =AU!AJ63 -> 0 | M28: =AU!AM63 -> 0 | N28: =SUM(D28:M28) -> 0 | Q28: =AU!C81 -> - | R28: =IF(AU!F81=0,"",AU!F81) | S28: =AU!L81 -> 0 | T28: =AU!O81 -> 0 | U28: =AU!R81 -> 0 | V28: =AU!U81 -> 0 | W28: =AU!X81 -> 0 | X28: =AU!AA81 -> 0 | Y28: =AU!AD81 -> 0 | Z28: =AU!AG81 -> 0 | AA28: =AU!AJ81 -> 0 | AB28: =AU!AM81 -> 0 | AC28: =SUM(S28:AB28) -> 0
B29: =AU!C64 -> - | C29: =IF(AU!F64=0,"",AU!F64) | D29: =AU!L64 -> 0 | E29: =AU!O64 -> 0 | F29: =AU!R64 -> 0 | G29: =AU!U64 -> 0 | H29: =AU!X64 -> 0 | I29: =AU!AA64 -> 0 | J29: =AU!AD64 -> 0 | K29: =AU!AG64 -> 0 | L29: =AU!AJ64 -> 0 | M29: =AU!AM64 -> 0 | N29: =SUM(D29:M29) -> 0 | Q29: =AU!C82 -> - | R29: =IF(AU!F82=0,"",AU!F82) | S29: =AU!L82 -> 0 | T29: =AU!O82 -> 0 | U29: =AU!R82 -> 0 | V29: =AU!U82 -> 0 | W29: =AU!X82 -> 0 | X29: =AU!AA82 -> 0 | Y29: =AU!AD82 -> 0 | Z29: =AU!AG82 -> 0 | AA29: =AU!AJ82 -> 0 | AB29: =AU!AM82 -> 0 | AC29: =SUM(S29:AB29) -> 0
B30: =AU!C65 -> - | C30: =IF(AU!F65=0,"",AU!F65) | D30: =AU!L65 -> 0 | E30: =AU!O65 -> 0 | F30: =AU!R65 -> 0 | G30: =AU!U65 -> 0 | H30: =AU!X65 -> 0 | I30: =AU!AA65 -> 0 | J30: =AU!AD65 -> 0 | K30: =AU!AG65 -> 0 | L30: =AU!AJ65 -> 0 | M30: =AU!AM65 -> 0 | N30: =SUM(D30:M30) -> 0 | Q30: =AU!C83 -> - | R30: =IF(AU!F83=0,"",AU!F83) | S30: =AU!L83 -> 0 | T30: =AU!O83 -> 0 | U30: =AU!R83 -> 0 | V30: =AU!U83 -> 0 | W30: =AU!X83 -> 0 | X30: =AU!AA83 -> 0 | Y30: =AU!AD83 -> 0 | Z30: =AU!AG83 -> 0 | AA30: =AU!AJ83 -> 0 | AB30: =AU!AM83 -> 0 | AC30: =SUM(S30:AB30) -> 0
B31: =AU!C66 -> - | C31: =IF(AU!F66=0,"",AU!F66) | D31: =AU!L66 -> 0 | E31: =AU!O66 -> 0 | F31: =AU!R66 -> 0 | G31: =AU!U66 -> 0 | H31: =AU!X66 -> 0 | I31: =AU!AA66 -> 0 | J31: =AU!AD66 -> 0 | K31: =AU!AG66 -> 0 | L31: =AU!AJ66 -> 0 | M31: =AU!AM66 -> 0 | N31: =SUM(D31:M31) -> 0 | Q31: =AU!C84 -> - | R31: =IF(AU!F84=0,"",AU!F84) | S31: =AU!L84 -> 0 | T31: =AU!O84 -> 0 | U31: =AU!R84 -> 0 | V31: =AU!U84 -> 0 | W31: =AU!X84 -> 0 | X31: =AU!AA84 -> 0 | Y31: =AU!AD84 -> 0 | Z31: =AU!AG84 -> 0 | AA31: =AU!AJ84 -> 0 | AB31: =AU!AM84 -> 0 | AC31: =SUM(S31:AB31) -> 0
B32: =AU!C67 -> - | C32: =IF(AU!F67=0,"",AU!F67) | D32: =AU!L67 -> 0 | E32: =AU!O67 -> 0 | F32: =AU!R67 -> 0 | G32: =AU!U67 -> 0 | H32: =AU!X67 -> 0 | I32: =AU!AA67 -> 0 | J32: =AU!AD67 -> 0 | K32: =AU!AG67 -> 0 | L32: =AU!AJ67 -> 0 | M32: =AU!AM67 -> 0 | N32: =SUM(D32:M32) -> 0 | Q32: =AU!C85 -> - | R32: =IF(AU!F85=0,"",AU!F85) | S32: =AU!L85 -> 0 | T32: =AU!O85 -> 0 | U32: =AU!R85 -> 0 | V32: =AU!U85 -> 0 | W32: =AU!X85 -> 0 | X32: =AU!AA85 -> 0 | Y32: =AU!AD85 -> 0 | Z32: =AU!AG85 -> 0 | AA32: =AU!AJ85 -> 0 | AB32: =AU!AM85 -> 0 | AC32: =SUM(S32:AB32) -> 0
... B36: =AU!C71 -> - | C36: =IF(AU!F71=0,"",AU!F71) | D36: =AU!L71 -> 0 | E36: =AU!O71 -> 0 | F36: =AU!R71 -> 0 | G36: =AU!U71 -> 0 | H36: =AU!X71 -> 0 | I36: =AU!AA71 -> 0 | J36: =AU!AD71 -> 0 | K36: =AU!AG71 -> 0 | L36: =AU!AJ71 -> 0 | M36: =AU!AM71 -> 0 | N36: =SUM(D36:M36) -> 0 | Q36: =AU!C89 -> - | R36: =IF(AU!F89=0,"",AU!F89) | S36: =AU!L89 -> 0 | T36: =AU!O89 -> 0 | U36: =AU!R89 -> 0 | V36: =AU!U89 -> 0 | W36: =AU!X89 -> 0 | X36: =AU!AA89 -> 0 | Y36: =AU!AD89 -> 0 | Z36: =AU!AG89 -> 0 | AA36: =AU!AJ89 -> 0 | AB36: =AU!AM89 -> 0 | AC36: =SUM(S36:AB36) -> 0
B37: Total | D37: =SUM(D4:D36) -> 18 | E37: =SUM(E4:E36) -> 36 | F37: =SUM(F4:F36) -> 48 | G37: =SUM(G4:G36) -> 42 | H37: =SUM(H4:H36) -> 24 | I37: =SUM(I4:I36) -> 12 | J37: =SUM(J4:J36) -> 0 | K37: =SUM(K4:K36) -> 0 | ... N37: =SUM(N4:N36) -> 180 | Q37: Total | S37: =SUM(S4:S36) -> 0 | T37: =SUM(T4:T36) -> 0 | U37: =SUM(U4:U36) -> 0 | V37: =SUM(V4:V36) -> 0 | W37: =SUM(W4:W36) -> 0 | X37: =SUM(X4:X36) -> 0 | Y37: =SUM(Y4:Y36) -> 0 | Z37: =SUM(Z4:Z36) -> 0 | ... AC37: =SUM(AC4:AC36) -> 0
B39: =AU!C19&" Salary costs " -> 1. VIP Salary costs | D39: =AU!L15 -> Year 1 | E39: =AU!O15 -> Year 2 | F39: =AU!R15 -> Year 3 | G39: =AU!U15 -> Year 4 | H39: =AU!X15 -> Year 5 | I39: =AU!AA15 -> Year 6 | J39: =AU!AD15 -> Year 7 | K39: =AU!AG15 -> Year 8 | L39: =AU!AJ15 -> Year 9 | M39: =AU!AM15 -> Year 10 | N39: Total | Q39: =B39 -> 1. VIP Salary costs | S39: =AU!L15 -> Year 1 | T39: =AU!O15 -> Year 2 | U39: =AU!R15 -> Year 3 | V39: =AU!U15 -> Year 4 | W39: =AU!X15 -> Year 5 | X39: =AU!AA15 -> Year 6 | Y39: =AU!AD15 -> Year 7 | Z39: =AU!AG15 -> Year 8 | AA39: =AU!AJ15 -> Year 9 | AB39: =AU!AM15 -> Year 10 | AC39: Total
B40: =AU!C20 -> Postdoc | C40: =IF(AU!F20=0,"",AU!F20) | D40: =AU!N20 -> 662001.6 | E40: =AU!Q20 -> 681861.65 | F40: =AU!T20 -> 702317.5 | G40: =AU!W20 -> 0 | H40: =AU!Z20 -> 0 | I40: =AU!AC20 -> 0 | J40: =AU!AF20 -> 0 | K40: =AU!AI20 -> 0 | L40: =AU!AL20 -> 0 | M40: =AU!AO20 -> 0 | N40: =SUM(D40:M40) -> 2046180.7 | Q40: =AU!C38 -> - | R40: =IF(AU!F38=0,"",AU!F38) | S40: =AU!N38 | T40: =AU!Q38 | U40: =AU!T38 | V40: =AU!W38 | W40: =AU!Z38 | X40: =AU!AC38 | Y40: =AU!AF38 | Z40: =AU!AI38 | AA40: =AU!AL38 | AB40: =AU!AO38 | AC40: =SUM(S40:AB40) -> 0
B41: =AU!C21 -> Postdoc | C41: =IF(AU!F21=0,"",AU!F21) | D41: =AU!N21 -> 0 | E41: =AU!Q21 -> 681861.65 | F41: =AU!T21 -> 702317.5 | G41: =AU!W21 -> 723387.02 | H41: =AU!Z21 -> 0 | I41: =AU!AC21 -> 0 | J41: =AU!AF21 -> 0 | K41: =AU!AI21 -> 0 | L41: =AU!AL21 -> 0 | M41: =AU!AO21 -> 0 | N41: =SUM(D41:M41) -> 2107566.2 | Q41: =AU!C39 -> - | R41: =IF(AU!F39=0,"",AU!F39) | S41: =AU!N39 | T41: =AU!Q39 | U41: =AU!T39 | V41: =AU!W39 | W41: =AU!Z39 | X41: =AU!AC39 | Y41: =AU!AF39 | Z41: =AU!AI39 | AA41: =AU!AL39 | AB41: =AU!AO39 | AC41: =SUM(S41:AB41) -> 0
B42: =AU!C22 -> Postdoc | C42: =IF(AU!F22=0,"",AU!F22) | D42: =AU!N22 -> 0 | E42: =AU!Q22 -> 0 | F42: =AU!T22 -> 351158.75 | G42: =AU!W22 -> 723387.02 | H42: =AU!Z22 -> 745088.63 | I42: =AU!AC22 -> 383720.65 | J42: =AU!AF22 -> 0 | K42: =AU!AI22 -> 0 | L42: =AU!AL22 -> 0 | M42: =AU!AO22 -> 0 | N42: =SUM(D42:M42) -> 2203355.1 | Q42: =AU!C40 -> - | R42: =IF(AU!F40=0,"",AU!F40) | S42: =AU!N40 | T42: =AU!Q40 | U42: =AU!T40 | V42: =AU!W40 | W42: =AU!Z40 | X42: =AU!AC40 | Y42: =AU!AF40 | Z42: =AU!AI40 | AA42: =AU!AL40 | AB42: =AU!AO40 | AC42: =SUM(S42:AB42) -> 0
B43: =AU!C23 -> PhD Student | C43: =IF(AU!F23=0,"",AU!F23) | D43: =AU!N23 -> 267346.8 | E43: =AU!Q23 -> 550734.41 | F43: =AU!T23 -> 567256.44 | G43: =AU!W23 -> 292137.07 | H43: =AU!Z23 -> 0 | I43: =AU!AC23 -> 0 | J43: =AU!AF23 -> 0 | K43: =AU!AI23 -> 0 | L43: =AU!AL23 -> 0 | M43: =AU!AO23 -> 0 | N43: =SUM(D43:M43) -> 1677474.7 | Q43: =AU!C41 -> - | R43: =IF(AU!F41=0,"",AU!F41) | S43: =AU!N41 | T43: =AU!Q41 | U43: =AU!T41 | V43: =AU!W41 | W43: =AU!Z41 | X43: =AU!AC41 | Y43: =AU!AF41 | Z43: =AU!AI41 | AA43: =AU!AL41 | AB43: =AU!AO41 | AC43: =SUM(S43:AB43) -> 0
B44: =AU!C24 -> PhD Student | C44: =IF(AU!F24=0,"",AU!F24) | D44: =AU!N24 -> 0 | E44: =AU!Q24 -> 0 | F44: =AU!T24 -> 283628.22 | G44: =AU!W24 -> 584274.13 | H44: =AU!Z24 -> 601802.36 | I44: =AU!AC24 -> 309928.21 | J44: =AU!AF24 -> 0 | K44: =AU!AI24 -> 0 | L44: =AU!AL24 -> 0 | M44: =AU!AO24 -> 0 | N44: =SUM(D44:M44) -> 1779632.9 | Q44: =AU!C42 -> - | R44: =IF(AU!F42=0,"",AU!F42) | S44: =AU!N42 | T44: =AU!Q42 | U44: =AU!T42 | V44: =AU!W42 | W44: =AU!Z42 | X44: =AU!AC42 | Y44: =AU!AF42 | Z44: =AU!AI42 | AA44: =AU!AL42 | AB44: =AU!AO42 | AC44: =SUM(S44:AB44) -> 0
B45: =AU!C25 -> - | C45: =IF(AU!F25=0,"",AU!F25) | D45: =AU!N25 | E45: =AU!Q25 | F45: =AU!T25 | G45: =AU!W25 | H45: =AU!Z25 | I45: =AU!AC25 | J45: =AU!AF25 | K45: =AU!AI25 | L45: =AU!AL25 | M45: =AU!AO25 | N45: =SUM(D45:M45) -> 0 | Q45: =AU!C43 -> - | R45: =IF(AU!F43=0,"",AU!F43) | S45: =AU!N43 | T45: =AU!Q43 | U45: =AU!T43 | V45: =AU!W43 | W45: =AU!Z43 | X45: =AU!AC43 | Y45: =AU!AF43 | Z45: =AU!AI43 | AA45: =AU!AL43 | AB45: =AU!AO43 | AC45: =SUM(S45:AB45) -> 0
B46: =AU!C26 -> - | C46: =IF(AU!F26=0,"",AU!F26) | D46: =AU!N26 | E46: =AU!Q26 | F46: =AU!T26 | G46: =AU!W26 | H46: =AU!Z26 | I46: =AU!AC26 | J46: =AU!AF26 | K46: =AU!AI26 | L46: =AU!AL26 | M46: =AU!AO26 | N46: =SUM(D46:M46) -> 0 | Q46: =AU!C44 -> - | R46: =IF(AU!F44=0,"",AU!F44) | S46: =AU!N44 | T46: =AU!Q44 | U46: =AU!T44 | V46: =AU!W44 | W46: =AU!Z44 | X46: =AU!AC44 | Y46: =AU!AF44 | Z46: =AU!AI44 | AA46: =AU!AL44 | AB46: =AU!AO44 | AC46: =SUM(S46:AB46) -> 0
B47: =AU!C27 -> - | C47: =IF(AU!F27=0,"",AU!F27) | D47: =AU!N27 | E47: =AU!Q27 | F47: =AU!T27 | G47: =AU!W27 | H47: =AU!Z27 | I47: =AU!AC27 | J47: =AU!AF27 | K47: =AU!AI27 | L47: =AU!AL27 | M47: =AU!AO27 | N47: =SUM(D47:M47) -> 0 | Q47: =AU!C45 -> - | R47: =IF(AU!F45=0,"",AU!F45) | S47: =AU!N45 | T47: =AU!Q45 | U47: =AU!T45 | V47: =AU!W45 | W47: =AU!Z45 | X47: =AU!AC45 | Y47: =AU!AF45 | Z47: =AU!AI45 | AA47: =AU!AL45 | AB47: =AU!AO45 | AC47: =SUM(S47:AB47) -> 0
B48: =AU!C28 -> - | C48: =IF(AU!F28=0,"",AU!F28) | D48: =AU!N28 | E48: =AU!Q28 | F48: =AU!T28 | G48: =AU!W28 | H48: =AU!Z28 | I48: =AU!AC28 | J48: =AU!AF28 | K48: =AU!AI28 | L48: =AU!AL28 | M48: =AU!AO28 | N48: =SUM(D48:M48) -> 0 | Q48: =AU!C46 -> - | R48: =IF(AU!F46=0,"",AU!F46) | S48: =AU!N46 | T48: =AU!Q46 | U48: =AU!T46 | V48: =AU!W46 | W48: =AU!Z46 | X48: =AU!AC46 | Y48: =AU!AF46 | Z48: =AU!AI46 | AA48: =AU!AL46 | AB48: =AU!AO46 | AC48: =SUM(S48:AB48) -> 0
B49: =AU!C29 -> - | C49: =IF(AU!F29=0,"",AU!F29) | D49: =AU!N29 | E49: =AU!Q29 | F49: =AU!T29 | G49: =AU!W29 | H49: =AU!Z29 | I49: =AU!AC29 | J49: =AU!AF29 | K49: =AU!AI29 | L49: =AU!AL29 | M49: =AU!AO29 | N49: =SUM(D49:M49) -> 0 | Q49: =AU!C47 -> - | R49: =IF(AU!F47=0,"",AU!F47) | S49: =AU!N47 | T49: =AU!Q47 | U49: =AU!T47 | V49: =AU!W47 | W49: =AU!Z47 | X49: =AU!AC47 | Y49: =AU!AF47 | Z49: =AU!AI47 | AA49: =AU!AL47 | AB49: =AU!AO47 | AC49: =SUM(S49:AB49) -> 0
B50: =AU!C30 -> - | C50: =IF(AU!F30=0,"",AU!F30) | D50: =AU!N30 | E50: =AU!Q30 | F50: =AU!T30 | G50: =AU!W30 | H50: =AU!Z30 | I50: =AU!AC30 | J50: =AU!AF30 | K50: =AU!AI30 | L50: =AU!AL30 | M50: =AU!AO30 | N50: =SUM(D50:M50) -> 0 | Q50: =AU!C48 -> - | R50: =IF(AU!F48=0,"",AU!F48) | S50: =AU!N48 | T50: =AU!Q48 | U50: =AU!T48 | V50: =AU!W48 | W50: =AU!Z48 | X50: =AU!AC48 | Y50: =AU!AF48 | Z50: =AU!AI48 | AA50: =AU!AL48 | AB50: =AU!AO48 | AC50: =SUM(S50:AB50) -> 0
B51: =AU!C31 -> - | C51: =IF(AU!F31=0,"",AU!F31) | D51: =AU!N31 | E51: =AU!Q31 | F51: =AU!T31 | G51: =AU!W31 | H51: =AU!Z31 | I51: =AU!AC31 | J51: =AU!AF31 | K51: =AU!AI31 | L51: =AU!AL31 | M51: =AU!AO31 | N51: =SUM(D51:M51) -> 0 | Q51: =AU!C49 -> - | R51: =IF(AU!F49=0,"",AU!F49) | S51: =AU!N49 | T51: =AU!Q49 | U51: =AU!T49 | V51: =AU!W49 | W51: =AU!Z49 | X51: =AU!AC49 | Y51: =AU!AF49 | Z51: =AU!AI49 | AA51: =AU!AL49 | AB51: =AU!AO49 | AC51: =SUM(S51:AB51) -> 0
... B55: =AU!C35 -> - | C55: =IF(AU!F35=0,"",AU!F35) | D55: =AU!N35 | E55: =AU!Q35 | F55: =AU!T35 | G55: =AU!W35 | H55: =AU!Z35 | I55: =AU!AC35 | J55: =AU!AF35 | K55: =AU!AI35 | L55: =AU!AL35 | M55: =AU!AO35 | N55: =SUM(D55:M55) -> 0 | Q55: =AU!C53 -> - | R55: =IF(AU!F53=0,"",AU!F53) | S55: =AU!N53 | T55: =AU!Q53 | U55: =AU!T53 | V55: =AU!W53 | W55: =AU!Z53 | X55: =AU!AC53 | Y55: =AU!AF53 | Z55: =AU!AI53 | AA55: =AU!AL53 | AB55: =AU!AO53 | AC55: =SUM(S55:AB55) -> 0
B56: =AU!C55&" Salary costs" -> 1. TAP Salary costs | Q56: =B56 -> 1. TAP Salary costs
B57: =AU!C56 -> AC staff et al. | C57: =IF(AU!F56=0,"",AU!F56) | D57: =AU!N56 -> 0 | E57: =AU!Q56 -> 0 | F57: =AU!T56 -> 0 | G57: =AU!W56 -> 0 | H57: =AU!Z56 -> 0 | I57: =AU!AC56 -> 0 | J57: =AU!AF56 -> 0 | K57: =AU!AI56 -> 0 | L57: =AU!AL56 -> 0 | M57: =AU!AO56 -> 0 | N57: =SUM(D57:M57) -> 0 | Q57: =AU!C74 -> - | R57: =IF(AU!F74=0,"",AU!F74) | S57: =AU!N74 | T57: =AU!Q74 | U57: =AU!T74 | V57: =AU!W74 | W57: =AU!Z74 | X57: =AU!AC74 | Y57: =AU!AF74 | Z57: =AU!AI74 | AA57: =AU!AL74 | AB57: =AU!AO74 | AC57: =SUM(S57:AB57) -> 0
B58: =AU!C57 -> - | C58: =IF(AU!F57=0,"",AU!F57) | D58: =AU!N57 | E58: =AU!Q57 | F58: =AU!T57 | G58: =AU!W57 | H58: =AU!Z57 | I58: =AU!AC57 | J58: =AU!AF57 | K58: =AU!AI57 | L58: =AU!AL57 | M58: =AU!AO57 | N58: =SUM(D58:M58) -> 0 | Q58: =AU!C75 -> - | R58: =IF(AU!F75=0,"",AU!F75) | S58: =AU!N75 | T58: =AU!Q75 | U58: =AU!T75 | V58: =AU!W75 | W58: =AU!Z75 | X58: =AU!AC75 | Y58: =AU!AF75 | Z58: =AU!AI75 | AA58: =AU!AL75 | AB58: =AU!AO75 | AC58: =SUM(S58:AB58) -> 0
B59: =AU!C58 -> - | C59: =IF(AU!F58=0,"",AU!F58) | D59: =AU!N58 | E59: =AU!Q58 | F59: =AU!T58 | G59: =AU!W58 | H59: =AU!Z58 | I59: =AU!AC58 | J59: =AU!AF58 | K59: =AU!AI58 | L59: =AU!AL58 | M59: =AU!AO58 | N59: =SUM(D59:M59) -> 0 | Q59: =AU!C76 -> - | R59: =IF(AU!F76=0,"",AU!F76) | S59: =AU!N76 | T59: =AU!Q76 | U59: =AU!T76 | V59: =AU!W76 | W59: =AU!Z76 | X59: =AU!AC76 | Y59: =AU!AF76 | Z59: =AU!AI76 | AA59: =AU!AL76 | AB59: =AU!AO76 | AC59: =SUM(S59:AB59) -> 0
B60: =AU!C59 -> - | C60: =IF(AU!F59=0,"",AU!F59) | D60: =AU!N59 | E60: =AU!Q59 | F60: =AU!T59 | G60: =AU!W59 | H60: =AU!Z59 | I60: =AU!AC59 | J60: =AU!AF59 | K60: =AU!AI59 | L60: =AU!AL59 | M60: =AU!AO59 | N60: =SUM(D60:M60) -> 0 | Q60: =AU!C77 -> - | R60: =IF(AU!F77=0,"",AU!F77) | S60: =AU!N77 | T60: =AU!Q77 | U60: =AU!T77 | V60: =AU!W77 | W60: =AU!Z77 | X60: =AU!AC77 | Y60: =AU!AF77 | Z60: =AU!AI77 | AA60: =AU!AL77 | AB60: =AU!AO77 | AC60: =SUM(S60:AB60) -> 0
B61: =AU!C60 -> - | C61: =IF(AU!F60=0,"",AU!F60) | D61: =AU!N60 | E61: =AU!Q60 | F61: =AU!T60 | G61: =AU!W60 | H61: =AU!Z60 | I61: =AU!AC60 | J61: =AU!AF60 | K61: =AU!AI60 | L61: =AU!AL60 | M61: =AU!AO60 | N61: =SUM(D61:M61) -> 0 | Q61: =AU!C78 -> - | R61: =IF(AU!F78=0,"",AU!F78) | S61: =AU!N78 | T61: =AU!Q78 | U61: =AU!T78 | V61: =AU!W78 | W61: =AU!Z78 | X61: =AU!AC78 | Y61: =AU!AF78 | Z61: =AU!AI78 | AA61: =AU!AL78 | AB61: =AU!AO78 | AC61: =SUM(S61:AB61) -> 0
B62: =AU!C61 -> - | C62: =IF(AU!F61=0,"",AU!F61) | D62: =AU!N61 | E62: =AU!Q61 | F62: =AU!T61 | G62: =AU!W61 | H62: =AU!Z61 | I62: =AU!AC61 | J62: =AU!AF61 | K62: =AU!AI61 | L62: =AU!AL61 | M62: =AU!AO61 | N62: =SUM(D62:M62) -> 0 | Q62: =AU!C79 -> - | R62: =IF(AU!F79=0,"",AU!F79) | S62: =AU!N79 | T62: =AU!Q79 | U62: =AU!T79 | V62: =AU!W79 | W62: =AU!Z79 | X62: =AU!AC79 | Y62: =AU!AF79 | Z62: =AU!AI79 | AA62: =AU!AL79 | AB62: =AU!AO79 | AC62: =SUM(S62:AB62) -> 0
B63: =AU!C62 -> - | C63: =IF(AU!F62=0,"",AU!F62) | D63: =AU!N62 | E63: =AU!Q62 | F63: =AU!T62 | G63: =AU!W62 | H63: =AU!Z62 | I63: =AU!AC62 | J63: =AU!AF62 | K63: =AU!AI62 | L63: =AU!AL62 | M63: =AU!AO62 | N63: =SUM(D63:M63) -> 0 | Q63: =AU!C80 -> - | R63: =IF(AU!F80=0,"",AU!F80) | S63: =AU!N80 | T63: =AU!Q80 | U63: =AU!T80 | V63: =AU!W80 | W63: =AU!Z80 | X63: =AU!AC80 | Y63: =AU!AF80 | Z63: =AU!AI80 | AA63: =AU!AL80 | AB63: =AU!AO80 | AC63: =SUM(S63:AB63) -> 0
B64: =AU!C63 -> - | C64: =IF(AU!F63=0,"",AU!F63) | D64: =AU!N63 | E64: =AU!Q63 | F64: =AU!T63 | G64: =AU!W63 | H64: =AU!Z63 | I64: =AU!AC63 | J64: =AU!AF63 | K64: =AU!AI63 | L64: =AU!AL63 | M64: =AU!AO63 | N64: =SUM(D64:M64) -> 0 | Q64: =AU!C81 -> - | R64: =IF(AU!F81=0,"",AU!F81) | S64: =AU!N81 | T64: =AU!Q81 | U64: =AU!T81 | V64: =AU!W81 | W64: =AU!Z81 | X64: =AU!AC81 | Y64: =AU!AF81 | Z64: =AU!AI81 | AA64: =AU!AL81 | AB64: =AU!AO81 | AC64: =SUM(S64:AB64) -> 0
B65: =AU!C64 -> - | C65: =IF(AU!F64=0,"",AU!F64) | D65: =AU!N64 | E65: =AU!Q64 | F65: =AU!T64 | G65: =AU!W64 | H65: =AU!Z64 | I65: =AU!AC64 | J65: =AU!AF64 | K65: =AU!AI64 | L65: =AU!AL64 | M65: =AU!AO64 | N65: =SUM(D65:M65) -> 0 | Q65: =AU!C82 -> - | R65: =IF(AU!F82=0,"",AU!F82) | S65: =AU!N82 | T65: =AU!Q82 | U65: =AU!T82 | V65: =AU!W82 | W65: =AU!Z82 | X65: =AU!AC82 | Y65: =AU!AF82 | Z65: =AU!AI82 | AA65: =AU!AL82 | AB65: =AU!AO82 | AC65: =SUM(S65:AB65) -> 0
B66: =AU!C65 -> - | C66: =IF(AU!F65=0,"",AU!F65) | D66: =AU!N65 | E66: =AU!Q65 | F66: =AU!T65 | G66: =AU!W65 | H66: =AU!Z65 | I66: =AU!AC65 | J66: =AU!AF65 | K66: =AU!AI65 | L66: =AU!AL65 | M66: =AU!AO65 | N66: =SUM(D66:M66) -> 0 | Q66: =AU!C83 -> - | R66: =IF(AU!F83=0,"",AU!F83) | S66: =AU!N83 | T66: =AU!Q83 | U66: =AU!T83 | V66: =AU!W83 | W66: =AU!Z83 | X66: =AU!AC83 | Y66: =AU!AF83 | Z66: =AU!AI83 | AA66: =AU!AL83 | AB66: =AU!AO83 | AC66: =SUM(S66:AB66) -> 0
B67: =AU!C66 -> - | C67: =IF(AU!F66=0,"",AU!F66) | D67: =AU!N66 | E67: =AU!Q66 | F67: =AU!T66 | G67: =AU!W66 | H67: =AU!Z66 | I67: =AU!AC66 | J67: =AU!AF66 | K67: =AU!AI66 | L67: =AU!AL66 | M67: =AU!AO66 | N67: =SUM(D67:M67) -> 0 | Q67: =AU!C84 -> - | R67: =IF(AU!F84=0,"",AU!F84) | S67: =AU!N84 | T67: =AU!Q84 | U67: =AU!T84 | V67: =AU!W84 | W67: =AU!Z84 | X67: =AU!AC84 | Y67: =AU!AF84 | Z67: =AU!AI84 | AA67: =AU!AL84 | AB67: =AU!AO84 | AC67: =SUM(S67:AB67) -> 0
B68: =AU!C67 -> - | C68: =IF(AU!F67=0,"",AU!F67) | D68: =AU!N67 | E68: =AU!Q67 | F68: =AU!T67 | G68: =AU!W67 | H68: =AU!Z67 | I68: =AU!AC67 | J68: =AU!AF67 | K68: =AU!AI67 | L68: =AU!AL67 | M68: =AU!AO67 | N68: =SUM(D68:M68) -> 0 | Q68: =AU!C85 -> - | R68: =IF(AU!F85=0,"",AU!F85) | S68: =AU!N85 | T68: =AU!Q85 | U68: =AU!T85 | V68: =AU!W85 | W68: =AU!Z85 | X68: =AU!AC85 | Y68: =AU!AF85 | Z68: =AU!AI85 | AA68: =AU!AL85 | AB68: =AU!AO85 | AC68: =SUM(S68:AB68) -> 0
... B72: =AU!C71 -> - | C72: =IF(AU!F71=0,"",AU!F71) | D72: =AU!N71 | E72: =AU!Q71 | F72: =AU!T71 | G72: =AU!W71 | H72: =AU!Z71 | I72: =AU!AC71 | J72: =AU!AF71 | K72: =AU!AI71 | L72: =AU!AL71 | M72: =AU!AO71 | N72: =SUM(D72:M72) -> 0 | Q72: =AU!C89 -> - | R72: =IF(AU!F89=0,"",AU!F89) | S72: =AU!N89 | T72: =AU!Q89 | U72: =AU!T89 | V72: =AU!W89 | W72: =AU!Z89 | X72: =AU!AC89 | Y72: =AU!AF89 | Z72: =AU!AI89 | AA72: =AU!AL89 | AB72: =AU!AO89 | AC72: =SUM(S72:AB72) -> 0
B73: Total | D73: =SUM(D40:D72) -> 929348.4 | E73: =SUM(E40:E72) -> 1914457.7 | F73: =SUM(F40:F72) -> 2606678.4 | G73: =SUM(G40:G72) -> 2323185.2 | H73: =SUM(H40:H72) -> 1346891 | I73: =SUM(I40:I72) -> 693648.86 | J73: =SUM(J40:J72) -> 0 | K73: =SUM(K40:K72) -> 0 | ... N73: =SUM(N40:N72) -> 9814209.6 | Q73: Total | S73: =SUM(S40:S72) -> 0 | T73: =SUM(T40:T72) -> 0 | U73: =SUM(U40:U72) -> 0 | V73: =SUM(V40:V72) -> 0 | W73: =SUM(W66:W72) -> 0 | X73: =SUM(X40:X72) -> 0 | Y73: =SUM(Y66:Y72) -> 0 | Z73: =SUM(Z66:Z72) -> 0 | AA73: =SUM(AA66:AA72) -> 0 | AB73: =SUM(AB66:AB72) -> 0 | AC73: =SUM(AC40:AC72) -> 0
B75: =AU!C94 -> 2. Operation | D75: =AU!L15 -> Year 1 | E75: =AU!O15 -> Year 2 | F75: =AU!R15 -> Year 3 | G75: =AU!U15 -> Year 4 | H75: =AU!X15 -> Year 5 | I75: =AU!AA15 -> Year 6 | J75: =AU!AD15 -> Year 7 | K75: =AU!AG15 -> Year 8 | L75: =AU!AJ15 -> Year 9 | M75: =AU!AM15 -> Year 10 | N75: Total | Q75: =B75 -> 2. Operation | S75: =AU!L15 -> Year 1 | T75: =AU!O15 -> Year 2 | U75: =AU!R15 -> Year 3 | V75: =AU!U15 -> Year 4 | W75: =AU!X15 -> Year 5 | X75: =AU!AA15 -> Year 6 | Y75: =AU!AD15 -> Year 7 | Z75: =AU!AG15 -> Year 8 | AA75: =AU!AJ15 -> Year 9 | AB75: =AU!AM15 -> Year 10 | AC75: Total
B76: =AU!C95 -> Equipment | C76: =IF(AU!F95=0,"",AU!F95) -> High-performance computers | D76: =AU!N95 -> 50000 | E76: =AU!Q95 -> 50000 | F76: =AU!T95 -> 50000 | G76: =AU!W95 -> 0 | H76: =AU!Z95 -> 0 | I76: =AU!AC95 -> 0 | J76: =AU!AF95 -> 0 | K76: =AU!AI95 -> 0 | L76: =AU!AL95 -> 0 | M76: =AU!AO95 -> 0 | N76: =SUM(D76:M76) -> 150000 | Q76: =AU!C123 -> - | R76: =IF(AU!F123=0,"",AU!F123) | S76: =AU!N123 -> 0 | T76: =AU!Q123 -> 0 | U76: =AU!T123 -> 0 | V76: =AU!W123 -> 0 | W76: =AU!Z123 -> 0 | X76: =AU!AC123 -> 0 | Y76: =AU!AF123 -> 0 | Z76: =AU!AI123 -> 0 | AA76: =AU!AL123 -> 0 | AB76: =AU!AO123 -> 0 | AC76: =SUM(S76:AB76) -> 0
B77: =AU!C96 -> Data management | C77: =IF(AU!F96=0,"",AU!F96) -> Cluster time | D77: =AU!N96 -> 50000 | E77: =AU!Q96 -> 50000 | F77: =AU!T96 -> 50000 | G77: =AU!W96 -> 50000 | H77: =AU!Z96 -> 50000 | I77: =AU!AC96 -> 50000 | J77: =AU!AF96 -> 0 | K77: =AU!AI96 -> 0 | L77: =AU!AL96 -> 0 | M77: =AU!AO96 -> 0 | N77: =SUM(D77:M77) -> 300000 | Q77: =AU!C124 -> - | R77: =IF(AU!F124=0,"",AU!F124) | S77: =AU!N124 -> 0 | T77: =AU!Q124 -> 0 | U77: =AU!T124 -> 0 | V77: =AU!W124 -> 0 | W77: =AU!Z124 -> 0 | X77: =AU!AC124 -> 0 | Y77: =AU!AF124 -> 0 | Z77: =AU!AI124 -> 0 | AA77: =AU!AL124 -> 0 | AB77: =AU!AO124 -> 0 | AC77: =SUM(S77:AB77) -> 0
B78: =AU!C97 -> Operating expenses | C78: =IF(AU!F97=0,"",AU!F97) -> Data storage | D78: =AU!N97 -> 100000 | E78: =AU!Q97 -> 100000 | F78: =AU!T97 -> 100000 | G78: =AU!W97 -> 10000 | H78: =AU!Z97 -> 100000 | I78: =AU!AC97 -> 90000 | J78: =AU!AF97 -> 0 | K78: =AU!AI97 -> 0 | L78: =AU!AL97 -> 0 | M78: =AU!AO97 -> 0 | N78: =SUM(D78:M78) -> 500000 | Q78: =AU!C125 -> - | R78: =IF(AU!F125=0,"",AU!F125) | S78: =AU!N125 -> 0 | T78: =AU!Q125 -> 0 | U78: =AU!T125 -> 0 | V78: =AU!W125 -> 0 | W78: =AU!Z125 -> 0 | X78: =AU!AC125 -> 0 | Y78: =AU!AF125 -> 0 | Z78: =AU!AI125 -> 0 | AA78: =AU!AL125 -> 0 | AB78: =AU!AO125 -> 0 | AC78: =SUM(S78:AB78) -> 0
B79: =AU!C98 -> - | C79: =IF(AU!F98=0,"",AU!F98) | D79: =AU!N98 -> 0 | E79: =AU!Q98 -> 0 | F79: =AU!T98 -> 0 | G79: =AU!W98 -> 0 | H79: =AU!Z98 -> 0 | I79: =AU!AC98 -> 0 | J79: =AU!AF98 -> 0 | K79: =AU!AI98 -> 0 | L79: =AU!AL98 -> 0 | M79: =AU!AO98 -> 0 | N79: =SUM(D79:M79) -> 0 | Q79: =AU!C126 -> - | R79: =IF(AU!F126=0,"",AU!F126) | S79: =AU!N126 -> 0 | T79: =AU!Q126 -> 0 | U79: =AU!T126 -> 0 | V79: =AU!W126 -> 0 | W79: =AU!Z126 -> 0 | X79: =AU!AC126 -> 0 | Y79: =AU!AF126 -> 0 | Z79: =AU!AI126 -> 0 | AA79: =AU!AL126 -> 0 | AB79: =AU!AO126 -> 0 | AC79: =SUM(S79:AB79) -> 0
B80: =AU!C99 -> - | C80: =IF(AU!F99=0,"",AU!F99) | D80: =AU!N99 -> 0 | E80: =AU!Q99 -> 0 | F80: =AU!T99 -> 0 | G80: =AU!W99 -> 0 | H80: =AU!Z99 -> 0 | I80: =AU!AC99 -> 0 | J80: =AU!AF99 -> 0 | K80: =AU!AI99 -> 0 | L80: =AU!AL99 -> 0 | M80: =AU!AO99 -> 0 | N80: =SUM(D80:M80) -> 0 | Q80: =AU!C127 -> - | R80: =IF(AU!F127=0,"",AU!F127) | S80: =AU!N127 -> 0 | T80: =AU!Q127 -> 0 | U80: =AU!T127 -> 0 | V80: =AU!W127 -> 0 | W80: =AU!Z127 -> 0 | X80: =AU!AC127 -> 0 | Y80: =AU!AF127 -> 0 | Z80: =AU!AI127 -> 0 | AA80: =AU!AL127 -> 0 | AB80: =AU!AO127 -> 0 | AC80: =SUM(S80:AB80) -> 0
B81: =AU!C100 -> - | C81: =IF(AU!F100=0,"",AU!F100) | D81: =AU!N100 -> 0 | E81: =AU!Q100 -> 0 | F81: =AU!T100 -> 0 | G81: =AU!W100 -> 0 | H81: =AU!Z100 -> 0 | I81: =AU!AC100 -> 0 | J81: =AU!AF100 -> 0 | K81: =AU!AI100 -> 0 | L81: =AU!AL100 -> 0 | M81: =AU!AO100 -> 0 | N81: =SUM(D81:M81) -> 0 | Q81: =AU!C128 -> - | R81: =IF(AU!F128=0,"",AU!F128) | S81: =AU!N128 -> 0 | T81: =AU!Q128 -> 0 | U81: =AU!T128 -> 0 | V81: =AU!W128 -> 0 | W81: =AU!Z128 -> 0 | X81: =AU!AC128 -> 0 | Y81: =AU!AF128 -> 0 | Z81: =AU!AI128 -> 0 | AA81: =AU!AL128 -> 0 | AB81: =AU!AO128 -> 0 | AC81: =SUM(S81:AB81) -> 0
B82: =AU!C101 -> - | C82: =IF(AU!F101=0,"",AU!F101) | D82: =AU!N101 -> 0 | E82: =AU!Q101 -> 0 | F82: =AU!T101 -> 0 | G82: =AU!W101 -> 0 | H82: =AU!Z101 -> 0 | I82: =AU!AC101 -> 0 | J82: =AU!AF101 -> 0 | K82: =AU!AI101 -> 0 | L82: =AU!AL101 -> 0 | M82: =AU!AO101 -> 0 | N82: =SUM(D82:M82) -> 0 | Q82: =AU!C129 -> - | R82: =IF(AU!F129=0,"",AU!F129) | S82: =AU!N129 -> 0 | T82: =AU!Q129 -> 0 | U82: =AU!T129 -> 0 | V82: =AU!W129 -> 0 | W82: =AU!Z129 -> 0 | X82: =AU!AC129 -> 0 | Y82: =AU!AF129 -> 0 | Z82: =AU!AI129 -> 0 | AA82: =AU!AL129 -> 0 | AB82: =AU!AO129 -> 0 | AC82: =SUM(S82:AB82) -> 0
B83: =AU!C102 -> - | C83: =IF(AU!F102=0,"",AU!F102) | D83: =AU!N102 -> 0 | E83: =AU!Q102 -> 0 | F83: =AU!T102 -> 0 | G83: =AU!W102 -> 0 | H83: =AU!Z102 -> 0 | I83: =AU!AC102 -> 0 | J83: =AU!AF102 -> 0 | K83: =AU!AI102 -> 0 | L83: =AU!AL102 -> 0 | M83: =AU!AO102 -> 0 | N83: =SUM(D83:M83) -> 0 | Q83: =AU!C130 -> - | R83: =IF(AU!F130=0,"",AU!F130) | S83: =AU!N130 -> 0 | T83: =AU!Q130 -> 0 | U83: =AU!T130 -> 0 | V83: =AU!W130 -> 0 | W83: =AU!Z130 -> 0 | X83: =AU!AC130 -> 0 | Y83: =AU!AF130 -> 0 | Z83: =AU!AI130 -> 0 | AA83: =AU!AL130 -> 0 | AB83: =AU!AO130 -> 0 | AC83: =SUM(S83:AB83) -> 0
B84: =AU!C103 -> - | C84: =IF(AU!F103=0,"",AU!F103) | D84: =AU!N103 -> 0 | E84: =AU!Q103 -> 0 | F84: =AU!T103 -> 0 | G84: =AU!W103 -> 0 | H84: =AU!Z103 -> 0 | I84: =AU!AC103 -> 0 | J84: =AU!AF103 -> 0 | K84: =AU!AI103 -> 0 | L84: =AU!AL103 -> 0 | M84: =AU!AO103 -> 0 | N84: =SUM(D84:M84) -> 0 | Q84: =AU!C131 -> - | R84: =IF(AU!F131=0,"",AU!F131) | S84: =AU!N131 -> 0 | T84: =AU!Q131 -> 0 | U84: =AU!T131 -> 0 | V84: =AU!W131 -> 0 | W84: =AU!Z131 -> 0 | X84: =AU!AC131 -> 0 | Y84: =AU!AF131 -> 0 | Z84: =AU!AI131 -> 0 | AA84: =AU!AL131 -> 0 | AB84: =AU!AO131 -> 0 | AC84: =SUM(S84:AB84) -> 0
B85: =AU!C104 -> - | C85: =IF(AU!F104=0,"",AU!F104) | D85: =AU!N104 -> 0 | E85: =AU!Q104 -> 0 | F85: =AU!T104 -> 0 | G85: =AU!W104 -> 0 | H85: =AU!Z104 -> 0 | I85: =AU!AC104 -> 0 | J85: =AU!AF104 -> 0 | K85: =AU!AI104 -> 0 | L85: =AU!AL104 -> 0 | M85: =AU!AO104 -> 0 | N85: =SUM(D85:M85) -> 0 | Q85: =AU!C132 -> - | R85: =IF(AU!F132=0,"",AU!F132) | S85: =AU!N132 -> 0 | T85: =AU!Q132 -> 0 | U85: =AU!T132 -> 0 | V85: =AU!W132 -> 0 | W85: =AU!Z132 -> 0 | X85: =AU!AC132 -> 0 | Y85: =AU!AF132 -> 0 | Z85: =AU!AI132 -> 0 | AA85: =AU!AL132 -> 0 | AB85: =AU!AO132 -> 0 | AC85: =SUM(S85:AB85) -> 0
B86: =AU!C105 -> - | C86: =IF(AU!F105=0,"",AU!F105) | D86: =AU!N105 -> 0 | E86: =AU!Q105 -> 0 | F86: =AU!T105 -> 0 | G86: =AU!W105 -> 0 | H86: =AU!Z105 -> 0 | I86: =AU!AC105 -> 0 | J86: =AU!AF105 -> 0 | K86: =AU!AI105 -> 0 | L86: =AU!AL105 -> 0 | M86: =AU!AO105 -> 0 | N86: =SUM(D86:M86) -> 0 | Q86: =AU!C133 -> - | R86: =IF(AU!F133=0,"",AU!F133) | S86: =AU!N133 -> 0 | T86: =AU!Q133 -> 0 | U86: =AU!T133 -> 0 | V86: =AU!W133 -> 0 | W86: =AU!Z133 -> 0 | X86: =AU!AC133 -> 0 | Y86: =AU!AF133 -> 0 | Z86: =AU!AI133 -> 0 | AA86: =AU!AL133 -> 0 | AB86: =AU!AO133 -> 0 | AC86: =SUM(S86:AB86) -> 0
B87: =AU!C106 -> - | C87: =IF(AU!F106=0,"",AU!F106) | D87: =AU!N106 -> 0 | E87: =AU!Q106 -> 0 | F87: =AU!T106 -> 0 | G87: =AU!W106 -> 0 | H87: =AU!Z106 -> 0 | I87: =AU!AC106 -> 0 | J87: =AU!AF106 -> 0 | K87: =AU!AI106 -> 0 | L87: =AU!AL106 -> 0 | M87: =AU!AO106 -> 0 | N87: =SUM(D87:M87) -> 0 | Q87: =AU!C134 -> - | R87: =IF(AU!F134=0,"",AU!F134) | S87: =AU!N134 -> 0 | T87: =AU!Q134 -> 0 | U87: =AU!T134 -> 0 | V87: =AU!W134 -> 0 | W87: =AU!Z134 -> 0 | X87: =AU!AC134 -> 0 | Y87: =AU!AF134 -> 0 | Z87: =AU!AI134 -> 0 | AA87: =AU!AL134 -> 0 | AB87: =AU!AO134 -> 0 | AC87: =SUM(S87:AB87) -> 0
... B91: =AU!C110 -> - | C91: =IF(AU!F110=0,"",AU!F110) | D91: =AU!N110 -> 0 | E91: =AU!Q110 -> 0 | F91: =AU!T110 -> 0 | G91: =AU!W110 -> 0 | H91: =AU!Z110 -> 0 | I91: =AU!AC110 -> 0 | J91: =AU!AF110 -> 0 | K91: =AU!AI110 -> 0 | L91: =AU!AL110 -> 0 | M91: =AU!AO110 -> 0 | N91: =SUM(D91:M91) -> 0 | Q91: =AU!C138 -> - | R91: =IF(AU!F138=0,"",AU!F138) | S91: =AU!N138 -> 0 | T91: =AU!Q138 -> 0 | U91: =AU!T138 -> 0 | V91: =AU!W138 -> 0 | W91: =AU!Z138 -> 0 | X91: =AU!AC138 -> 0 | Y91: =AU!AF138 -> 0 | Z91: =AU!AI138 -> 0 | AA91: =AU!AL138 -> 0 | AB91: =AU!AO138 -> 0 | AC91: =SUM(S91:AB91) -> 0
B92: =AU!C111 -> 3. Dissemination, training, education | J92: =AU!AF111 -> 0 | K92: =AU!AI111 -> 0 | L92: =AU!AL111 -> 0 | M92: =AU!AO111 -> 0 | Q92: =B92 -> 3. Dissemination, training, education | Y92: =AU!AF139 -> 0 | Z92: =AU!AI139 -> 0 | AA92: =AU!AL139 -> 0 | AB92: =AU!AO139 -> 0
B93: =AU!C112 -> Conference participation | C93: =IF(AU!F112=0,"",AU!F112) | D93: =AU!N112 -> 15000 | E93: =AU!Q112 -> 15000 | F93: =AU!T112 -> 15000 | G93: =AU!W112 -> 15000 | H93: =AU!Z112 -> 15000 | I93: =AU!AC112 -> 5000 | J93: =AU!AF112 -> 0 | K93: =AU!AI112 -> 0 | L93: =AU!AL112 -> 0 | M93: =AU!AO112 -> 0 | N93: =SUM(D93:M93) -> 80000 | Q93: =AU!C140 -> - | R93: =IF(AU!F140=0,"",AU!F140) | S93: =AU!N140 -> 0 | T93: =AU!Q140 -> 0 | U93: =AU!T140 -> 0 | V93: =AU!W140 -> 0 | W93: =AU!Z140 -> 0 | X93: =AU!AC140 -> 0 | Y93: =AU!AF140 -> 0 | Z93: =AU!AI140 -> 0 | AA93: =AU!AL140 -> 0 | AB93: =AU!AO140 -> 0 | AC93: =SUM(S93:AB93) -> 0
B94: =AU!C113 -> Travel | C94: =IF(AU!F113=0,"",AU!F113) | D94: =AU!N113 -> 20000 | E94: =AU!Q113 -> 20000 | F94: =AU!T113 -> 20000 | G94: =AU!W113 -> 20000 | H94: =AU!Z113 -> 20000 | I94: =AU!AC113 -> 20000 | J94: =AU!AF113 -> 0 | K94: =AU!AI113 -> 0 | L94: =AU!AL113 -> 0 | M94: =AU!AO113 -> 0 | N94: =SUM(D94:M94) -> 120000 | Q94: =AU!C141 -> - | R94: =IF(AU!F141=0,"",AU!F141) | S94: =AU!N141 -> 0 | T94: =AU!Q141 -> 0 | U94: =AU!T141 -> 0 | V94: =AU!W141 -> 0 | W94: =AU!Z141 -> 0 | X94: =AU!AC141 -> 0 | Y94: =AU!AF141 -> 0 | Z94: =AU!AI141 -> 0 | AA94: =AU!AL141 -> 0 | AB94: =AU!AO141 -> 0 | AC94: =SUM(S94:AB94) -> 0
B95: =AU!C114 -> Publication costs | C95: =IF(AU!F114=0,"",AU!F114) | D95: =AU!N114 -> 0 | E95: =AU!Q114 -> 25000 | F95: =AU!T114 -> 25000 | G95: =AU!W114 -> 25000 | H95: =AU!Z114 -> 25000 | I95: =AU!AC114 -> 25000 | J95: =AU!AF114 -> 0 | K95: =AU!AI114 -> 0 | L95: =AU!AL114 -> 0 | M95: =AU!AO114 -> 0 | N95: =SUM(D95:M95) -> 125000 | Q95: =AU!C142 -> - | R95: =IF(AU!F142=0,"",AU!F142) | S95: =AU!N142 -> 0 | T95: =AU!Q142 -> 0 | U95: =AU!T142 -> 0 | V95: =AU!W142 -> 0 | W95: =AU!Z142 -> 0 | X95: =AU!AC142 -> 0 | Y95: =AU!AF142 -> 0 | Z95: =AU!AI142 -> 0 | AA95: =AU!AL142 -> 0 | AB95: =AU!AO142 -> 0 | AC95: =SUM(S95:AB95) -> 0
B96: =AU!C115 -> Travel | C96: =IF(AU!F115=0,"",AU!F115) -> PhD research stay abroad | D96: =AU!N115 -> 0 | E96: =AU!Q115 -> 0 | F96: =AU!T115 -> 30000 | G96: =AU!W115 -> 0 | H96: =AU!Z115 -> 30000 | I96: =AU!AC115 -> 0 | J96: =AU!AF115 -> 0 | K96: =AU!AI115 -> 0 | L96: =AU!AL115 -> 0 | M96: =AU!AO115 -> 0 | N96: =SUM(D96:M96) -> 60000 | Q96: =AU!C143 -> - | R96: =IF(AU!F143=0,"",AU!F143) | S96: =AU!N143 -> 0 | T96: =AU!Q143 -> 0 | U96: =AU!T143 -> 0 | V96: =AU!W143 -> 0 | W96: =AU!Z143 -> 0 | X96: =AU!AC143 -> 0 | Y96: =AU!AF143 -> 0 | Z96: =AU!AI143 -> 0 | AA96: =AU!AL143 -> 0 | AB96: =AU!AO143 -> 0 | AC96: =SUM(S96:AB96) -> 0
B97: =AU!C116 -> - | C97: =IF(AU!F116=0,"",AU!F116) | D97: =AU!N116 -> 0 | E97: =AU!Q116 -> 0 | F97: =AU!T116 -> 0 | G97: =AU!W116 -> 0 | H97: =AU!Z116 -> 0 | I97: =AU!AC116 -> 0 | J97: =AU!AF116 -> 0 | K97: =AU!AI116 -> 0 | L97: =AU!AL116 -> 0 | M97: =AU!AO116 -> 0 | N97: =SUM(D97:M97) -> 0 | Q97: =AU!C144 -> - | R97: =IF(AU!F144=0,"",AU!F144) | S97: =AU!N144 -> 0 | T97: =AU!Q144 -> 0 | U97: =AU!T144 -> 0 | V97: =AU!W144 -> 0 | W97: =AU!Z144 -> 0 | X97: =AU!AC144 -> 0 | Y97: =AU!AF144 -> 0 | Z97: =AU!AI144 -> 0 | AA97: =AU!AL144 -> 0 | AB97: =AU!AO144 -> 0 | AC97: =SUM(S97:AB97) -> 0
B98: =AU!C117 -> - | C98: =IF(AU!F117=0,"",AU!F117) | D98: =AU!N117 -> 0 | E98: =AU!Q117 -> 0 | F98: =AU!T117 -> 0 | G98: =AU!W117 -> 0 | H98: =AU!Z117 -> 0 | I98: =AU!AC117 -> 0 | J98: =AU!AF117 -> 0 | K98: =AU!AI117 -> 0 | L98: =AU!AL117 -> 0 | M98: =AU!AO117 -> 0 | N98: =SUM(D98:M98) -> 0 | Q98: =AU!C145 -> - | R98: =IF(AU!F145=0,"",AU!F145) | S98: =AU!N145 -> 0 | T98: =AU!Q145 -> 0 | U98: =AU!T145 -> 0 | V98: =AU!W145 -> 0 | W98: =AU!Z145 -> 0 | X98: =AU!AC145 -> 0 | Y98: =AU!AF145 -> 0 | Z98: =AU!AI145 -> 0 | AA98: =AU!AL145 -> 0 | AB98: =AU!AO145 -> 0 | AC98: =SUM(S98:AB98) -> 0
B99: =AU!C118 -> - | C99: =IF(AU!F118=0,"",AU!F118) | D99: =AU!N118 -> 0 | E99: =AU!Q118 -> 0 | F99: =AU!T118 -> 0 | G99: =AU!W118 -> 0 | H99: =AU!Z118 -> 0 | I99: =AU!AC118 -> 0 | J99: =AU!AF118 -> 0 | K99: =AU!AI118 -> 0 | L99: =AU!AL118 -> 0 | M99: =AU!AO118 -> 0 | N99: =SUM(D99:M99) -> 0 | Q99: =AU!C146 -> - | R99: =IF(AU!F146=0,"",AU!F146) | S99: =AU!N146 -> 0 | T99: =AU!Q146 -> 0 | U99: =AU!T146 -> 0 | V99: =AU!W146 -> 0 | W99: =AU!Z146 -> 0 | X99: =AU!AC146 -> 0 | Y99: =AU!AF146 -> 0 | Z99: =AU!AI146 -> 0 | AA99: =AU!AL146 -> 0 | AB99: =AU!AO146 -> 0 | AC99: =SUM(S99:AB99) -> 0
B100: =AU!C119 -> Tuition fee | C100: =IF(AU!F119=0,"",AU!F119) | D100: =AU!N119 -> 40000 | E100: =AU!Q119 -> 80000 | F100: =AU!T119 -> 120000 | G100: =AU!W119 -> 120000 | H100: =AU!Z119 -> 80000 | I100: =AU!AC119 -> 40000 | J100: =AU!AF119 -> 0 | K100: =AU!AI119 -> 0 | L100: =AU!AL119 -> 0 | M100: =AU!AO119 -> 0 | N100: =SUM(D100:M100) -> 480000 | Q100: =AU!C147 -> Tuition fee | R100: =IF(AU!F147=0,"",AU!F147) | S100: =AU!N147 -> 0 | T100: =AU!Q147 -> 0 | U100: =AU!T147 -> 0 | V100: =AU!W147 -> 0 | W100: =AU!Z147 -> 0 | X100: =AU!AC147 -> 0 | Y100: =AU!AF147 -> 0 | Z100: =AU!AI147 -> 0 | AA100: =AU!AL147 -> 0 | AB100: =AU!AO147 -> 0 | AC100: =SUM(S100:AB100) -> 0
B101: =AU!C120 -> Bench fee | C101: =IF(AU!J120=0,"",AU!J120) | D101: =AU!N120 -> 0 | E101: =AU!Q120 -> 0 | F101: =AU!T120 -> 0 | G101: =AU!W120 -> 0 | H101: =AU!Z120 -> 0 | I101: =AU!AC120 -> 0 | J101: =AU!AF120 -> 0 | K101: =AU!AI120 -> 0 | L101: =AU!AL120 -> 0 | M101: =AU!AO120 -> 0 | N101: =SUM(D101:M101) -> 0 | Q101: =AU!C148 -> Bench fee | R101: =IF(AU!F148=0,"",AU!F148) | S101: =AU!N148 -> 0 | T101: =AU!Q148 -> 0 | U101: =AU!T148 -> 0 | V101: =AU!W148 -> 0 | W101: =AU!Z148 -> 0 | X101: =AU!AC148 -> 0 | Y101: =AU!AF148 -> 0 | Z101: =AU!AI148 -> 0 | AA101: =AU!AL148 -> 0 | AB101: =AU!AO148 -> 0 | AC101: =SUM(S101:AB101) -> 0
B102: Total | D102: =SUM(D76:D101) -> 275000 | E102: =SUM(E76:E101) -> 340000 | F102: =SUM(F76:F101) -> 410000 | G102: =SUM(G76:G101) -> 240000 | H102: =SUM(H76:H101) -> 320000 | I102: =SUM(I76:I101) -> 230000 | J102: =SUM(J76:J101) -> 0 | K102: =SUM(K76:K101) -> 0 | ... N102: =SUM(N76:N101) -> 1815000 | Q102: Total | S102: =SUM(S76:S101) -> 0 | T102: =SUM(T76:T101) -> 0 | U102: =SUM(U76:U101) -> 0 | V102: =SUM(V76:V101) -> 0 | W102: =SUM(W76:W101) -> 0 | X102: =SUM(X76:X101) -> 0 | Y102: =SUM(Y98:Y100) -> 0 | Z102: =SUM(Z98:Z100) -> 0 | AA102: =SUM(AA98:AA100) -> 0 | AB102: =SUM(AB98:AB100) -> 0 | AC102: =SUM(AC76:AC101) -> 0
B104: ="Total "&AU!B152 -> Total Applied for from the foundation | D104: =AU!L15 -> Year 1 | E104: =AU!O15 -> Year 2 | F104: =AU!R15 -> Year 3 | G104: =AU!U15 -> Year 4 | H104: =AU!X15 -> Year 5 | I104: =AU!AA15 -> Year 6 | J104: =AU!AD15 -> Year 7 | K104: =AU!AG15 -> Year 8 | L104: =AU!AJ15 -> Year 9 | M104: =AU!AM15 -> Year 10 | N104: Total
B105: =AU!C153 -> Direct costs (salary + project costs) | D105: =AU!N153 -> 1204348.4 | E105: =AU!Q153 -> 2254457.7 | F105: =AU!T153 -> 3016678.4 | G105: =AU!W153 -> 2563185.2 | H105: =AU!Z153 -> 1666891 | I105: =AU!AC153 -> 923648.86 | J105: =AU!AF153 -> 0 | K105: =AU!AI153 -> 0 | L105: =AU!AL153 -> 0 | M105: =AU!AO153 -> 0 | N105: =SUM(D105:M105) -> 11629210 | Q105: ="Total "&AU!B159 -> Total Co-financing | S105: =AU!L15 -> Year 1 | T105: =AU!O15 -> Year 2 | U105: =AU!R15 -> Year 3 | V105: =AU!U15 -> Year 4 | W105: =AU!X15 -> Year 5 | X105: =AU!AA15 -> Year 6 | Y105: =AU!AD15 -> Year 7 | Z105: =AU!AG15 -> Year 8 | AA105: =AU!AJ15 -> Year 9 | AB105: =AU!AM15 -> Year 10 | AC105: Total
B106: =AU!C155 -> Project supplement | C106: =IFERROR(ROUND(AU!$AQ$155*100,0)&"% (of "&IF(AU!F180="Total","direct costs+proj.suppl.)","direct costs)"),"") -> 24% (of direct costs+proj.suppl.) | D106: =AU!N155 -> 375000 | E106: =AU!Q155 -> 750000 | F106: =AU!T155 -> 1000000 | G106: =AU!W155 -> 875000 | H106: =AU!Z155 -> 500000 | I106: =AU!AC155 -> 250000 | J106: =AU!AF155 -> 0 | K106: =AU!AI155 -> 0 | L106: =AU!AL155 -> 0 | M106: =AU!AO155 -> 0 | N106: =SUM(D106:M106) -> 3750000 | Q106: =AU!C153 -> Direct costs (salary + project costs) | S106: =SUM(AU!N160:N162) -> 0 | T106: =SUM(AU!Q160:Q162) -> 0 | U106: =SUM(AU!T160:T162) -> 0 | V106: =SUM(AU!W160:W162) -> 0 | W106: =SUM(AU!Z160:Z162) -> 0 | X106: =SUM(AU!AC160:AC162) -> 0 | Y106: =SUM(AU!AF160:AF162) -> 0 | Z106: =SUM(AU!AI160:AI162) -> 0 | AA106: =SUM(AU!AL160:AL162) -> 0 | AB106: =SUM(AU!AO160:AO162) -> 0 | AC106: =SUM(S106:AB106) -> 0
B107: =AU!C156 -> Administrative expenses | C107: =OHPctPartner1 -> 0 | D107: =AU!N156 -> 0 | E107: =AU!Q156 -> 0 | F107: =AU!T156 -> 0 | G107: =AU!W156 -> 0 | H107: =AU!Z156 -> 0 | I107: =AU!AC156 -> 0 | J107: =AU!AF156 -> 0 | K107: =AU!AI156 -> 0 | L107: =AU!AL156 -> 0 | M107: =AU!AO156 -> 0 | N107: =SUM(D107:M107) -> 0 | Q107: =AU!C156 -> Administrative expenses | R107: =OHPctCoFinancePartner1 -> 0 | S107: =AU!N163 -> 0 | T107: =AU!Q163 -> 0 | U107: =AU!T163 -> 0 | V107: =AU!W163 -> 0 | W107: =AU!Z163 -> 0 | X107: =AU!AC163 -> 0 | Y107: =AU!AF163 -> 0 | Z107: =AU!AI163 -> 0 | AA107: =AU!AL163 -> 0 | AB107: =AU!AO163 -> 0 | AC107: =SUM(S107:AB107) -> 0
B108: Total | D108: =SUM(D105:D107) -> 1579348.4 | E108: =SUM(E105:E107) -> 3004457.7 | F108: =SUM(F105:F107) -> 4016678.4 | G108: =SUM(G105:G107) -> 3438185.2 | H108: =SUM(H105:H107) -> 2166891 | I108: =SUM(I105:I107) -> 1173648.9 | J108: =SUM(J105:J107) -> 0 | K108: =SUM(K105:K107) -> 0 | ... N108: =SUM(N105:N107) -> 15379210 | Q108: Total | R108: {=IFERROR(ROUND(SUM((AC106:AC107)/N111)*100,0) &"% (of total costs)","")} -> 0% (of total costs) | S108: =SUM(S106:S107) -> 0 | T108: =SUM(T106:T107) -> 0 | U108: =SUM(U106:U107) -> 0 | V108: =SUM(V106:V107) -> 0 | W108: =SUM(W106:W107) -> 0 | X108: =SUM(X106:X107) -> 0 | Y108: =SUM(Y106:Y107) -> 0 | Z108: =SUM(Z106:Z107) -> 0 | ... AC108: =SUM(AC106:AC107) -> 0
B110: =AU!B166 -> Total costs (Applied for+co-financing) | D110: =AU!L15 -> Year 1 | E110: =AU!O15 -> Year 2 | F110: =AU!R15 -> Year 3 | G110: =AU!U15 -> Year 4 | H110: =AU!X15 -> Year 5 | I110: =AU!AA15 -> Year 6 | J110: =AU!AD15 -> Year 7 | K110: =AU!AG15 -> Year 8 | L110: =AU!AJ15 -> Year 9 | M110: =AU!AM15 -> Year 10 | N110: Total | Q110: Purchase of departmental services | S110: =AU!L15 -> Year 1 | T110: =AU!O15 -> Year 2 | U110: =AU!R15 -> Year 3 | V110: =AU!U15 -> Year 4 | W110: =AU!X15 -> Year 5 | X110: =AU!AA15 -> Year 6 | Y110: =AU!AD15 -> Year 7 | Z110: =AU!AG15 -> Year 8 | AA110: =AU!AJ15 -> Year 9 | AB110: =AU!AM15 -> Year 10 | AC110: Total
D111: =D108+S108 -> 1579348.4 | E111: =E108+T108 -> 3004457.7 | F111: =F108+U108 -> 4016678.4 | G111: =G108+V108 -> 3438185.2 | H111: =H108+W108 -> 2166891 | I111: =I108+X108 -> 1173648.9 | J111: =J108+Y108 -> 0 | K111: =K108+Z108 -> 0 | ... M111: =M108+AB108 -> 0 | N111: =SUM(D111:M111) -> 15379210 | Q111: =ROUND(AU!$AQ$154*100,0)&"% (of "&IF(AU!F177="Total","direct costs+proj.suppl.","direct costs")&IF(AU!F174="Yes"," excl. equipment","")&")" -> 0% (of direct costs+proj.suppl. excl. equipment) | S111: =AU!L154 -> 0 | T111: =AU!O154 -> 0 | U111: =AU!R154 -> 0 | V111: =AU!U154 -> 0 | W111: =AU!X154 -> 0 | X111: =AU!AA154 -> 0 | Y111: =AU!AD154 -> 0 | Z111: =AU!AG154 -> 0 | AA111: =AU!AJ154 -> 0 | AB111: =AU!AM154 -> 0 | AC111: =AU!AP154 -> 0

Sheet For NORMA
B2: ="Project title: " & IF(AU!D15=0, "",AU!D15) -> Project title: | D2: =AU!L15 -> Year 1 | F2: =AU!O15 -> Year 2 | H2: =AU!R15 -> Year 3 | J2: =AU!U15 -> Year 4 | L2: =AU!X15 -> Year 5 | N2: =AU!AA15 -> Year 6 | P2: =AU!AD15 -> Year 7 | R2: =AU!AG15 -> Year 8 | T2: =AU!AJ15 -> Year 9 | V2: =AU!AM15 -> Year 10
A3: 1. | B3: Salary | C3: Notes/name | D3: Budget | E3: FTE | F3: Budget | G3: FTE | H3: Budget | I3: FTE | J3: Budget | K3: FTE | L3: Budget | M3: FTE | N3: Budget | O3: FTE | P3: Budget | Q3: FTE | R3: Budget | S3: FTE | T3: Budget | U3: FTE | V3: Budget | W3: FTE
B4: VIP
B5: =AU!C20 -> Postdoc | C5: =IF(AU!F20="","",AU!F20) | D5: =AU!N20 -> 662001.6 | E5: =AU!M20 -> 1 | F5: =AU!Q20 -> 681861.65 | G5: =AU!P20 -> 1 | H5: =AU!T20 -> 702317.5 | I5: =AU!S20 -> 1 | J5: =AU!W20 -> 0 | K5: =AU!V20 -> 0 | L5: =AU!Z20 -> 0 | M5: =AU!Y20 -> 0 | N5: =AU!AC20 -> 0 | O5: =AU!AB20 -> 0 | P5: =AU!AF20 -> 0 | Q5: =AU!AE20 -> 0 | R5: =AU!AI20 -> 0 | S5: =AU!AH20 -> 0 | T5: =AU!AL20 -> 0 | U5: =AU!AK20 -> 0 | V5: =AU!AO20 -> 0 | W5: =AU!AN20 -> 0
B6: =AU!C21 -> Postdoc | C6: =IF(AU!F21="","",AU!F21) | D6: =AU!N21 -> 0 | E6: =AU!M21 -> 0 | F6: =AU!Q21 -> 681861.65 | G6: =AU!P21 -> 1 | H6: =AU!T21 -> 702317.5 | I6: =AU!S21 -> 1 | J6: =AU!W21 -> 723387.02 | K6: =AU!V21 -> 1 | L6: =AU!Z21 -> 0 | M6: =AU!Y21 -> 0 | N6: =AU!AC21 -> 0 | O6: =AU!AB21 -> 0 | P6: =AU!AF21 -> 0 | Q6: =AU!AE21 -> 0 | R6: =AU!AI21 -> 0 | S6: =AU!AH21 -> 0 | T6: =AU!AL21 -> 0 | U6: =AU!AK21 -> 0 | V6: =AU!AO21 -> 0 | W6: =AU!AN21 -> 0
B7: =AU!C22 -> Postdoc | C7: =IF(AU!F22="","",AU!F22) | D7: =AU!N22 -> 0 | E7: =AU!M22 -> 0 | F7: =AU!Q22 -> 0 | G7: =AU!P22 -> 0 | H7: =AU!T22 -> 351158.75 | I7: =AU!S22 -> 0.5 | J7: =AU!W22 -> 723387.02 | K7: =AU!V22 -> 1 | L7: =AU!Z22 -> 745088.63 | M7: =AU!Y22 -> 1 | N7: =AU!AC22 -> 383720.65 | O7: =AU!AB22 -> 0.5 | P7: =AU!AF22 -> 0 | Q7: =AU!AE22 -> 0 | R7: =AU!AI22 -> 0 | S7: =AU!AH22 -> 0 | T7: =AU!AL22 -> 0 | U7: =AU!AK22 -> 0 | V7: =AU!AO22 -> 0 | W7: =AU!AN22 -> 0
B8: =AU!C23 -> PhD Student | C8: =IF(AU!F23="","",AU!F23) | D8: =AU!N23 -> 267346.8 | E8: =AU!M23 -> 0.5 | F8: =AU!Q23 -> 550734.41 | G8: =AU!P23 -> 1 | H8: =AU!T23 -> 567256.44 | I8: =AU!S23 -> 1 | J8: =AU!W23 -> 292137.07 | K8: =AU!V23 -> 0.5 | L8: =AU!Z23 -> 0 | M8: =AU!Y23 -> 0 | N8: =AU!AC23 -> 0 | O8: =AU!AB23 -> 0 | P8: =AU!AF23 -> 0 | Q8: =AU!AE23 -> 0 | R8: =AU!AI23 -> 0 | S8: =AU!AH23 -> 0 | T8: =AU!AL23 -> 0 | U8: =AU!AK23 -> 0 | V8: =AU!AO23 -> 0 | W8: =AU!AN23 -> 0
B9: =AU!C24 -> PhD Student | C9: =IF(AU!F24="","",AU!F24) | D9: =AU!N24 -> 0 | E9: =AU!M24 -> 0 | F9: =AU!Q24 -> 0 | G9: =AU!P24 -> 0 | H9: =AU!T24 -> 283628.22 | I9: =AU!S24 -> 0.5 | J9: =AU!W24 -> 584274.13 | K9: =AU!V24 -> 1 | L9: =AU!Z24 -> 601802.36 | M9: =AU!Y24 -> 1 | N9: =AU!AC24 -> 309928.21 | O9: =AU!AB24 -> 0.5 | P9: =AU!AF24 -> 0 | Q9: =AU!AE24 -> 0 | R9: =AU!AI24 -> 0 | S9: =AU!AH24 -> 0 | T9: =AU!AL24 -> 0 | U9: =AU!AK24 -> 0 | V9: =AU!AO24 -> 0 | W9: =AU!AN24 -> 0
B10: =AU!C25 -> - | C10: =IF(AU!F25="","",AU!F25) | D10: =AU!N25 | E10: =AU!M25 -> 0 | F10: =AU!Q25 | G10: =AU!P25 -> 0 | H10: =AU!T25 | I10: =AU!S25 -> 0 | J10: =AU!W25 | K10: =AU!V25 -> 0 | L10: =AU!Z25 | M10: =AU!Y25 -> 0 | N10: =AU!AC25 | O10: =AU!AB25 -> 0 | P10: =AU!AF25 | Q10: =AU!AE25 -> 0 | R10: =AU!AI25 | S10: =AU!AH25 -> 0 | T10: =AU!AL25 | U10: =AU!AK25 -> 0 | V10: =AU!AO25 | W10: =AU!AN25 -> 0
B11: =AU!C26 -> - | C11: =IF(AU!F26="","",AU!F26) | D11: =AU!N26 | E11: =AU!M26 -> 0 | F11: =AU!Q26 | G11: =AU!P26 -> 0 | H11: =AU!T26 | I11: =AU!S26 -> 0 | J11: =AU!W26 | K11: =AU!V26 -> 0 | L11: =AU!Z26 | M11: =AU!Y26 -> 0 | N11: =AU!AC26 | O11: =AU!AB26 -> 0 | P11: =AU!AF26 | Q11: =AU!AE26 -> 0 | R11: =AU!AI26 | S11: =AU!AH26 -> 0 | T11: =AU!AL26 | U11: =AU!AK26 -> 0 | V11: =AU!AO26 | W11: =AU!AN26 -> 0
B12: =AU!C27 -> - | C12: =IF(AU!F27="","",AU!F27) | D12: =AU!N27 | E12: =AU!M27 -> 0 | F12: =AU!Q27 | G12: =AU!P27 -> 0 | H12: =AU!T27 | I12: =AU!S27 -> 0 | J12: =AU!W27 | K12: =AU!V27 -> 0 | L12: =AU!Z27 | M12: =AU!Y27 -> 0 | N12: =AU!AC27 | O12: =AU!AB27 -> 0 | P12: =AU!AF27 | Q12: =AU!AE27 -> 0 | R12: =AU!AI27 | S12: =AU!AH27 -> 0 | T12: =AU!AL27 | U12: =AU!AK27 -> 0 | V12: =AU!AO27 | W12: =AU!AN27 -> 0
B13: =AU!C28 -> - | C13: =IF(AU!F28="","",AU!F28) | D13: =AU!N28 | E13: =AU!M28 -> 0 | F13: =AU!Q28 | G13: =AU!P28 -> 0 | H13: =AU!T28 | I13: =AU!S28 -> 0 | J13: =AU!W28 | K13: =AU!V28 -> 0 | L13: =AU!Z28 | M13: =AU!Y28 -> 0 | N13: =AU!AC28 | O13: =AU!AB28 -> 0 | P13: =AU!AF28 | Q13: =AU!AE28 -> 0 | R13: =AU!AI28 | S13: =AU!AH28 -> 0 | T13: =AU!AL28 | U13: =AU!AK28 -> 0 | V13: =AU!AO28 | W13: =AU!AN28 -> 0
B14: =AU!C29 -> - | C14: =IF(AU!F29="","",AU!F29) | D14: =AU!N29 | E14: =AU!M29 -> 0 | F14: =AU!Q29 | G14: =AU!P29 -> 0 | H14: =AU!T29 | I14: =AU!S29 -> 0 | J14: =AU!W29 | K14: =AU!V29 -> 0 | L14: =AU!Z29 | M14: =AU!Y29 -> 0 | N14: =AU!AC29 | O14: =AU!AB29 -> 0 | P14: =AU!AF29 | Q14: =AU!AE29 -> 0 | R14: =AU!AI29 | S14: =AU!AH29 -> 0 | T14: =AU!AL29 | U14: =AU!AK29 -> 0 | V14: =AU!AO29 | W14: =AU!AN29 -> 0
B15: =AU!C30 -> - | C15: =IF(AU!F30="","",AU!F30) | D15: =AU!N30 | E15: =AU!M30 -> 0 | F15: =AU!Q30 | G15: =AU!P30 -> 0 | H15: =AU!T30 | I15: =AU!S30 -> 0 | J15: =AU!W30 | K15: =AU!V30 -> 0 | L15: =AU!Z30 | M15: =AU!Y30 -> 0 | N15: =AU!AC30 | O15: =AU!AB30 -> 0 | P15: =AU!AF30 | Q15: =AU!AE30 -> 0 | R15: =AU!AI30 | S15: =AU!AH30 -> 0 | T15: =AU!AL30 | U15: =AU!AK30 -> 0 | V15: =AU!AO30 | W15: =AU!AN30 -> 0
B16: =AU!C31 -> - | C16: =IF(AU!F31="","",AU!F31) | D16: =AU!N31 | E16: =AU!M31 -> 0 | F16: =AU!Q31 | G16: =AU!P31 -> 0 | H16: =AU!T31 | I16: =AU!S31 -> 0 | J16: =AU!W31 | K16: =AU!V31 -> 0 | L16: =AU!Z31 | M16: =AU!Y31 -> 0 | N16: =AU!AC31 | O16: =AU!AB31 -> 0 | P16: =AU!AF31 | Q16: =AU!AE31 -> 0 | R16: =AU!AI31 | S16: =AU!AH31 -> 0 | T16: =AU!AL31 | U16: =AU!AK31 -> 0 | V16: =AU!AO31 | W16: =AU!AN31 -> 0
... B20: =AU!C35 -> - | C20: =IF(AU!F35="","",AU!F35) | D20: =AU!N35 | E20: =AU!M35 -> 0 | F20: =AU!Q35 | G20: =AU!P35 -> 0 | H20: =AU!T35 | I20: =AU!S35 -> 0 | J20: =AU!W35 | K20: =AU!V35 -> 0 | L20: =AU!Z35 | M20: =AU!Y35 -> 0 | N20: =AU!AC35 | O20: =AU!AB35 -> 0 | P20: =AU!AF35 | Q20: =AU!AE35 -> 0 | R20: =AU!AI35 | S20: =AU!AH35 -> 0 | T20: =AU!AL35 | U20: =AU!AK35 -> 0 | V20: =AU!AO35 | W20: =AU!AN35 -> 0
B21: TAP | C21: =IF(AU!F35="","",AU!F35)
B22: =AU!C56 -> AC staff et al. | C22: =IF(AU!F56="","",AU!F56) | D22: =AU!N56 -> 0 | E22: =AU!M56 -> 0 | F22: =AU!Q56 -> 0 | G22: =AU!P56 -> 0 | H22: =AU!T56 -> 0 | I22: =AU!S56 -> 0 | J22: =AU!W56 -> 0 | K22: =AU!V56 -> 0 | L22: =AU!Z56 -> 0 | M22: =AU!Y56 -> 0 | N22: =AU!AC56 -> 0 | O22: =AU!AB56 -> 0 | P22: =AU!AF56 -> 0 | Q22: =AU!AE56 -> 0 | R22: =AU!AI56 -> 0 | S22: =AU!AH56 -> 0 | T22: =AU!AL56 -> 0 | U22: =AU!AK56 -> 0 | V22: =AU!AO56 -> 0 | W22: =AU!AN56 -> 0
B23: =AU!C57 -> - | C23: =IF(AU!F57="","",AU!F57) | D23: =AU!N57 | E23: =AU!M57 -> 0 | F23: =AU!Q57 | G23: =AU!P57 -> 0 | H23: =AU!T57 | I23: =AU!S57 -> 0 | J23: =AU!W57 | K23: =AU!V57 -> 0 | L23: =AU!Z57 | M23: =AU!Y57 -> 0 | N23: =AU!AC57 | O23: =AU!AB57 -> 0 | P23: =AU!AF57 | Q23: =AU!AE57 -> 0 | R23: =AU!AI57 | S23: =AU!AH57 -> 0 | T23: =AU!AL57 | U23: =AU!AK57 -> 0 | V23: =AU!AO57 | W23: =AU!AN57 -> 0
B24: =AU!C58 -> - | C24: =IF(AU!F58="","",AU!F58) | D24: =AU!N58 | E24: =AU!M58 -> 0 | F24: =AU!Q58 | G24: =AU!P58 -> 0 | H24: =AU!T58 | I24: =AU!S58 -> 0 | J24: =AU!W58 | K24: =AU!V58 -> 0 | L24: =AU!Z58 | M24: =AU!Y58 -> 0 | N24: =AU!AC58 | O24: =AU!AB58 -> 0 | P24: =AU!AF58 | Q24: =AU!AE58 -> 0 | R24: =AU!AI58 | S24: =AU!AH58 -> 0 | T24: =AU!AL58 | U24: =AU!AK58 -> 0 | V24: =AU!AO58 | W24: =AU!AN58 -> 0
B25: =AU!C59 -> - | C25: =IF(AU!F59="","",AU!F59) | D25: =AU!N59 | E25: =AU!M59 -> 0 | F25: =AU!Q59 | G25: =AU!P59 -> 0 | H25: =AU!T59 | I25: =AU!S59 -> 0 | J25: =AU!W59 | K25: =AU!V59 -> 0 | L25: =AU!Z59 | M25: =AU!Y59 -> 0 | N25: =AU!AC59 | O25: =AU!AB59 -> 0 | P25: =AU!AF59 | Q25: =AU!AE59 -> 0 | R25: =AU!AI59 | S25: =AU!AH59 -> 0 | T25: =AU!AL59 | U25: =AU!AK59 -> 0 | V25: =AU!AO59 | W25: =AU!AN59 -> 0
B26: =AU!C60 -> - | C26: =IF(AU!F60="","",AU!F60) | D26: =AU!N60 | E26: =AU!M60 -> 0 | F26: =AU!Q60 | G26: =AU!P60 -> 0 | H26: =AU!T60 | I26: =AU!S60 -> 0 | J26: =AU!W60 | K26: =AU!V60 -> 0 | L26: =AU!Z60 | M26: =AU!Y60 -> 0 | N26: =AU!AC60 | O26: =AU!AB60 -> 0 | P26: =AU!AF60 | Q26: =AU!AE60 -> 0 | R26: =AU!AI60 | S26: =AU!AH60 -> 0 | T26: =AU!AL60 | U26: =AU!AK60 -> 0 | V26: =AU!AO60 | W26: =AU!AN60 -> 0
B27: =AU!C61 -> - | C27: =IF(AU!F61="","",AU!F61) | D27: =AU!N61 | E27: =AU!M61 -> 0 | F27: =AU!Q61 | G27: =AU!P61 -> 0 | H27: =AU!T61 | I27: =AU!S61 -> 0 | J27: =AU!W61 | K27: =AU!V61 -> 0 | L27: =AU!Z61 | M27: =AU!Y61 -> 0 | N27: =AU!AC61 | O27: =AU!AB61 -> 0 | P27: =AU!AF61 | Q27: =AU!AE61 -> 0 | R27: =AU!AI61 | S27: =AU!AH61 -> 0 | T27: =AU!AL61 | U27: =AU!AK61 -> 0 | V27: =AU!AO61 | W27: =AU!AN61 -> 0
B28: =AU!C62 -> - | C28: =IF(AU!F62="","",AU!F62) | D28: =AU!N62 | E28: =AU!M62 -> 0 | F28: =AU!Q62 | G28: =AU!P62 -> 0 | H28: =AU!T62 | I28: =AU!S62 -> 0 | J28: =AU!W62 | K28: =AU!V62 -> 0 | L28: =AU!Z62 | M28: =AU!Y62 -> 0 | N28: =AU!AC62 | O28: =AU!AB62 -> 0 | P28: =AU!AF62 | Q28: =AU!AE62 -> 0 | R28: =AU!AI62 | S28: =AU!AH62 -> 0 | T28: =AU!AL62 | U28: =AU!AK62 -> 0 | V28: =AU!AO62 | W28: =AU!AN62 -> 0
B29: =AU!C63 -> - | C29: =IF(AU!F63="","",AU!F63) | D29: =AU!N63 | E29: =AU!M63 -> 0 | F29: =AU!Q63 | G29: =AU!P63 -> 0 | H29: =AU!T63 | I29: =AU!S63 -> 0 | J29: =AU!W63 | K29: =AU!V63 -> 0 | L29: =AU!Z63 | M29: =AU!Y63 -> 0 | N29: =AU!AC63 | O29: =AU!AB63 -> 0 | P29: =AU!AF63 | Q29: =AU!AE63 -> 0 | R29: =AU!AI63 | S29: =AU!AH63 -> 0 | T29: =AU!AL63 | U29: =AU!AK63 -> 0 | V29: =AU!AO63 | W29: =AU!AN63 -> 0
B30: =AU!C64 -> - | C30: =IF(AU!F64="","",AU!F64) | D30: =AU!N64 | E30: =AU!M64 -> 0 | F30: =AU!Q64 | G30: =AU!P64 -> 0 | H30: =AU!T64 | I30: =AU!S64 -> 0 | J30: =AU!W64 | K30: =AU!V64 -> 0 | L30: =AU!Z64 | M30: =AU!Y64 -> 0 | N30: =AU!AC64 | O30: =AU!AB64 -> 0 | P30: =AU!AF64 | Q30: =AU!AE64 -> 0 | R30: =AU!AI64 | S30: =AU!AH64 -> 0 | T30: =AU!AL64 | U30: =AU!AK64 -> 0 | V30: =AU!AO64 | W30: =AU!AN64 -> 0
B31: =AU!C65 -> - | C31: =IF(AU!F65="","",AU!F65) | D31: =AU!N65 | E31: =AU!M65 -> 0 | F31: =AU!Q65 | G31: =AU!P65 -> 0 | H31: =AU!T65 | I31: =AU!S65 -> 0 | J31: =AU!W65 | K31: =AU!V65 -> 0 | L31: =AU!Z65 | M31: =AU!Y65 -> 0 | N31: =AU!AC65 | O31: =AU!AB65 -> 0 | P31: =AU!AF65 | Q31: =AU!AE65 -> 0 | R31: =AU!AI65 | S31: =AU!AH65 -> 0 | T31: =AU!AL65 | U31: =AU!AK65 -> 0 | V31: =AU!AO65 | W31: =AU!AN65 -> 0
B32: =AU!C66 -> - | C32: =IF(AU!F66="","",AU!F66) | D32: =AU!N66 | E32: =AU!M66 -> 0 | F32: =AU!Q66 | G32: =AU!P66 -> 0 | H32: =AU!T66 | I32: =AU!S66 -> 0 | J32: =AU!W66 | K32: =AU!V66 -> 0 | L32: =AU!Z66 | M32: =AU!Y66 -> 0 | N32: =AU!AC66 | O32: =AU!AB66 -> 0 | P32: =AU!AF66 | Q32: =AU!AE66 -> 0 | R32: =AU!AI66 | S32: =AU!AH66 -> 0 | T32: =AU!AL66 | U32: =AU!AK66 -> 0 | V32: =AU!AO66 | W32: =AU!AN66 -> 0
B33: =AU!C67 -> - | C33: =IF(AU!F67="","",AU!F67) | D33: =AU!N67 | E33: =AU!M67 -> 0 | F33: =AU!Q67 | G33: =AU!P67 -> 0 | H33: =AU!T67 | I33: =AU!S67 -> 0 | J33: =AU!W67 | K33: =AU!V67 -> 0 | L33: =AU!Z67 | M33: =AU!Y67 -> 0 | N33: =AU!AC67 | O33: =AU!AB67 -> 0 | P33: =AU!AF67 | Q33: =AU!AE67 -> 0 | R33: =AU!AI67 | S33: =AU!AH67 -> 0 | T33: =AU!AL67 | U33: =AU!AK67 -> 0 | V33: =AU!AO67 | W33: =AU!AN67 -> 0
... B36: =AU!C70 -> - | C36: =IF(AU!F70="","",AU!F70) | D36: =AU!N70 | E36: =AU!M70 -> 0 | F36: =AU!Q70 | G36: =AU!P70 -> 0 | H36: =AU!T70 | I36: =AU!S70 -> 0 | J36: =AU!W70 | K36: =AU!V70 -> 0 | L36: =AU!Z70 | M36: =AU!Y70 -> 0 | N36: =AU!AC70 | O36: =AU!AB70 -> 0 | P36: =AU!AF70 | Q36: =AU!AE70 -> 0 | R36: =AU!AI70 | S36: =AU!AH70 -> 0 | T36: =AU!AL70 | U36: =AU!AK70 -> 0 | V36: =AU!AO70 | W36: =AU!AN70 -> 0
B37: =AU!C71 -> - | C37: =IF(AU!F71="","",AU!F71) | D37: =AU!N71 | E37: =AU!M71 -> 0 | F37: =AU!Q71 | G37: =AU!P71 -> 0 | H37: =AU!T71 | I37: =AU!S71 -> 0 | J37: =AU!W71 | K37: =AU!V71 -> 0 | L37: =AU!Z71 | M37: =AU!Y71 -> 0 | N37: =AU!AC57 | O37: =AU!AB57 -> 0 | P37: =AU!AF57 | Q37: =AU!AE57 -> 0 | R37: =AU!AI57 | S37: =AU!AH57 -> 0 | T37: =AU!AL57 | U37: =AU!AK57 -> 0 | V37: =AU!AO57 | W37: =AU!AN57 -> 0
A38: 2. | B38: Operation | C38: Notes
B39: =AU!C95 -> Equipment | C39: =IF(AU!F95="","",AU!F95) -> High-performance computers | D39: =AU!N95 -> 50000 | F39: =AU!Q95 -> 50000 | H39: =AU!T95 -> 50000 | J39: =AU!W95 -> 0 | L39: =AU!Z95 -> 0 | N39: =AU!AC95 -> 0 | P39: =AU!AF95 -> 0 | R39: =AU!AI95 -> 0 | T39: =AU!AL95 -> 0 | V39: =AU!AO95 -> 0
B40: =AU!C96 -> Data management | C40: =IF(AU!F96="","",AU!F96) -> Cluster time | D40: =AU!N96 -> 50000 | F40: =AU!Q96 -> 50000 | H40: =AU!T96 -> 50000 | J40: =AU!W96 -> 50000 | L40: =AU!Z96 -> 50000 | N40: =AU!AC96 -> 50000 | P40: =AU!AF96 -> 0 | R40: =AU!AI96 -> 0 | T40: =AU!AL96 -> 0 | V40: =AU!AO96 -> 0
B41: =AU!C97 -> Operating expenses | C41: =IF(AU!F97="","",AU!F97) -> Data storage | D41: =AU!N97 -> 100000 | F41: =AU!Q97 -> 100000 | H41: =AU!T97 -> 100000 | J41: =AU!W97 -> 10000 | L41: =AU!Z97 -> 100000 | N41: =AU!AC97 -> 90000 | P41: =AU!AF97 -> 0 | R41: =AU!AI97 -> 0 | T41: =AU!AL97 -> 0 | V41: =AU!AO97 -> 0
B42: =AU!C98 -> - | C42: =IF(AU!F98="","",AU!F98) | D42: =AU!N98 -> 0 | F42: =AU!Q98 -> 0 | H42: =AU!T98 -> 0 | J42: =AU!W98 -> 0 | L42: =AU!Z98 -> 0 | N42: =AU!AC98 -> 0 | P42: =AU!AF98 -> 0 | R42: =AU!AI98 -> 0 | T42: =AU!AL98 -> 0 | V42: =AU!AO98 -> 0
B43: =AU!C99 -> - | C43: =IF(AU!F99="","",AU!F99) | D43: =AU!N99 -> 0 | F43: =AU!Q99 -> 0 | H43: =AU!T99 -> 0 | J43: =AU!W99 -> 0 | L43: =AU!Z99 -> 0 | N43: =AU!AC99 -> 0 | P43: =AU!AF99 -> 0 | R43: =AU!AI99 -> 0 | T43: =AU!AL99 -> 0 | V43: =AU!AO99 -> 0
B44: =AU!C100 -> - | C44: =IF(AU!F100="","",AU!F100) | D44: =AU!N100 -> 0 | F44: =AU!Q100 -> 0 | H44: =AU!T100 -> 0 | J44: =AU!W100 -> 0 | L44: =AU!Z100 -> 0 | N44: =AU!AC100 -> 0 | P44: =AU!AF100 -> 0 | R44: =AU!AI100 -> 0 | T44: =AU!AL100 -> 0 | V44: =AU!AO100 -> 0
B45: =AU!C101 -> - | C45: =IF(AU!F101="","",AU!F101) | D45: =AU!N101 -> 0 | F45: =AU!Q101 -> 0 | H45: =AU!T101 -> 0 | J45: =AU!W101 -> 0 | L45: =AU!Z101 -> 0 | N45: =AU!AC101 -> 0 | P45: =AU!AF101 -> 0 | R45: =AU!AI101 -> 0 | T45: =AU!AL101 -> 0 | V45: =AU!AO101 -> 0
B46: =AU!C102 -> - | C46: =IF(AU!F102="","",AU!F102) | D46: =AU!N102 -> 0 | F46: =AU!Q102 -> 0 | H46: =AU!T102 -> 0 | J46: =AU!W102 -> 0 | L46: =AU!Z102 -> 0 | N46: =AU!AC102 -> 0 | P46: =AU!AF102 -> 0 | R46: =AU!AI102 -> 0 | T46: =AU!AL102 -> 0 | V46: =AU!AO102 -> 0
B47: =AU!C103 -> - | C47: =IF(AU!F103="","",AU!F103) | D47: =AU!N103 -> 0 | F47: =AU!Q103 -> 0 | H47: =AU!T103 -> 0 | J47: =AU!W103 -> 0 | L47: =AU!Z103 -> 0 | N47: =AU!AC103 -> 0 | P47: =AU!AF103 -> 0 | R47: =AU!AI103 -> 0 | T47: =AU!AL103 -> 0 | V47: =AU!AO103 -> 0
B48: =AU!C104 -> - | C48: =IF(AU!F104="","",AU!F104) | D48: =AU!N104 -> 0 | F48: =AU!Q104 -> 0 | H48: =AU!T104 -> 0 | J48: =AU!W104 -> 0 | L48: =AU!Z104 -> 0 | N48: =AU!AC104 -> 0 | P48: =AU!AF104 -> 0 | R48: =AU!AI104 -> 0 | T48: =AU!AL104 -> 0 | V48: =AU!AO104 -> 0
B49: =AU!C105 -> - | C49: =IF(AU!F105="","",AU!F105) | D49: =AU!N105 -> 0 | F49: =AU!Q105 -> 0 | H49: =AU!T105 -> 0 | J49: =AU!W105 -> 0 | L49: =AU!Z105 -> 0 | N49: =AU!AC105 -> 0 | P49: =AU!AF105 -> 0 | R49: =AU!AI105 -> 0 | T49: =AU!AL105 -> 0 | V49: =AU!AO105 -> 0
B50: =AU!C106 -> - | C50: =IF(AU!F106="","",AU!F106) | D50: =AU!N106 -> 0 | F50: =AU!Q106 -> 0 | H50: =AU!T106 -> 0 | J50: =AU!W106 -> 0 | L50: =AU!Z106 -> 0 | N50: =AU!AC106 -> 0 | P50: =AU!AF106 -> 0 | R50: =AU!AI106 -> 0 | T50: =AU!AL106 -> 0 | V50: =AU!AO106 -> 0
... B54: =AU!C110 -> - | C54: =IF(AU!F110="","",AU!F110) | D54: =AU!N110 -> 0 | F54: =AU!Q110 -> 0 | H54: =AU!T110 -> 0 | J54: =AU!W110 -> 0 | L54: =AU!Z110 -> 0 | N54: =AU!AC110 -> 0 | P54: =AU!AF110 -> 0 | R54: =AU!AI110 -> 0 | T54: =AU!AL110 -> 0 | V54: =AU!AO110 -> 0
B55: =AU!C120 -> Bench fee | C55: =IF(AU!J120="","",AU!J120) | D55: =AU!N120 -> 0 | F55: =AU!Q120 -> 0 | H55: =AU!T120 -> 0 | J55: =AU!W120 -> 0 | L55: =AU!Z120 -> 0 | N55: =AU!AC120 -> 0 | P55: =AU!AF120 -> 0 | R55: =AU!AI120 -> 0 | T55: =AU!AL120 -> 0 | V55: =AU!AO120 -> 0
A56: 3. | B56: Dissemination, training, education
B57: =AU!C112 -> Conference participation | C57: =IF(AU!F112="","",AU!F112) | D57: =AU!N112 -> 15000 | F57: =AU!Q112 -> 15000 | H57: =AU!T112 -> 15000 | J57: =AU!W112 -> 15000 | L57: =AU!Z112 -> 15000 | N57: =AU!AC112 -> 5000 | P57: =AU!AF112 -> 0 | R57: =AU!AI112 -> 0 | T57: =AU!AL112 -> 0 | V57: =AU!AO112 -> 0
B58: =AU!C113 -> Travel | C58: =IF(AU!F113="","",AU!F113) | D58: =AU!N113 -> 20000 | F58: =AU!Q113 -> 20000 | H58: =AU!T113 -> 20000 | J58: =AU!W113 -> 20000 | L58: =AU!Z113 -> 20000 | N58: =AU!AC113 -> 20000 | P58: =AU!AF113 -> 0 | R58: =AU!AI113 -> 0 | T58: =AU!AL113 -> 0 | V58: =AU!AO113 -> 0
B59: =AU!C114 -> Publication costs | C59: =IF(AU!F114="","",AU!F114) | D59: =AU!N114 -> 0 | F59: =AU!Q114 -> 25000 | H59: =AU!T114 -> 25000 | J59: =AU!W114 -> 25000 | L59: =AU!Z114 -> 25000 | N59: =AU!AC114 -> 25000 | P59: =AU!AF114 -> 0 | R59: =AU!AI114 -> 0 | T59: =AU!AL114 -> 0 | V59: =AU!AO114 -> 0
B60: =AU!C115 -> Travel | C60: =IF(AU!F115="","",AU!F115) -> PhD research stay abroad | D60: =AU!N115 -> 0 | F60: =AU!Q115 -> 0 | H60: =AU!T115 -> 30000 | J60: =AU!W115 -> 0 | L60: =AU!Z115 -> 30000 | N60: =AU!AC115 -> 0 | P60: =AU!AF115 -> 0 | R60: =AU!AI115 -> 0 | T60: =AU!AL115 -> 0 | V60: =AU!AO115 -> 0
B61: =AU!C116 -> - | C61: =IF(AU!F116="","",AU!F116) | D61: =AU!N116 -> 0 | F61: =AU!Q116 -> 0 | H61: =AU!T116 -> 0 | J61: =AU!W116 -> 0 | L61: =AU!Z116 -> 0 | N61: =AU!AC116 -> 0 | P61: =AU!AF116 -> 0 | R61: =AU!AI116 -> 0 | T61: =AU!AL116 -> 0 | V61: =AU!AO116 -> 0
B62: =AU!C117 -> - | C62: =IF(AU!F117="","",AU!F117) | D62: =AU!N117 -> 0 | F62: =AU!Q117 -> 0 | H62: =AU!T117 -> 0 | J62: =AU!W117 -> 0 | L62: =AU!Z117 -> 0 | N62: =AU!AC117 -> 0 | P62: =AU!AF117 -> 0 | R62: =AU!AI117 -> 0 | T62: =AU!AL117 -> 0 | V62: =AU!AO117 -> 0
B63: =AU!C118 -> - | C63: =IF(AU!F118="","",AU!F118) | D63: =AU!N118 -> 0 | F63: =AU!Q118 -> 0 | H63: =AU!T118 -> 0 | J63: =AU!W118 -> 0 | L63: =AU!Z118 -> 0 | N63: =AU!AC118 -> 0 | P63: =AU!AF118 -> 0 | R63: =AU!AI118 -> 0 | T63: =AU!AL118 -> 0 | V63: =AU!AO118 -> 0
B64: =AU!C119 -> Tuition fee | C64: =IF(AU!F119="","",AU!F119) | D64: =AU!N119 -> 40000 | F64: =AU!Q119 -> 80000 | H64: =AU!T119 -> 120000 | J64: =AU!W119 -> 120000 | L64: =AU!Z119 -> 80000 | N64: =AU!AC119 -> 40000 | P64: =AU!AF119 -> 0 | R64: =AU!AI119 -> 0 | T64: =AU!AL119 -> 0 | V64: =AU!AO119 -> 0
A65: 2. | B65: Project supplement
B66: Project supplement | D66: =AU!N155 -> 375000 | F66: =AU!Q155 -> 750000 | H66: =AU!T155 -> 1000000 | J66: =AU!W155 -> 875000 | L66: =AU!Z155 -> 500000 | N66: =AU!AC155 -> 250000 | P66: =AU!AF155 -> 0 | R66: =AU!AI155 -> 0 | T66: =AU!AL155 -> 0 | V66: =AU!AO155 -> 0
A67: 4. | B67: Administration
B68: Direct administrative expenses | D68: =AU!N156 -> 0 | F68: =AU!Q156 -> 0 | H68: =AU!T156 -> 0 | J68: =AU!W156 -> 0 | L68: =AU!Z156 -> 0 | N68: =AU!AC156 -> 0 | P68: =AU!AF156 -> 0 | R68: =AU!AI156 -> 0 | T68: =AU!AL156 -> 0 | V68: =AU!AO156 -> 0
A69: Total | C69: =SUM(D69:W69) -> 15379210 | D69: =SUM(D5:D68) -> 1579348.4 | F69: =SUM(F5:F68) -> 3004457.7 | H69: =SUM(H5:H68) -> 4016678.4 | J69: =SUM(J5:J68) -> 3438185.2 | L69: =SUM(L5:L68) -> 2166891 | N69: =SUM(N5:N68) -> 1173648.9 | P69: =SUM(P5:P68) -> 0 | R69: =SUM(R5:R68) -> 0 | T69: =SUM(T5:T68) -> 0 | V69: =SUM(V5:V68) -> 0
B72: Received from the administering institution
A73: Total | C73: =SUM(D73:W73) -> 0 | D73: =AU!N164 -> 0 | F73: =AU!Q164 -> 0 | H73: =AU!T164 -> 0 | J73: =AU!W164 -> 0 | L73: =AU!Z164 -> 0 | N73: =AU!AC164 -> 0 | P73: =AU!AF164 -> 0 | R73: =AU!AI164 -> 0 | T73: =AU!AL164 -> 0 | V73: =AU!AO164 -> 0

Sheet AU salary costs 2025
A1: Source: | B1: 2025_-_Takstkatalog_baseret_paa_ressourcekostpriser.pdf
A2: and: | B2: Loensatser_pr._01.11.2025.pdf
B3: Average monthly (37 hr/week) salary cost prices 2025 | G3: Converted to employment of | I3: 15 | J3: hours per week
B5: Position | C5: Low | D5: Mean | E5: High | H5: Stillingstype | I5: Low | J5: Mean | K5: High
B6: VIP employed | H6: VIP employed
A7: 111 | B7: Professor | C7: 78000 | D7: 85000 | E7: 88000 | G7: 111 | H7: Professor | I7: =C7*($I$3/37) -> 31621.622 | J7: =D7*($I$3/37) -> 34459.459 | K7: =E7*($I$3/37) -> 35675.676
A8: 114 | B8: Professor (MSO) | C8: 74000 | D8: 76000 | E8: 77000 | G8: 114 | H8: Professor (MSO) | I8: =C8*($I$3/37) -> 30000 | J8: =D8*($I$3/37) -> 30810.811 | K8: =E8*($I$3/37) -> 31216.216
A9: 121 | B9: Associate Professor | C9: 63000 | D9: 68000 | E9: 70000 | G9: 121 | H9: Associate Professor | I9: =C9*($I$3/37) -> 25540.541 | J9: =D9*($I$3/37) -> 27567.568 | K9: =E9*($I$3/37) -> 28378.378
A10: 124 | B10: Senior Researcher | C10: 57000 | D10: 64000 | E10: 68000 | G10: 124 | H10: Senior Researcher | I10: =C10*($I$3/37) -> 23108.108 | J10: =D10*($I$3/37) -> 25945.946 | K10: =E10*($I$3/37) -> 27567.568
A11: 131 | B11: Assistant Professor | C11: 52000 | D11: 54000 | E11: 55000 | G11: 131 | H11: Assistant Professor | I11: =C11*($I$3/37) -> 21081.081 | J11: =D11*($I$3/37) -> 21891.892 | K11: =E11*($I$3/37) -> 22297.297
A12: 137 | B12: Postdoc | C12: 52000 | D12: 52000 | E12: 53000 | G12: 137 | H12: Postdoc | I12: =C12*($I$3/37) -> 21081.081 | J12: =D12*($I$3/37) -> 21081.081 | K12: =E12*($I$3/37) -> 21486.486
A13: 154 | B13: Research Assistant | C13: 42000 | D13: 46000 | E13: 50000 | G13: 154 | H13: Research Assistant | I13: =C13*($I$3/37) -> 17027.027 | J13: =D13*($I$3/37) -> 18648.649 | K13: =E13*($I$3/37) -> 20270.27
A14: 212 | B14: PhD Student | C14: 39000 | D14: 42000 | E14: 44000 | G14: 212 | H14: PhD Student | I14: =C14*($I$3/37) -> 15810.811 | J14: =D14*($I$3/37) -> 17027.027 | K14: =E14*($I$3/37) -> 17837.838
B15: PhD Student 4+4 Part A | C15: 19500 | D15: 21000 | E15: 22000 | I15: =C15*($I$3/37) -> 7905.4054 | J15: =D15*($I$3/37) -> 8513.5135 | K15: =E15*($I$3/37) -> 8918.9189
B16: PhD Student 4+4 Part B | C16: 39000 | D16: 42000 | E16: 44000 | I16: =C16*($I$3/37) -> 15810.811 | J16: =D16*($I$3/37) -> 17027.027 | K16: =E16*($I$3/37) -> 17837.838
B17: TAP employed | H17: TAP employed
A18: 421 | B18: Special Consultant | C18: 60000 | D18: 64000 | E18: 67000 | G18: 421 | H18: Special Consultant | I18: =C18*($I$3/37) -> 24324.324 | J18: =D18*($I$3/37) -> 25945.946 | K18: =E18*($I$3/37) -> 27162.162
A19: 422 | B19: AC-Administrative officer | C19: 49000 | D19: 53000 | E19: 57000 | G19: 422 | H19: AC-fuldmægtig | I19: =C19*($I$3/37) -> 19864.865 | J19: =D19*($I$3/37) -> 21486.486 | K19: =E19*($I$3/37) -> 23108.108
A20: 431 | B20: Office staff et al. | C20: 40000 | D20: 45000 | E20: 49000 | G20: 431 | H20: Kontor m.fl. | I20: =C20*($I$3/37) -> 16216.216 | J20: =D20*($I$3/37) -> 18243.243 | K20: =E20*($I$3/37) -> 19864.865
A21: 451 | B21: AC staff et al. | C21: 49000 | D21: 52000 | E21: 57000 | G21: 451 | H21: AC-personale m.fl. | I21: =C21*($I$3/37) -> 19864.865 | J21: =D21*($I$3/37) -> 21081.081 | K21: =E21*($I$3/37) -> 23108.108
A22: 461 | B22: Technician | C22: 46000 | D22: 50000 | E22: 54000 | G22: 461 | H22: Technician | I22: =C22*($I$3/37) -> 18648.649 | J22: =D22*($I$3/37) -> 20270.27 | K22: =E22*($I$3/37) -> 21891.892
A23: 465 | B23: Lab. technician | C23: 40000 | D23: 44000 | E23: 47000 | G23: 465 | H23: Lab. Technician | I23: =C23*($I$3/37) -> 16216.216 | J23: =D23*($I$3/37) -> 17837.838 | K23: =E23*($I$3/37) -> 19054.054
A24: 466 | B24: IT staff | C24: 39000 | D24: 48000 | E24: 55000 | G24: 466 | H24: IT Assistant | I24: =C24*($I$3/37) -> 15810.811 | J24: =D24*($I$3/37) -> 19459.459 | K24: =E24*($I$3/37) -> 22297.297
A25: 521 | B25: Student Programmer | C25: =181.89*160.33 -> 29162.424 | D25: =181.89*160.33 -> 29162.424 | E25: =181.89*160.33 -> 29162.424 | F25: PROSA | G25: 521 | H25: Student Programmer | I25: =C25*($I$3/37) -> 11822.604 | J25: =D25*($I$3/37) -> 11822.604 | K25: =E25*($I$3/37) -> 11822.604
A26: 512 | B26: Student Assistant | C26: =214.9*160.33 -> 34454.917 | D26: =214.9*160.33 -> 34454.917 | E26: =214.9*160.33 -> 34454.917 | G26: 512 | H26: Student Assistant | I26: =C26*($I$3/37) -> 13968.21 | J26: =D26*($I$3/37) -> 13968.21 | K26: =E26*($I$3/37) -> 13968.21
B28: Other with project supplement (VIP Group C) | D28: Type in salary
B29: Other without project supplement | D29: Type in salary
B30: Project employed group leader (project supplement) | D30: Type in salary
B31: Other | D31: Type in salary
B32: PhD Student 4+4 Part A project supplement | D32: 21000
B33: PhD Student 4+4 Part A no project supplement | D33: 21000
B34: PhD Student 4+4 Part B project supplement | D34: 42000
B35: PhD Student 4+4 Part B no project supplement | D35: 42000

Sheet Lists
A1: Institution | C1: Faculty | I1: Wet/dry dependencies | L1: Yes/No | N1: Staff category (VIP) | Q1: Project costs (B) | S1: P/L | U1: Kategorisering af budgetpost | W1: Foundation - drop down | X1: OH (%) | Y1: OH term | Z1: Bench fee | AB1: FTE Hours
A2: CBS | C2: - | D2: Wet'/'Dry' | E2: Project supplement ('wet'/'dry') | F2: Tuition fee | G2: DFF tuition fee | J2: Project supplement | L2: - | N2: - | O2: Applicable for project supplement? (0 = No, 1 = Yes) | Q2: - | S2: 0 | U2: Foundation | W2: Carlsberg | Y2: Indirect costs | AB2: 1924
A3: ITU | C3: Natural Sciences | D3: Wet | E3: =_xlfn.XLOOKUP($D3,$I:$I,J:J) -> 250000 | F3: 80000 | G3: 120000 | I3: Wet | J3: 250000 | L3: Yes | N3: Professor | O3: 0 | Q3: Equipment | S3: 0.01 | U3: Foundation AND "inddækning" | W3: Leo | Y3: Indirect costs | AB3: 1642
A4: RUC | C4: Technical Sciences | D4: Wet | E4: =_xlfn.XLOOKUP($D4,$I:$I,J:J) -> 250000 | F4: 80000 | G4: 120000 | I4: Dry | J4: 200000 | L4: No | N4: Professor (MSO) | O4: 0 | Q4: Consumables | S4: 0.02 | U4: Co-financing | W4: Lundbeck | Y4: Indirect costs | AB4: 1500
A5: DTU | C5: Health | D5: Wet | E5: =_xlfn.XLOOKUP($D5,$I:$I,J:J) -> 250000 | F5: 40000 | G5: 40000 | N5: Associate Professor | O5: 0 | Q5: Travel expenses | S5: 0.03 | W5: Novo Nordisk | Y5: Administrative expenses | Z5: 8000
A6: UCPH | C6: Arts | D6: Dry | E6: =_xlfn.XLOOKUP($D6,$I:$I,J:J) -> 200000 | F6: 104200 | G6: 75000 | N6: Senior Researcher | O6: 0 | Q6: Research stays | S6: 0.04 | W6: Novo Nordisk no proj. suppl. | X6: 0.05 | Y6: Administrative expenses | Z6: 8000
A7: SDU | C7: BSS | D7: Dry | E7: =_xlfn.XLOOKUP($D7,$I:$I,J:J) -> 200000 | F7: 104200 | G7: 75000 | N7: Assistant Professor | O7: 0 | Q7: Conference participation | S7: 0.05 | W7: Tryg | Y7: Indirect costs
A8: AAU | C8: Scientific Area | N8: Postdoc | O8: 1 | Q8: Dissemination | S8: 0.06 | W8: Velux | Y8: Indirect costs
A9: AU | C9: - | E9: 0 | N9: Research Assistant | O9: 1 | Q9: Arranging conferences/seminars/workshops | S9: 0.07 | W9: Villum | Y9: Indirect costs
A10: Other (write name here) | C10: Natural Sciences | D10: Wet | E10: =_xlfn.XLOOKUP($D10,$I:$I,J:J) -> 250000 | N10: PhD Student | O10: 1 | Q10: Publication | S10: 0.08 | W10: DFF | X10: 0.44 | Y10: Overhead percentage
C11: Technical Sciences | D11: Wet | E11: =_xlfn.XLOOKUP($D11,$I:$I,J:J) -> 250000 | N11: PhD Student 4+4 Part A project supplement | O11: 1 | Q11: Data management | S11: 0.09 | W11: IFD | X11: 0.44 | Y11: Overhead percentage
C12: Health | D12: Wet | E12: =_xlfn.XLOOKUP($D12,$I:$I,J:J) -> 250000 | N12: PhD Student 4+4 Part A no project supplement | O12: 0 | Q12: Fee for service (core facility) | S12: 0.1 | W12: DG | X12: 0.44 | Y12: Overhead percentage
C13: Humanities | D13: Dry | E13: =_xlfn.XLOOKUP($D13,$I:$I,J:J) -> 200000 | N13: PhD Student 4+4 Part B project supplement | O13: 1 | Q13: Other | W13: Spar Nord | Y13: Indirect costs
C14: Social Sciences | D14: Dry | E14: =_xlfn.XLOOKUP($D14,$I:$I,J:J) -> 200000 | N14: PhD Student 4+4 Part B no project supplement | O14: 0 | W14: Other | Y14: Overhead percentage
C15: Theology | D15: Dry | E15: =_xlfn.XLOOKUP($D15,$I:$I,J:J) -> 200000 | N15: Project employed group leader (project supplement) | O15: 1 | Q15: NNF | W15: Other w/ proj. suppl. | Y15: Indirect costs
C16: Law | D16: Dry | E16: =_xlfn.XLOOKUP($D16,$I:$I,J:J) -> 200000 | N16: Other with project supplement (VIP Group C) | O16: 1 | Q16: Operation
N17: Other without project supplement | O17: 0 | Q17: - | W17: Project Supplement foundations
Q18: Equipment | W18: Carlsberg
C19: Natural Sciences | D19: Technical Sciences | E19: Health | F19: Arts | G19: BSS | H19: Other | N19: Staff category (TAP) | Q19: Data management | W19: Leo
C20: BIO | D20: AGRO | E20: Biomedicine | F20: Communication and Culture | G20: Business Development and Technology | O20: =O2 -> Applicable for project supplement? (0 = No, 1 = Yes) | Q20: Operating expenses | W20: Lundbeck
C21: CHEM | D21: ANIVET | E21: Clinical Medicine | F21: Culture and Society | G21: Economics and Business Economics | N21: - | W21: Novo Nordisk
C22: CS | D22: BCE | E22: Dentistry and Oral Health | F22: Danish School of Education | G22: Law | N22: Special Consultant | O22: 0 | Q22: Dissemination, training, education | W22: Tryg
C23: GEO | D23: CAE | E23: Forensic Medicine | G23: Management | N23: AC-Administrative officer | O23: 0 | Q23: - | W23: Velux
C24: iNANO | D24: DCA | E24: Public Health | G24: Political Science | N24: Office staff et al. | O24: 0 | Q24: Conference participation | W24: Villum
C25: MATH | D25: DCE | G25: Psychology and Behavioural Sciences | N25: AC staff et al. | O25: 0 | Q25: Publication costs | W25: Spar Nord
C26: MBG | D26: ECE | N26: Technician | O26: 0 | Q26: Travel | W26: Other w/ proj. suppl.
C27: PHYS | D27: ECOS | N27: Lab. technician | O27: 0
D28: ENVS | N28: IT staff | O28: 0
D29: FOOD | N29: Student Programmer | O29: 0
D30: ICROFS | N30: Student Assistant | O30: 0
D31: MPE | N31: Other | O31: 0
D32: QGG
N33: Co-financing staff category (VIP)
N34: -
C35: Natural Sciences AU | D35: Wet/Dry | E35: Bench fee Nat | N35: Professor
C36: BIO | D36: Wet | E36: 28140 | N36: Professor (MSO)
C37: CHEM | D37: Wet | E37: 28140 | N37: Associate Professor
C38: CS | D38: Dry | E38: 10995 | N38: Senior Researcher
C39: GEO | D39: Wet | E39: 28140 | N39: Assistant Professor
C40: iNANO | D40: Wet | E40: 28140 | N40: Postdoc
C41: MATH | D41: Dry | E41: 10995 | N41: Research Assistant
C42: MBG | D42: Wet | E42: 28140 | N42: PhD Student
C43: PHYS | D43: Dry | E43: 28140 | N43: PhD Student 4+4 Part A
N44: PhD Student 4+4 Part B
N45: Other
